Workbook

Sheet Distruibuição de aporte
A1: Aporte total | B1: =H15 -> 12000 | C1: =B1+G13 -> 255783.45
A2: Tipo de ativo | B2: Porcentagem desejada | C2: Proporção ajustada | D2: Diferença | E2: Condição | F2: % Atual | G2: Valor atual | H2: Aporte por ativo | I2: Valor após aportes
A3: Reserva de investimento | B3: 0.05 | C3: =IF(E3=1,D3/D13,0) -> 0.096234904 | D3: =IF(E3=1,C1*B3-G3,0) -> 12789.163 | E3: =IF(B3>G3/C1,1,0) -> 1 | F3: =G3/G13 -> 4.1020011e-08 | G3: ='RI, RV e RF'!F42 -> 0.01 | H3: =IF(G3/C1>B3,C1*B3-G3,C3*B1) -> 1154.8188 | I3: =G3+H3 -> 1154.8288 | J3: =I3/C1 -> 0.0045148692
A4: Reserva de valor | B4: 0.05 | C4: =IF(E4=1,D4/D13,0) -> 0.081239727 | D4: =IF(E4=1,C1*B4-G4,0) -> 10796.375 | E4: =IF(B4>G4/C1,1,0) -> 1 | F4: =G4/G13 -> 0.0081744593 | G4: ='RI, RV e RF'!F43 -> 1992.7979 | H4: =IF(H3>0,C4*B1,C4*(B1-H3)) -> 974.87673 | I4: =G4+H4 -> 2967.6747 | J4: =I4/C1 -> 0.011602293
A5: Renda fixa BR | B5: 0.1 | C5: =IF(E5=1,D5/D13,0) -> 0.095408334 | D5: =IF(E5=1,C1*B5-G5,0) -> 12679.315 | E5: =IF(B5>G5/C1,1,0) -> 1 | F5: =G5/G13 -> 0.052911835 | G5: ='RI, RV e RF'!F44 -> 12899.03 | H5: =IF(H3>0,C5*B1,C5*(B1-H3)) -> 1144.9 | I5: =G5+H5 -> 14043.93 | J5: =I5/C1 -> 0.054905545
A6: FIIs | B6: 0.15 | C6: =IF(E6=1,D6/D13,0) -> 0 | D6: =IF(E6=1,C1*B6-G6,0) -> 0 | E6: =IF(B6>G6/C1,1,0) -> 0 | F6: =G6/G13 -> 0.6532961 | G6: =FII!F23 -> 159262.78 | H6: =IF(H3>0,C6*B1,C6*(B1-H3)) -> 0 | I6: =G6+H6 -> 159262.78 | J6: =I6/C1 -> 0.62264692
A7: Ações BR | B7: 0.35 | C7: =IF(E7=1,D7/D13,0) -> 0.36904235 | D7: =IF(E7=1,C1*B7-G7,0) -> 49043.979 | E7: =IF(B7>G7/C1,1,0) -> 1 | F7: =G7/G13 -> 0.16604995 | G7: ='Ações'!E102 -> 40480.23 | H7: =IF(H3>0,C7*B1,C7*(B1-H3)) -> 4428.5082 | I7: =G7+H7 -> 44908.738 | J7: =I7/C1 -> 0.17557327
A8: Ações US | B8: 0.1 | C8: =IF(E8=1,D8/D13,0) -> 0.12050918 | D8: =IF(E8=1,C1*B8-G8,0) -> 16015.099 | E8: =IF(B8>G8/C1,1,0) -> 1 | F8: =G8/G13 -> 0.039228449 | G8: =Exterior!H42 -> 9563.2469 | H8: =IF(H3>0,C8*B1,C8*(B1-H3)) -> 1446.1101 | I8: =G8+H8 -> 11009.357 | J8: =I8/C1 -> 0.043041709
A9: REITs | B9: 0.05 | C9: =IF(E9=1,D9/D13,0) -> 0.061962672 | D9: =IF(E9=1,C1*B9-G9,0) -> 8234.5455 | E9: =IF(B9>G9/C1,1,0) -> 1 | F9: =G9/G13 -> 0.018683086 | G9: =Exterior!H43 -> 4554.6272 | H9: =IF(H3>0,C9*B1,C9*(B1-H3)) -> 743.55207 | I9: =G9+H9 -> 5298.1793 | J9: =I9/C1 -> 0.020713534
A10: Renda fixa no exterior | B10: 0.05 | C10: =IF(E10=1,D10/D13,0) -> 0.058949277 | D10: =IF(E10=1,C1*B10-G10,0) -> 7834.0795 | E10: =IF(B10>G10/C1,1,0) -> 1 | F10: =G10/G13 -> 0.020325798 | G10: =Exterior!H44 -> 4955.0932 | H10: =IF(H3>0,C10*B1,C10*(B1-H3)) -> 707.39132 | I10: =G10+H10 -> 5662.4845 | J10: =I10/C1 -> 0.022137806
A11: Ações Europa | B11: 0.05 | C11: =IF(E11=1,D11/D13,0) -> 0.059711567 | D11: =IF(E11=1,C1*B11-G11,0) -> 7935.3844 | E11: =IF(B11>G11/C1,1,0) -> 1 | F11: =G11/G13 -> 0.019910245 | G11: =Exterior!H45 -> 4853.7884 | H11: =IF(H3>0,C11*B1,C11*(B1-H3)) -> 716.53881 | I11: =G11+H11 -> 5570.3272 | J11: =I11/C1 -> 0.021777512
A12: Ações Asia | B12: 0.05 | C12: =IF(E12=1,D12/D13,0) -> 0.056941996 | D12: =IF(E12=1,C1*B12-G12,0) -> 7567.3215 | E12: =IF(B12>G12/C1,1,0) -> 1 | F12: =G12/G13 -> 0.02142004 | G12: =Exterior!H46 -> 5221.8513 | H12: =IF(H3>0,C12*B1,C12*(B1-H3)) -> 683.30395 | I12: =G12+H12 -> 5905.1552 | J12: =I12/C1 -> 0.023086541
A13: Soma: | B13: =SUM(B3:B12) -> 1 | C13: =SUM(C3:C12) -> 1 | D13: =SUM(D3:D12) -> 132895.26 | F13: =SUM(F3:F12) -> 1 | G13: =SUM(G3:G12) -> 243783.45 | H13: =SUM(H3:H12) -> 12000 | I13: =SUM(I3:I12) -> 255783.45 | J13: =SUM(J3:J12) -> 1
A15: Aporte | B15: 12000 | F15: =G13+B15 -> 255783.45 | H15: =SUM(H16,B15) -> 12000 | J15: =J16/2 -> 159696.61
B16: 12084.15 | F16: =B16-B17 -> 0 | G16: =I16*B16 -> 63609.757 | H16: =IF(G16/F15<1,0,J15-F15) -> 0 | I16: =IFERROR(__xludf.DUMMYFUNCTION("GOOGLEFINANCE(""CURRENCY:USDBRL"")"),5.2639) -> 5.2639 | J16: =SUM(G16,G13,B15) -> 319393.21
B17: =(G16-H16)/I16 -> 12084.15 | G17: =I16*B17 -> 63609.757

Sheet RI, RV e RF
B1: Ativo | C1: Setor | D1: Quantidade | E1: Cotação | F1: Saldo | G1: %Carteira | H1: %C/aporte | I1: % Ideal | J1: Bal | K1: Bal | M1: Aporte: | N1: =SUM(D42:D46) -> 3274.5956 | O1: Aporte ideal por ativo | P1: % após aport
A2: 1 | B2: ROMP | D2: 0.01 | E2: 1 | F2: =D2*E2 -> 0.01 | G2: =IFS(L2="Grupo 0",0,L2="Grupo 1",F2/F42,L2="Grupo 2",F2/F43,L2="Grupo 3",F2/F44,L2="Grupo 4",F2/F45,L2="Grupo 5",F2/F46) -> 1 | H2: =IFS(L2="Grupo 0",0,L2="Grupo 1",F2/E42,L2="Grupo 2",F2/E43,L2="Grupo 3",F2/E44,L2="Grupo 4",F2/E45,L2="Grupo 5",F2/E46) -> 8.6592918e-06 | I2: =IFS(L2="Grupo 0",0,L2="Grupo 1",M2/M42,L2="Grupo 2",M2/M43,L2="Grupo 3",M2/M44,L2="Grupo 4",M2/M45,L2="Grupo 5",M2/M46) -> 1 | J2: =IFS(L2="Grupo 0",0,L2="Grupo 1",K2/K42,L2="Grupo 2",K2/K43,L2="Grupo 3",K2/K44,L2="Grupo 4",K2/K45,L2="Grupo 5",K2/K46) -> 1 | K2: =IFS(L2="Grupo 0",0,L2="Grupo 1",(E42*I2-F2)*N2,L2="Grupo 2",(E43*I2-F2)*N2,L2="Grupo 3",(E44*I2-F2)*N2,L2="Grupo 4",(E45*I2-F2)*N2,L2="Grupo 5",(E46*I2-F2)*N2) -> 1154.8188 | L2: Grupo 1 | M2: 5 | N2: =IF(I2<H2,0,1) -> 1 | O2: =IFS(L2="Grupo 0",0,L2="Grupo 1",J2*D42,L2="Grupo 2",J2*D43,L2="Grupo 3",J2*D44,L2="Grupo 4",J2*D45,L2="Grupo 5",J2*D46) -> 1154.8188 | P2: =(F2+O2)/D41 -> 0.063569376
A3: 2 | F3: =D3*E3 -> 0 | G3: =IFS(L3="Grupo 0",0,L3="Grupo 1",F3/F42,L3="Grupo 2",F3/F43,L3="Grupo 3",F3/F44,L3="Grupo 4",F3/F45,L3="Grupo 5",F3/F46) -> 0 | H3: =IFS(L3="Grupo 0",0,L3="Grupo 1",F3/E42,L3="Grupo 2",F3/E43,L3="Grupo 3",F3/E44,L3="Grupo 4",F3/E45,L3="Grupo 5",F3/E46) -> 0 | I3: =IFS(L3="Grupo 0",0,L3="Grupo 1",M3/M42,L3="Grupo 2",M3/M43,L3="Grupo 3",M3/M44,L3="Grupo 4",M3/M45,L3="Grupo 5",M3/M46) -> 0 | J3: =IFS(L3="Grupo 0",0,L3="Grupo 1",K3/K42,L3="Grupo 2",K3/K43,L3="Grupo 3",K3/K44,L3="Grupo 4",K3/K45,L3="Grupo 5",K3/K46) -> 0 | K3: =IFS(L3="Grupo 0",0,L3="Grupo 1",(E42*I3-F3)*N3,L3="Grupo 2",(E43*I3-F3)*N3,L3="Grupo 3",(E44*I3-F3)*N3,L3="Grupo 4",(E45*I3-F3)*N3,L3="Grupo 5",(E46*I3-F3)*N3) -> 0 | L3: Grupo 0 | M3: 1 | N3: =IF(I3<H3,0,1) -> 1 | O3: =IFS(L3="Grupo 0",0,L3="Grupo 1",J3*D42,L3="Grupo 2",J3*D43,L3="Grupo 3",J3*D44,L3="Grupo 4",J3*D45,L3="Grupo 5",J3*D46) -> 0 | P3: =(F3+O3)/D41 -> 0
A4: 3 | F4: =D4*E4 -> 0 | G4: =IFS(L4="Grupo 0",0,L4="Grupo 1",F4/F42,L4="Grupo 2",F4/F43,L4="Grupo 3",F4/F44,L4="Grupo 4",F4/F45,L4="Grupo 5",F4/F46) -> 0 | H4: =IFS(L4="Grupo 0",0,L4="Grupo 1",F4/E42,L4="Grupo 2",F4/E43,L4="Grupo 3",F4/E44,L4="Grupo 4",F4/E45,L4="Grupo 5",F4/E46) -> 0 | I4: =IFS(L4="Grupo 0",0,L4="Grupo 1",M4/M42,L4="Grupo 2",M4/M43,L4="Grupo 3",M4/M44,L4="Grupo 4",M4/M45,L4="Grupo 5",M4/M46) -> 0 | J4: =IFS(L4="Grupo 0",0,L4="Grupo 1",K4/K42,L4="Grupo 2",K4/K43,L4="Grupo 3",K4/K44,L4="Grupo 4",K4/K45,L4="Grupo 5",K4/K46) -> 0 | K4: =IFS(L4="Grupo 0",0,L4="Grupo 1",(E42*I4-F4)*N4,L4="Grupo 2",(E43*I4-F4)*N4,L4="Grupo 3",(E44*I4-F4)*N4,L4="Grupo 4",(E45*I4-F4)*N4,L4="Grupo 5",(E46*I4-F4)*N4) -> 0 | L4: Grupo 0 | M4: 10 | N4: =IF(I4<H4,0,1) -> 1 | O4: =IFS(L4="Grupo 0",0,L4="Grupo 1",J4*D42,L4="Grupo 2",J4*D43,L4="Grupo 3",J4*D44,L4="Grupo 4",J4*D45,L4="Grupo 5",J4*D46) -> 0 | P4: =(F4+O4)/D41 -> 0
A5: 4 | F5: =D5*E5 -> 0 | G5: =IFS(L5="Grupo 0",0,L5="Grupo 1",F5/F42,L5="Grupo 2",F5/F43,L5="Grupo 3",F5/F44,L5="Grupo 4",F5/F45,L5="Grupo 5",F5/F46) -> 0 | H5: =IFS(L5="Grupo 0",0,L5="Grupo 1",F5/E42,L5="Grupo 2",F5/E43,L5="Grupo 3",F5/E44,L5="Grupo 4",F5/E45,L5="Grupo 5",F5/E46) -> 0 | I5: =IFS(L5="Grupo 0",0,L5="Grupo 1",M5/M42,L5="Grupo 2",M5/M43,L5="Grupo 3",M5/M44,L5="Grupo 4",M5/M45,L5="Grupo 5",M5/M46) -> 0 | J5: =IFS(L5="Grupo 0",0,L5="Grupo 1",K5/K42,L5="Grupo 2",K5/K43,L5="Grupo 3",K5/K44,L5="Grupo 4",K5/K45,L5="Grupo 5",K5/K46) -> 0 | K5: =IFS(L5="Grupo 0",0,L5="Grupo 1",(E42*I5-F5)*N5,L5="Grupo 2",(E43*I5-F5)*N5,L5="Grupo 3",(E44*I5-F5)*N5,L5="Grupo 4",(E45*I5-F5)*N5,L5="Grupo 5",(E46*I5-F5)*N5) -> 0 | L5: Grupo 0 | M5: 1 | N5: =IF(I5<H5,0,1) -> 1 | O5: =IFS(L5="Grupo 0",0,L5="Grupo 1",J5*D42,L5="Grupo 2",J5*D43,L5="Grupo 3",J5*D44,L5="Grupo 4",J5*D45,L5="Grupo 5",J5*D46) -> 0 | P5: =(F5+O5)/D41 -> 0
A6: 5 | B6: Tesouro IPCA | D6: 3102.81 | E6: 1 | F6: =D6*E6 -> 3102.81 | G6: =IFS(L6="Grupo 0",0,L6="Grupo 1",F6/F42,L6="Grupo 2",F6/F43,L6="Grupo 3",F6/F44,L6="Grupo 4",F6/F45,L6="Grupo 5",F6/F46) -> 0.24054599 | H6: =IFS(L6="Grupo 0",0,L6="Grupo 1",F6/E42,L6="Grupo 2",F6/E43,L6="Grupo 3",F6/E44,L6="Grupo 4",F6/E45,L6="Grupo 5",F6/E46) -> 0.22093602 | I6: =IFS(L6="Grupo 0",0,L6="Grupo 1",M6/M42,L6="Grupo 2",M6/M43,L6="Grupo 3",M6/M44,L6="Grupo 4",M6/M45,L6="Grupo 5",M6/M46) -> 0.5 | J6: =IFS(L6="Grupo 0",0,L6="Grupo 1",K6/K42,L6="Grupo 2",K6/K43,L6="Grupo 3",K6/K44,L6="Grupo 4",K6/K45,L6="Grupo 5",K6/K46) -> 1 | K6: =IFS(L6="Grupo 0",0,L6="Grupo 1",(E42*I6-F6)*N6,L6="Grupo 2",(E43*I6-F6)*N6,L6="Grupo 3",(E44*I6-F6)*N6,L6="Grupo 4",(E45*I6-F6)*N6,L6="Grupo 5",(E46*I6-F6)*N6) -> 3919.155 | L6: Grupo 3 | M6: 10 | N6: =IF(I6<H6,0,1) -> 1 | O6: =IFS(L6="Grupo 0",0,L6="Grupo 1",J6*D42,L6="Grupo 2",J6*D43,L6="Grupo 3",J6*D44,L6="Grupo 4",J6*D45,L6="Grupo 5",J6*D46) -> 1144.9 | P6: =(F6+O6)/D41 -> 0.2338219
A7: 6 | B7: CDB, LCA, ETC | D7: 9796.22 | E7: 1 | F7: =D7*E7 -> 9796.22 | G7: =IFS(L7="Grupo 0",0,L7="Grupo 1",F7/F42,L7="Grupo 2",F7/F43,L7="Grupo 3",F7/F44,L7="Grupo 4",F7/F45,L7="Grupo 5",F7/F46) -> 0.75945401 | H7: =IFS(L7="Grupo 0",0,L7="Grupo 1",F7/E42,L7="Grupo 2",F7/E43,L7="Grupo 3",F7/E44,L7="Grupo 4",F7/E45,L7="Grupo 5",F7/E46) -> 0.69754122 | I7: =IFS(L7="Grupo 0",0,L7="Grupo 1",M7/M42,L7="Grupo 2",M7/M43,L7="Grupo 3",M7/M44,L7="Grupo 4",M7/M45,L7="Grupo 5",M7/M46) -> 0.5 | J7: =IFS(L7="Grupo 0",0,L7="Grupo 1",K7/K42,L7="Grupo 2",K7/K43,L7="Grupo 3",K7/K44,L7="Grupo 4",K7/K45,L7="Grupo 5",K7/K46) -> 0 | K7: =IFS(L7="Grupo 0",0,L7="Grupo 1",(E42*I7-F7)*N7,L7="Grupo 2",(E43*I7-F7)*N7,L7="Grupo 3",(E44*I7-F7)*N7,L7="Grupo 4",(E45*I7-F7)*N7,L7="Grupo 5",(E46*I7-F7)*N7) -> 0 | L7: Grupo 3 | M7: 10 | N7: =IF(I7<H7,0,1) -> 0 | O7: =IFS(L7="Grupo 0",0,L7="Grupo 1",J7*D42,L7="Grupo 2",J7*D43,L7="Grupo 3",J7*D44,L7="Grupo 4",J7*D45,L7="Grupo 5",J7*D46) -> 0 | P7: =(F7+O7)/D41 -> 0.53924839
A8: 7 | F8: =D8*E8 -> 0 | G8: =IFS(L8="Grupo 0",0,L8="Grupo 1",F8/F42,L8="Grupo 2",F8/F43,L8="Grupo 3",F8/F44,L8="Grupo 4",F8/F45,L8="Grupo 5",F8/F46) -> 0 | H8: =IFS(L8="Grupo 0",0,L8="Grupo 1",F8/E42,L8="Grupo 2",F8/E43,L8="Grupo 3",F8/E44,L8="Grupo 4",F8/E45,L8="Grupo 5",F8/E46) -> 0 | I8: =IFS(L8="Grupo 0",0,L8="Grupo 1",M8/M42,L8="Grupo 2",M8/M43,L8="Grupo 3",M8/M44,L8="Grupo 4",M8/M45,L8="Grupo 5",M8/M46) -> 0 | J8: =IFS(L8="Grupo 0",0,L8="Grupo 1",K8/K42,L8="Grupo 2",K8/K43,L8="Grupo 3",K8/K44,L8="Grupo 4",K8/K45,L8="Grupo 5",K8/K46) -> 0 | K8: =IFS(L8="Grupo 0",0,L8="Grupo 1",(E42*I8-F8)*N8,L8="Grupo 2",(E43*I8-F8)*N8,L8="Grupo 3",(E44*I8-F8)*N8,L8="Grupo 4",(E45*I8-F8)*N8,L8="Grupo 5",(E46*I8-F8)*N8) -> 0 | L8: Grupo 0 | N8: =IF(I8<H8,0,1) -> 1 | O8: =IFS(L8="Grupo 0",0,L8="Grupo 1",J8*D42,L8="Grupo 2",J8*D43,L8="Grupo 3",J8*D44,L8="Grupo 4",J8*D45,L8="Grupo 5",J8*D46) -> 0 | P8: =(F8+O8)/D41 -> 0
A9: 8 | F9: =D9*E9 -> 0 | G9: =IFS(L9="Grupo 0",0,L9="Grupo 1",F9/F42,L9="Grupo 2",F9/F43,L9="Grupo 3",F9/F44,L9="Grupo 4",F9/F45,L9="Grupo 5",F9/F46) -> 0 | H9: =IFS(L9="Grupo 0",0,L9="Grupo 1",F9/E42,L9="Grupo 2",F9/E43,L9="Grupo 3",F9/E44,L9="Grupo 4",F9/E45,L9="Grupo 5",F9/E46) -> 0 | I9: =IFS(L9="Grupo 0",0,L9="Grupo 1",M9/M42,L9="Grupo 2",M9/M43,L9="Grupo 3",M9/M44,L9="Grupo 4",M9/M45,L9="Grupo 5",M9/M46) -> 0 | J9: =IFS(L9="Grupo 0",0,L9="Grupo 1",K9/K42,L9="Grupo 2",K9/K43,L9="Grupo 3",K9/K44,L9="Grupo 4",K9/K45,L9="Grupo 5",K9/K46) -> 0 | K9: =IFS(L9="Grupo 0",0,L9="Grupo 1",(E42*I9-F9)*N9,L9="Grupo 2",(E43*I9-F9)*N9,L9="Grupo 3",(E44*I9-F9)*N9,L9="Grupo 4",(E45*I9-F9)*N9,L9="Grupo 5",(E46*I9-F9)*N9) -> 0 | L9: Grupo 0 | N9: =IF(I9<H9,0,1) -> 1 | O9: =IFS(L9="Grupo 0",0,L9="Grupo 1",J9*D42,L9="Grupo 2",J9*D43,L9="Grupo 3",J9*D44,L9="Grupo 4",J9*D45,L9="Grupo 5",J9*D46) -> 0 | P9: =(F9+O9)/D41 -> 0
A10: 9 | F10: =D10*E10 -> 0 | G10: =IFS(L10="Grupo 0",0,L10="Grupo 1",F10/F42,L10="Grupo 2",F10/F43,L10="Grupo 3",F10/F44,L10="Grupo 4",F10/F45,L10="Grupo 5",F10/F46) -> 0 | H10: =IFS(L10="Grupo 0",0,L10="Grupo 1",F10/E42,L10="Grupo 2",F10/E43,L10="Grupo 3",F10/E44,L10="Grupo 4",F10/E45,L10="Grupo 5",F10/E46) -> 0 | I10: =IFS(L10="Grupo 0",0,L10="Grupo 1",M10/M42,L10="Grupo 2",M10/M43,L10="Grupo 3",M10/M44,L10="Grupo 4",M10/M45,L10="Grupo 5",M10/M46) -> 0 | J10: =IFS(L10="Grupo 0",0,L10="Grupo 1",K10/K42,L10="Grupo 2",K10/K43,L10="Grupo 3",K10/K44,L10="Grupo 4",K10/K45,L10="Grupo 5",K10/K46) -> 0 | K10: =IFS(L10="Grupo 0",0,L10="Grupo 1",(E42*I10-F10)*N10,L10="Grupo 2",(E43*I10-F10)*N10,L10="Grupo 3",(E44*I10-F10)*N10,L10="Grupo 4",(E45*I10-F10)*N10,L10="Grupo 5",(E46*I10-F10)*N10) -> 0 | L10: Grupo 0 | N10: =IF(I10<H10,0,1) -> 1 | O10: =IFS(L10="Grupo 0",0,L10="Grupo 1",J10*D42,L10="Grupo 2",J10*D43,L10="Grupo 3",J10*D44,L10="Grupo 4",J10*D45,L10="Grupo 5",J10*D46) -> 0 | P10: =(F10+O10)/D41 -> 0
A11: 10 | F11: =D11*E11 -> 0 | G11: =IFS(L11="Grupo 0",0,L11="Grupo 1",F11/F42,L11="Grupo 2",F11/F43,L11="Grupo 3",F11/F44,L11="Grupo 4",F11/F45,L11="Grupo 5",F11/F46) -> 0 | H11: =IFS(L11="Grupo 0",0,L11="Grupo 1",F11/E42,L11="Grupo 2",F11/E43,L11="Grupo 3",F11/E44,L11="Grupo 4",F11/E45,L11="Grupo 5",F11/E46) -> 0 | I11: =IFS(L11="Grupo 0",0,L11="Grupo 1",M11/M42,L11="Grupo 2",M11/M43,L11="Grupo 3",M11/M44,L11="Grupo 4",M11/M45,L11="Grupo 5",M11/M46) -> 0 | J11: =IFS(L11="Grupo 0",0,L11="Grupo 1",K11/K42,L11="Grupo 2",K11/K43,L11="Grupo 3",K11/K44,L11="Grupo 4",K11/K45,L11="Grupo 5",K11/K46) -> 0 | K11: =IFS(L11="Grupo 0",0,L11="Grupo 1",(E42*I11-F11)*N11,L11="Grupo 2",(E43*I11-F11)*N11,L11="Grupo 3",(E44*I10-F11)*N11,L11="Grupo 4",(E45*I11-F11)*N11,L11="Grupo 5",(E46*I11-F11)*N11) -> 0 | L11: Grupo 0 | N11: =IF(I11<H11,0,1) -> 1 | O11: =IFS(L11="Grupo 0",0,L11="Grupo 1",J11*D42,L11="Grupo 2",J11*D43,L11="Grupo 3",J11*D44,L11="Grupo 4",J11*D45,L11="Grupo 5",J11*D46) -> 0 | P11: =(F11+O11)/D41 -> 0
A12: 11 | F12: =D12*E12 -> 0 | G12: =IFS(L12="Grupo 0",0,L12="Grupo 1",F12/F42,L12="Grupo 2",F12/F43,L12="Grupo 3",F12/F44,L12="Grupo 4",F12/F45,L12="Grupo 5",F12/F46) -> 0 | H12: =IFS(L12="Grupo 0",0,L12="Grupo 1",F12/E42,L12="Grupo 2",F12/E43,L12="Grupo 3",F12/E44,L12="Grupo 4",F12/E45,L12="Grupo 5",F12/E46) -> 0 | I12: =IFS(L12="Grupo 0",0,L12="Grupo 1",M12/M42,L12="Grupo 2",M12/M43,L12="Grupo 3",M12/M44,L12="Grupo 4",M12/M45,L12="Grupo 5",M12/M46) -> 0 | J12: =IFS(L12="Grupo 0",0,L12="Grupo 1",K12/K42,L12="Grupo 2",K12/K43,L12="Grupo 3",K12/K44,L12="Grupo 4",K12/K45,L12="Grupo 5",K12/K46) -> 0 | K12: =IFS(L12="Grupo 0",0,L12="Grupo 1",(E42*I12-F12)*N12,L12="Grupo 2",(E43*I12-F12)*N12,L12="Grupo 3",(E44*I12-F12)*N12,L12="Grupo 4",(E45*I12-F12)*N12,L12="Grupo 5",(E46*I12-F12)*N12) -> 0 | L12: Grupo 0 | N12: =IF(I12<H12,0,1) -> 1 | O12: =IFS(L12="Grupo 0",0,L12="Grupo 1",J12*D42,L12="Grupo 2",J12*D43,L12="Grupo 3",J12*D44,L12="Grupo 4",J12*D45,L12="Grupo 5",J12*D46) -> 0 | P12: =(F12+O12)/D41 -> 0
A13: 12 | B13: BTC | C13: =IFERROR(__xludf.DUMMYFUNCTION("GOOGLEFINANCE(""CURRENCY:BTCUSD"")"),71027.81) -> 71027.81 | D13: 0.00533 | E13: =IFERROR(__xludf.DUMMYFUNCTION("GOOGLEFINANCE(""CURRENCY:BTCBRL"")"),373883.289) -> 373883.29 | F13: =D13*E13 -> 1992.7979 | G13: =IFS(L13="Grupo 0",0,L13="Grupo 1",F13/F42,L13="Grupo 2",F13/F43,L13="Grupo 3",F13/F44,L13="Grupo 4",F13/F45,L13="Grupo 5",F13/F46) -> 1 | H13: =IFS(L13="Grupo 0",0,L13="Grupo 1",F13/E42,L13="Grupo 2",F13/E43,L13="Grupo 3",F13/E44,L13="Grupo 4",F13/E45,L13="Grupo 5",F13/E46) -> 0.67150148 | I13: =IFS(L13="Grupo 0",0,L13="Grupo 1",M13/M42,L13="Grupo 2",M13/M43,L13="Grupo 3",M13/M44,L13="Grupo 4",M13/M45,L13="Grupo 5",M13/M46) -> 1 | J13: =IFS(L13="Grupo 0",0,L13="Grupo 1",K13/K42,L13="Grupo 2",K13/K43,L13="Grupo 3",K13/K44,L13="Grupo 4",K13/K45,L13="Grupo 5",K13/K46) -> 1 | K13: =IFS(L13="Grupo 0",0,L13="Grupo 1",(E42*I13-F13)*N13,L13="Grupo 2",(E43*I13-F13)*N13,L13="Grupo 3",(E44*I13-F13)*N13,L13="Grupo 4",(E45*I13-F13)*N13,L13="Grupo 5",(E46*I13-F13)*N13) -> 974.87673 | L13: Grupo 2 | M13: 10 | N13: =IF(I13<H13,0,1) -> 1 | O13: =IFS(L13="Grupo 0",0,L13="Grupo 1",J13*D42,L13="Grupo 2",J13*D43,L13="Grupo 3",J13*D44,L13="Grupo 4",J13*D45,L13="Grupo 5",J13*D46) -> 974.87673 | P13: =(F13+O13)/D41 -> 0.16336033
A14: 13 | F14: =D14*E14 -> 0 | G14: =IFS(L14="Grupo 0",0,L14="Grupo 1",F14/F42,L14="Grupo 2",F14/F43,L14="Grupo 3",F14/F44,L14="Grupo 4",F14/F45,L14="Grupo 5",F14/F46) -> 0 | H14: =IFS(L14="Grupo 0",0,L14="Grupo 1",F14/E42,L14="Grupo 2",F14/E43,L14="Grupo 3",F14/E44,L14="Grupo 4",F14/E45,L14="Grupo 5",F14/E46) -> 0 | I14: =IFS(L14="Grupo 0",0,L14="Grupo 1",M14/M42,L14="Grupo 2",M14/M43,L14="Grupo 3",M14/M44,L14="Grupo 4",M14/M45,L14="Grupo 5",M14/M46) -> 0 | J14: =IFS(L14="Grupo 0",0,L14="Grupo 1",K14/K42,L14="Grupo 2",K14/K43,L14="Grupo 3",K14/K44,L14="Grupo 4",K14/K45,L14="Grupo 5",K14/K46) -> 0 | K14: =IFS(L14="Grupo 0",0,L14="Grupo 1",(E42*I14-F14)*N14,L14="Grupo 2",(E43*I14-F14)*N14,L14="Grupo 3",(E44*I14-F14)*N14,L14="Grupo 4",(E45*I14-F14)*N14,L14="Grupo 5",(E46*I14-F14)*N14) -> 0 | L14: Grupo 0 | N14: =IF(I14<H14,0,1) -> 1 | O14: =IFS(L14="Grupo 0",0,L14="Grupo 1",J14*D42,L14="Grupo 2",J14*D43,L14="Grupo 3",J14*D44,L14="Grupo 4",J14*D45,L14="Grupo 5",J14*D46) -> 0 | P14: =(F14+O14)/D41 -> 0
A15: 14 | F15: =D15*E15 -> 0 | G15: =IFS(L15="Grupo 0",0,L15="Grupo 1",F15/F42,L15="Grupo 2",F15/F43,L15="Grupo 3",F15/F44,L15="Grupo 4",F15/F45,L15="Grupo 5",F15/F46) -> 0 | H15: =IFS(L15="Grupo 0",0,L15="Grupo 1",F15/E42,L15="Grupo 2",F15/E43,L15="Grupo 3",F15/E44,L15="Grupo 4",F15/E45,L15="Grupo 5",F15/E46) -> 0 | I15: =IFS(L15="Grupo 0",0,L15="Grupo 1",M15/M42,L15="Grupo 2",M15/M43,L15="Grupo 3",M15/M44,L15="Grupo 4",M15/M45,L15="Grupo 5",M15/M46) -> 0 | J15: =IFS(L15="Grupo 0",0,L15="Grupo 1",K15/K42,L15="Grupo 2",K15/K43,L15="Grupo 3",K15/K44,L15="Grupo 4",K15/K45,L15="Grupo 5",K15/K46) -> 0 | K15: =IFS(L15="Grupo 0",0,L15="Grupo 1",(E42*I15-F15)*N15,L15="Grupo 2",(E43*I15-F15)*N15,L15="Grupo 3",(E44*I15-F15)*N15,L15="Grupo 4",(E45*I15-F15)*N15,L15="Grupo 5",(E46*I15-F15)*N15) -> 0 | L15: Grupo 0 | N15: =IF(I15<H15,0,1) -> 1 | O15: =IFS(L15="Grupo 0",0,L15="Grupo 1",J15*D42,L15="Grupo 2",J15*D43,L15="Grupo 3",J15*D44,L15="Grupo 4",J15*D45,L15="Grupo 5",J15*D46) -> 0 | P15: =(F15+O15)/D41 -> 0
A16: 15 | F16: =D16*E16 -> 0 | G16: =IFS(L16="Grupo 0",0,L16="Grupo 1",F16/F42,L16="Grupo 2",F16/F43,L16="Grupo 3",F16/F44,L16="Grupo 4",F16/F45,L16="Grupo 5",F16/F46) -> 0 | H16: =IFS(L16="Grupo 0",0,L16="Grupo 1",F16/E42,L16="Grupo 2",F16/E43,L16="Grupo 3",F16/E44,L16="Grupo 4",F16/E45,L16="Grupo 5",F16/E46) -> 0 | I16: =IFS(L16="Grupo 0",0,L16="Grupo 1",M16/M42,L16="Grupo 2",M16/M43,L16="Grupo 3",M16/M44,L16="Grupo 4",M16/M45,L16="Grupo 5",M16/M46) -> 0 | J16: =IFS(L16="Grupo 0",0,L16="Grupo 1",K16/K42,L16="Grupo 2",K16/K43,L16="Grupo 3",K16/K44,L16="Grupo 4",K16/K45,L16="Grupo 5",K16/K46) -> 0 | K16: =IFS(L16="Grupo 0",0,L16="Grupo 1",(E42*I16-F16)*N16,L16="Grupo 2",(E43*I16-F16)*N16,L16="Grupo 3",(E44*I16-F16)*N16,L16="Grupo 4",(E45*I16-F16)*N16,L16="Grupo 5",(E46*I16-F16)*N16) -> 0 | L16: Grupo 0 | N16: =IF(I16<H16,0,1) -> 1 | O16: =IFS(L16="Grupo 0",0,L16="Grupo 1",J16*D42,L16="Grupo 2",J16*D43,L16="Grupo 3",J16*D44,L16="Grupo 4",J16*D45,L16="Grupo 5",J16*D46) -> 0 | P16: =(F16+O16)/D41 -> 0
A17: 16 | F17: =D17*E17 -> 0 | G17: =IFS(L17="Grupo 0",0,L17="Grupo 1",F17/F42,L17="Grupo 2",F17/F43,L17="Grupo 3",F17/F44,L17="Grupo 4",F17/F45,L17="Grupo 5",F17/F46) -> 0 | H17: =IFS(L17="Grupo 0",0,L17="Grupo 1",F17/E42,L17="Grupo 2",F17/E43,L17="Grupo 3",F17/E44,L17="Grupo 4",F17/E45,L17="Grupo 5",F17/E46) -> 0 | I17: =IFS(L17="Grupo 0",0,L17="Grupo 1",M17/M42,L17="Grupo 2",M17/M43,L17="Grupo 3",M17/M44,L17="Grupo 4",M17/M45,L17="Grupo 5",M17/M46) -> 0 | J17: =IFS(L17="Grupo 0",0,L17="Grupo 1",K17/K42,L17="Grupo 2",K17/K43,L17="Grupo 3",K17/K44,L17="Grupo 4",K17/K45,L17="Grupo 5",K17/K46) -> 0 | K17: =IFS(L17="Grupo 0",0,L17="Grupo 1",(E42*I17-F17)*N17,L17="Grupo 2",(E43*I17-F17)*N17,L17="Grupo 3",(E44*I17-F17)*N17,L17="Grupo 4",(E45*I17-F17)*N17,L17="Grupo 5",(E46*I17-F17)*N17) -> 0 | L17: Grupo 0 | N17: =IF(I17<H17,0,1) -> 1 | O17: =IFS(L17="Grupo 0",0,L17="Grupo 1",J17*D42,L17="Grupo 2",J17*D43,L17="Grupo 3",J17*D44,L17="Grupo 4",J17*D45,L17="Grupo 5",J17*D46) -> 0 | P17: =(F17+O17)/D41 -> 0
A18: 17 | F18: =D18*E18 -> 0 | G18: =IFS(L18="Grupo 0",0,L18="Grupo 1",F18/F42,L18="Grupo 2",F18/F43,L18="Grupo 3",F18/F44,L18="Grupo 4",F18/F45,L18="Grupo 5",F18/F46) -> 0 | H18: =IFS(L18="Grupo 0",0,L18="Grupo 1",F18/E42,L18="Grupo 2",F18/E43,L18="Grupo 3",F18/E44,L18="Grupo 4",F18/E45,L18="Grupo 5",F18/E46) -> 0 | I18: =IFS(L18="Grupo 0",0,L18="Grupo 1",M18/M42,L18="Grupo 2",M18/M43,L18="Grupo 3",M18/M44,L18="Grupo 4",M18/M45,L18="Grupo 5",M18/M46) -> 0 | J18: =IFS(L18="Grupo 0",0,L18="Grupo 1",K18/K42,L18="Grupo 2",K18/K43,L18="Grupo 3",K18/K44,L18="Grupo 4",K18/K45,L18="Grupo 5",K18/K46) -> 0 | K18: =IFS(L18="Grupo 0",0,L18="Grupo 1",(E42*I18-F18)*N18,L18="Grupo 2",(E43*I18-F18)*N18,L18="Grupo 3",(E44*I18-F18)*N18,L18="Grupo 4",(E45*I18-F18)*N18,L18="Grupo 5",(E46*I18-F18)*N18) -> 0 | L18: Grupo 0 | N18: =IF(I18<H18,0,1) -> 1 | O18: =IFS(L18="Grupo 0",0,L18="Grupo 1",J18*D42,L18="Grupo 2",J18*D43,L18="Grupo 3",J18*D44,L18="Grupo 4",J18*D45,L18="Grupo 5",J18*D46) -> 0 | P18: =(F18+O18)/D41 -> 0
A19: 18 | F19: =D19*E19 -> 0 | G19: =IFS(L19="Grupo 0",0,L19="Grupo 1",F19/F42,L19="Grupo 2",F19/F43,L19="Grupo 3",F19/F44,L19="Grupo 4",F19/F45,L19="Grupo 5",F19/F46) -> 0 | H19: =IFS(L19="Grupo 0",0,L19="Grupo 1",F19/E42,L19="Grupo 2",F19/E43,L19="Grupo 3",F19/E44,L19="Grupo 4",F19/E45,L19="Grupo 5",F19/E46) -> 0 | I19: =IFS(L19="Grupo 0",0,L19="Grupo 1",M19/M42,L19="Grupo 2",M19/M43,L19="Grupo 3",M19/M44,L19="Grupo 4",M19/M45,L19="Grupo 5",M19/M46) -> 0 | J19: =IFS(L19="Grupo 0",0,L19="Grupo 1",K19/K42,L19="Grupo 2",K19/K43,L19="Grupo 3",K19/K44,L19="Grupo 4",K19/K45,L19="Grupo 5",K19/K46) -> 0 | K19: =IFS(L19="Grupo 0",0,L19="Grupo 1",(E42*I19-F19)*N19,L19="Grupo 2",(E43*I19-F19)*N19,L19="Grupo 3",(E44*I19-F19)*N19,L19="Grupo 4",(E45*I19-F19)*N19,L19="Grupo 5",(E46*I19-F19)*N19) -> 0 | L19: Grupo 0 | N19: =IF(I19<H19,0,1) -> 1 | O19: =IFS(L19="Grupo 0",0,L19="Grupo 1",J19*D42,L19="Grupo 2",J19*D43,L19="Grupo 3",J19*D44,L19="Grupo 4",J19*D45,L19="Grupo 5",J19*D46) -> 0 | P19: =(F19+O19)/D41 -> 0
A20: 19 | F20: =D20*E20 -> 0 | G20: =IFS(L20="Grupo 0",0,L20="Grupo 1",F20/F42,L20="Grupo 2",F20/F43,L20="Grupo 3",F20/F44,L20="Grupo 4",F20/F45,L20="Grupo 5",F20/F46) -> 0 | H20: =IFS(L20="Grupo 0",0,L20="Grupo 1",F20/E42,L20="Grupo 2",F20/E43,L20="Grupo 3",F20/E44,L20="Grupo 4",F20/E45,L20="Grupo 5",F20/E46) -> 0 | I20: =IFS(L20="Grupo 0",0,L20="Grupo 1",M20/M42,L20="Grupo 2",M20/M43,L20="Grupo 3",M20/M44,L20="Grupo 4",M20/M45,L20="Grupo 5",M20/M46) -> 0 | J20: =IFS(L20="Grupo 0",0,L20="Grupo 1",K20/K42,L20="Grupo 2",K20/K43,L20="Grupo 3",K20/K44,L20="Grupo 4",K20/K45,L20="Grupo 5",K20/K46) -> 0 | K20: =IFS(L20="Grupo 0",0,L20="Grupo 1",(E42*I20-F20)*N20,L20="Grupo 2",(E43*I20-F20)*N20,L20="Grupo 3",(E44*I20-F20)*N20,L20="Grupo 4",(E45*I20-F20)*N20,L20="Grupo 5",(E46*I20-F20)*N20) -> 0 | L20: Grupo 0 | N20: =IF(I20<H20,0,1) -> 1 | O20: =IFS(L20="Grupo 0",0,L20="Grupo 1",J20*D42,L20="Grupo 2",J20*D43,L20="Grupo 3",J20*D44,L20="Grupo 4",J20*D45,L20="Grupo 5",J20*D46) -> 0 | P20: =(F20+O20)/D41 -> 0
A21: 20 | F21: =D21*E21 -> 0 | G21: =IFS(L21="Grupo 0",0,L21="Grupo 1",F21/F42,L21="Grupo 2",F21/F43,L21="Grupo 3",F21/F44,L21="Grupo 4",F21/F45,L21="Grupo 5",F21/F46) -> 0 | H21: =IFS(L21="Grupo 0",0,L21="Grupo 1",F21/E42,L21="Grupo 2",F21/E43,L21="Grupo 3",F21/E44,L21="Grupo 4",F21/E45,L21="Grupo 5",F21/E46) -> 0 | I21: =IFS(L21="Grupo 0",0,L21="Grupo 1",M21/M42,L21="Grupo 2",M21/M43,L21="Grupo 3",M21/M44,L21="Grupo 4",M21/M45,L21="Grupo 5",M21/M46) -> 0 | J21: =IFS(L21="Grupo 0",0,L21="Grupo 1",K21/K42,L21="Grupo 2",K21/K43,L21="Grupo 3",K21/K44,L21="Grupo 4",K21/K45,L21="Grupo 5",K21/K46) -> 0 | K21: =IFS(L21="Grupo 0",0,L21="Grupo 1",(E42*I21-F21)*N21,L21="Grupo 2",(E43*I21-F21)*N21,L21="Grupo 3",(E44*I20-F21)*N21,L21="Grupo 4",(E45*I21-F21)*N21,L21="Grupo 5",(E46*I21-F21)*N21) -> 0 | L21: Grupo 0 | N21: =IF(I21<H21,0,1) -> 1 | O21: =IFS(L21="Grupo 0",0,L21="Grupo 1",J21*D42,L21="Grupo 2",J21*D43,L21="Grupo 3",J21*D44,L21="Grupo 4",J21*D45,L21="Grupo 5",J21*D46) -> 0 | P21: =(F21+O21)/D41 -> 0
A22: 21 | F22: =D22*E22 -> 0 | G22: =IFS(L22="Grupo 0",0,L22="Grupo 1",F22/F42,L22="Grupo 2",F22/F43,L22="Grupo 3",F22/F44,L22="Grupo 4",F22/F45,L22="Grupo 5",F22/F46) -> 0 | H22: =IFS(L22="Grupo 0",0,L22="Grupo 1",F22/E42,L22="Grupo 2",F22/E43,L22="Grupo 3",F22/E44,L22="Grupo 4",F22/E45,L22="Grupo 5",F22/E46) -> 0 | I22: =IFS(L22="Grupo 0",0,L22="Grupo 1",M22/M42,L22="Grupo 2",M22/M43,L22="Grupo 3",M22/M44,L22="Grupo 4",M22/M45,L22="Grupo 5",M22/M46) -> 0 | J22: =IFS(L22="Grupo 0",0,L22="Grupo 1",K22/K42,L22="Grupo 2",K22/K43,L22="Grupo 3",K22/K44,L22="Grupo 4",K22/K45,L22="Grupo 5",K22/K46) -> 0 | K22: =IFS(L22="Grupo 0",0,L22="Grupo 1",(E42*I22-F22)*N22,L22="Grupo 2",(E43*I22-F22)*N22,L22="Grupo 3",(E44*I22-F22)*N22,L22="Grupo 4",(E45*I22-F22)*N22,L22="Grupo 5",(E46*I22-F22)*N22) -> 0 | L22: Grupo 0 | N22: =IF(I22<H22,0,1) -> 1 | O22: =IFS(L22="Grupo 0",0,L22="Grupo 1",J22*D42,L22="Grupo 2",J22*D43,L22="Grupo 3",J22*D44,L22="Grupo 4",J22*D45,L22="Grupo 5",J22*D46) -> 0
A23: 22 | F23: =D23*E23 -> 0 | G23: =IFS(L23="Grupo 0",0,L23="Grupo 1",F23/F42,L23="Grupo 2",F23/F43,L23="Grupo 3",F23/F44,L23="Grupo 4",F23/F45,L23="Grupo 5",F23/F46) -> 0 | H23: =IFS(L23="Grupo 0",0,L23="Grupo 1",F23/E42,L23="Grupo 2",F23/E43,L23="Grupo 3",F23/E44,L23="Grupo 4",F23/E45,L23="Grupo 5",F23/E46) -> 0 | I23: =IFS(L23="Grupo 0",0,L23="Grupo 1",M23/M42,L23="Grupo 2",M23/M43,L23="Grupo 3",M23/M44,L23="Grupo 4",M23/M45,L23="Grupo 5",M23/M46) -> 0 | J23: =IFS(L23="Grupo 0",0,L23="Grupo 1",K23/K42,L23="Grupo 2",K23/K43,L23="Grupo 3",K23/K44,L23="Grupo 4",K23/K45,L23="Grupo 5",K23/K46) -> 0 | K23: =IFS(L23="Grupo 0",0,L23="Grupo 1",(E42*I23-F23)*N23,L23="Grupo 2",(E43*I23-F23)*N23,L23="Grupo 3",(E44*I23-F23)*N23,L23="Grupo 4",(E45*I23-F23)*N23,L23="Grupo 5",(E46*I23-F23)*N23) -> 0 | L23: Grupo 0 | N23: =IF(I23<H23,0,1) -> 1 | O23: =IFS(L23="Grupo 0",0,L23="Grupo 1",J23*D42,L23="Grupo 2",J23*D43,L23="Grupo 3",J23*D44,L23="Grupo 4",J23*D45,L23="Grupo 5",J23*D46) -> 0
A24: 23 | F24: =D24*E24 -> 0 | G24: =IFS(L24="Grupo 0",0,L24="Grupo 1",F24/F42,L24="Grupo 2",F24/F43,L24="Grupo 3",F24/F44,L24="Grupo 4",F24/F45,L24="Grupo 5",F24/F46) -> 0 | H24: =IFS(L24="Grupo 0",0,L24="Grupo 1",F24/E42,L24="Grupo 2",F24/E43,L24="Grupo 3",F24/E44,L24="Grupo 4",F24/E45,L24="Grupo 5",F24/E46) -> 0 | I24: =IFS(L24="Grupo 0",0,L24="Grupo 1",M24/M42,L24="Grupo 2",M24/M43,L24="Grupo 3",M24/M44,L24="Grupo 4",M24/M45,L24="Grupo 5",M24/M46) -> 0 | J24: =IFS(L24="Grupo 0",0,L24="Grupo 1",K24/K42,L24="Grupo 2",K24/K43,L24="Grupo 3",K24/K44,L24="Grupo 4",K24/K45,L24="Grupo 5",K24/K46) -> 0 | K24: =IFS(L24="Grupo 0",0,L24="Grupo 1",(E42*I24-F24)*N24,L24="Grupo 2",(E43*I24-F24)*N24,L24="Grupo 3",(E44*I24-F24)*N24,L24="Grupo 4",(E45*I24-F24)*N24,L24="Grupo 5",(E46*I24-F24)*N24) -> 0 | L24: Grupo 0 | N24: =IF(I24<H24,0,1) -> 1 | O24: =IFS(L24="Grupo 0",0,L24="Grupo 1",J24*D42,L24="Grupo 2",J24*D43,L24="Grupo 3",J24*D44,L24="Grupo 4",J24*D45,L24="Grupo 5",J24*D46) -> 0
A25: 24 | F25: =D25*E25 -> 0 | G25: =IFS(L25="Grupo 0",0,L25="Grupo 1",F25/F42,L25="Grupo 2",F25/F43,L25="Grupo 3",F25/F44,L25="Grupo 4",F25/F45,L25="Grupo 5",F25/F46) -> 0 | H25: =IFS(L25="Grupo 0",0,L25="Grupo 1",F25/E42,L25="Grupo 2",F25/E43,L25="Grupo 3",F25/E44,L25="Grupo 4",F25/E45,L25="Grupo 5",F25/E46) -> 0 | I25: =IFS(L25="Grupo 0",0,L25="Grupo 1",M25/M42,L25="Grupo 2",M25/M43,L25="Grupo 3",M25/M44,L25="Grupo 4",M25/M45,L25="Grupo 5",M25/M46) -> 0 | J25: =IFS(L25="Grupo 0",0,L25="Grupo 1",K25/K42,L25="Grupo 2",K25/K43,L25="Grupo 3",K25/K44,L25="Grupo 4",K25/K45,L25="Grupo 5",K25/K46) -> 0 | K25: =IFS(L25="Grupo 0",0,L25="Grupo 1",(E42*I25-F25)*N25,L25="Grupo 2",(E43*I25-F25)*N25,L25="Grupo 3",(E44*I25-F25)*N25,L25="Grupo 4",(E45*I25-F25)*N25,L25="Grupo 5",(E46*I25-F25)*N25) -> 0 | L25: Grupo 0 | N25: =IF(I25<H25,0,1) -> 1 | O25: =IFS(L25="Grupo 0",0,L25="Grupo 1",J25*D42,L25="Grupo 2",J25*D43,L25="Grupo 3",J25*D44,L25="Grupo 4",J25*D45,L25="Grupo 5",J25*D46) -> 0
A26: 25 | F26: =D26*E26 -> 0 | G26: =IFS(L26="Grupo 0",0,L26="Grupo 1",F26/F42,L26="Grupo 2",F26/F43,L26="Grupo 3",F26/F44,L26="Grupo 4",F26/F45,L26="Grupo 5",F26/F46) -> 0 | H26: =IFS(L26="Grupo 0",0,L26="Grupo 1",F26/E42,L26="Grupo 2",F26/E43,L26="Grupo 3",F26/E44,L26="Grupo 4",F26/E45,L26="Grupo 5",F26/E46) -> 0 | I26: =IFS(L26="Grupo 0",0,L26="Grupo 1",M26/M42,L26="Grupo 2",M26/M43,L26="Grupo 3",M26/M44,L26="Grupo 4",M26/M45,L26="Grupo 5",M26/M46) -> 0 | J26: =IFS(L26="Grupo 0",0,L26="Grupo 1",K26/K42,L26="Grupo 2",K26/K43,L26="Grupo 3",K26/K44,L26="Grupo 4",K26/K45,L26="Grupo 5",K26/K46) -> 0 | K26: =IFS(L26="Grupo 0",0,L26="Grupo 1",(E42*I26-F26)*N26,L26="Grupo 2",(E43*I26-F26)*N26,L26="Grupo 3",(E44*I26-F26)*N26,L26="Grupo 4",(E45*I26-F26)*N26,L26="Grupo 5",(E46*I26-F26)*N26) -> 0 | L26: Grupo 0 | N26: =IF(I26<H26,0,1) -> 1 | O26: =IFS(L26="Grupo 0",0,L26="Grupo 1",J26*D42,L26="Grupo 2",J26*D43,L26="Grupo 3",J26*D44,L26="Grupo 4",J26*D45,L26="Grupo 5",J26*D46) -> 0
A27: 26 | F27: =D27*E27 -> 0 | G27: =IFS(L27="Grupo 0",0,L27="Grupo 1",F27/F42,L27="Grupo 2",F27/F43,L27="Grupo 3",F27/F44,L27="Grupo 4",F27/F45,L27="Grupo 5",F27/F46) -> 0 | H27: =IFS(L27="Grupo 0",0,L27="Grupo 1",F27/E42,L27="Grupo 2",F27/E43,L27="Grupo 3",F27/E44,L27="Grupo 4",F27/E45,L27="Grupo 5",F27/E46) -> 0 | I27: =IFS(L27="Grupo 0",0,L27="Grupo 1",M27/M42,L27="Grupo 2",M27/M43,L27="Grupo 3",M27/M44,L27="Grupo 4",M27/M45,L27="Grupo 5",M27/M46) -> 0 | J27: =IFS(L27="Grupo 0",0,L27="Grupo 1",K27/K42,L27="Grupo 2",K27/K43,L27="Grupo 3",K27/K44,L27="Grupo 4",K27/K45,L27="Grupo 5",K27/K46) -> 0 | K27: =IFS(L27="Grupo 0",0,L27="Grupo 1",(E42*I27-F27)*N27,L27="Grupo 2",(E43*I27-F27)*N27,L27="Grupo 3",(E44*I27-F27)*N27,L27="Grupo 4",(E45*I27-F27)*N27,L27="Grupo 5",(E46*I27-F27)*N27) -> 0 | L27: Grupo 0 | N27: =IF(I27<H27,0,1) -> 1 | O27: =IFS(L27="Grupo 0",0,L27="Grupo 1",J27*D42,L27="Grupo 2",J27*D43,L27="Grupo 3",J27*D44,L27="Grupo 4",J27*D45,L27="Grupo 5",J27*D46) -> 0
A28: 27 | F28: =D28*E28 -> 0 | G28: =IFS(L28="Grupo 0",0,L28="Grupo 1",F28/F42,L28="Grupo 2",F28/F43,L28="Grupo 3",F28/F44,L28="Grupo 4",F28/F45,L28="Grupo 5",F28/F46) -> 0 | H28: =IFS(L28="Grupo 0",0,L28="Grupo 1",F28/E42,L28="Grupo 2",F28/E43,L28="Grupo 3",F28/E44,L28="Grupo 4",F28/E45,L28="Grupo 5",F28/E46) -> 0 | I28: =IFS(L28="Grupo 0",0,L28="Grupo 1",M28/M42,L28="Grupo 2",M28/M43,L28="Grupo 3",M28/M44,L28="Grupo 4",M28/M45,L28="Grupo 5",M28/M46) -> 0 | J28: =IFS(L28="Grupo 0",0,L28="Grupo 1",K28/K42,L28="Grupo 2",K28/K43,L28="Grupo 3",K28/K44,L28="Grupo 4",K28/K45,L28="Grupo 5",K28/K46) -> 0 | K28: =IFS(L28="Grupo 0",0,L28="Grupo 1",(E42*I28-F28)*N28,L28="Grupo 2",(E43*I28-F28)*N28,L28="Grupo 3",(E44*I28-F28)*N28,L28="Grupo 4",(E45*I28-F28)*N28,L28="Grupo 5",(E46*I28-F28)*N28) -> 0 | L28: Grupo 0 | N28: =IF(I28<H28,0,1) -> 1 | O28: =IFS(L28="Grupo 0",0,L28="Grupo 1",J28*D42,L28="Grupo 2",J28*D43,L28="Grupo 3",J28*D44,L28="Grupo 4",J28*D45,L28="Grupo 5",J28*D46) -> 0
A29: 28 | F29: =D29*E29 -> 0 | G29: =IFS(L29="Grupo 0",0,L29="Grupo 1",F29/F42,L29="Grupo 2",F29/F43,L29="Grupo 3",F29/F44,L29="Grupo 4",F29/F45,L29="Grupo 5",F29/F46) -> 0 | H29: =IFS(L29="Grupo 0",0,L29="Grupo 1",F29/E42,L29="Grupo 2",F29/E43,L29="Grupo 3",F29/E44,L29="Grupo 4",F29/E45,L29="Grupo 5",F29/E46) -> 0 | I29: =IFS(L29="Grupo 0",0,L29="Grupo 1",M29/M42,L29="Grupo 2",M29/M43,L29="Grupo 3",M29/M44,L29="Grupo 4",M29/M45,L29="Grupo 5",M29/M46) -> 0 | J29: =IFS(L29="Grupo 0",0,L29="Grupo 1",K29/K42,L29="Grupo 2",K29/K43,L29="Grupo 3",K29/K44,L29="Grupo 4",K29/K45,L29="Grupo 5",K29/K46) -> 0 | K29: =IFS(L29="Grupo 0",0,L29="Grupo 1",(E42*I29-F29)*N29,L29="Grupo 2",(E43*I29-F29)*N29,L29="Grupo 3",(E44*I29-F29)*N29,L29="Grupo 4",(E45*I29-F29)*N29,L29="Grupo 5",(E46*I29-F29)*N29) -> 0 | L29: Grupo 0 | N29: =IF(I29<H29,0,1) -> 1 | O29: =IFS(L29="Grupo 0",0,L29="Grupo 1",J29*D42,L29="Grupo 2",J29*D43,L29="Grupo 3",J29*D44,L29="Grupo 4",J29*D45,L29="Grupo 5",J29*D46) -> 0
A30: 29 | F30: =D30*E30 -> 0 | G30: =IFS(L30="Grupo 0",0,L30="Grupo 1",F30/F42,L30="Grupo 2",F30/F43,L30="Grupo 3",F30/F44,L30="Grupo 4",F30/F45,L30="Grupo 5",F30/F46) -> 0 | H30: =IFS(L30="Grupo 0",0,L30="Grupo 1",F30/E42,L30="Grupo 2",F30/E43,L30="Grupo 3",F30/E44,L30="Grupo 4",F30/E45,L30="Grupo 5",F30/E46) -> 0 | I30: =IFS(L30="Grupo 0",0,L30="Grupo 1",M30/M42,L30="Grupo 2",M30/M43,L30="Grupo 3",M30/M44,L30="Grupo 4",M30/M45,L30="Grupo 5",M30/M46) -> 0 | J30: =IFS(L30="Grupo 0",0,L30="Grupo 1",K30/K42,L30="Grupo 2",K30/K43,L30="Grupo 3",K30/K44,L30="Grupo 4",K30/K45,L30="Grupo 5",K30/K46) -> 0 | K30: =IFS(L30="Grupo 0",0,L30="Grupo 1",(E42*I30-F30)*N30,L30="Grupo 2",(E43*I30-F30)*N30,L30="Grupo 3",(E44*I30-F30)*N30,L30="Grupo 4",(E45*I30-F30)*N30,L30="Grupo 5",(E46*I30-F30)*N30) -> 0 | L30: Grupo 0 | N30: =IF(I30<H30,0,1) -> 1 | O30: =IFS(L30="Grupo 0",0,L30="Grupo 1",J30*D42,L30="Grupo 2",J30*D43,L30="Grupo 3",J30*D44,L30="Grupo 4",J30*D45,L30="Grupo 5",J30*D46) -> 0
A31: 30 | F31: =D31*E31 -> 0 | G31: =IFS(L31="Grupo 0",0,L31="Grupo 1",F31/F42,L31="Grupo 2",F31/F43,L31="Grupo 3",F31/F44,L31="Grupo 4",F31/F45,L31="Grupo 5",F31/F46) -> 0 | H31: =IFS(L31="Grupo 0",0,L31="Grupo 1",F31/E42,L31="Grupo 2",F31/E43,L31="Grupo 3",F31/E44,L31="Grupo 4",F31/E45,L31="Grupo 5",F31/E46) -> 0 | I31: =IFS(L31="Grupo 0",0,L31="Grupo 1",M31/M42,L31="Grupo 2",M31/M43,L31="Grupo 3",M31/M44,L31="Grupo 4",M31/M45,L31="Grupo 5",M31/M46) -> 0 | J31: =IFS(L31="Grupo 0",0,L31="Grupo 1",K31/K42,L31="Grupo 2",K31/K43,L31="Grupo 3",K31/K44,L31="Grupo 4",K31/K45,L31="Grupo 5",K31/K46) -> 0 | K31: =IFS(L31="Grupo 0",0,L31="Grupo 1",(E42*I31-F31)*N31,L31="Grupo 2",(E43*I31-F31)*N31,L31="Grupo 3",(E44*I30-F31)*N31,L31="Grupo 4",(E45*I31-F31)*N31,L31="Grupo 5",(E46*I31-F31)*N31) -> 0 | L31: Grupo 0 | N31: =IF(I31<H31,0,1) -> 1 | O31: =IFS(L31="Grupo 0",0,L31="Grupo 1",J31*D42,L31="Grupo 2",J31*D43,L31="Grupo 3",J31*D44,L31="Grupo 4",J31*D45,L31="Grupo 5",J31*D46) -> 0
A32: 31 | F32: =D32*E32 -> 0 | G32: =IFS(L32="Grupo 0",0,L32="Grupo 1",F32/F42,L32="Grupo 2",F32/F43,L32="Grupo 3",F32/F44,L32="Grupo 4",F32/F45,L32="Grupo 5",F32/F46) -> 0 | H32: =IFS(L32="Grupo 0",0,L32="Grupo 1",F32/E42,L32="Grupo 2",F32/E43,L32="Grupo 3",F32/E44,L32="Grupo 4",F32/E45,L32="Grupo 5",F32/E46) -> 0 | I32: =IFS(L32="Grupo 0",0,L32="Grupo 1",M32/M42,L32="Grupo 2",M32/M43,L32="Grupo 3",M32/M44,L32="Grupo 4",M32/M45,L32="Grupo 5",M32/M46) -> 0 | J32: =IFS(L32="Grupo 0",0,L32="Grupo 1",K32/K42,L32="Grupo 2",K32/K43,L32="Grupo 3",K32/K44,L32="Grupo 4",K32/K45,L32="Grupo 5",K32/K46) -> 0 | K32: =IFS(L32="Grupo 0",0,L32="Grupo 1",(E42*I32-F32)*N32,L32="Grupo 2",(E43*I32-F32)*N32,L32="Grupo 3",(E44*I32-F32)*N32,L32="Grupo 4",(E45*I32-F32)*N32,L32="Grupo 5",(E46*I32-F32)*N32) -> 0 | L32: Grupo 0 | N32: =IF(I32<H32,0,1) -> 1 | O32: =IFS(L32="Grupo 0",0,L32="Grupo 1",J32*D42,L32="Grupo 2",J32*D43,L32="Grupo 3",J32*D44,L32="Grupo 4",J32*D45,L32="Grupo 5",J32*D46) -> 0
A33: 32 | F33: =D33*E33 -> 0 | G33: =IFS(L33="Grupo 0",0,L33="Grupo 1",F33/F42,L33="Grupo 2",F33/F43,L33="Grupo 3",F33/F44,L33="Grupo 4",F33/F45,L33="Grupo 5",F33/F46) -> 0 | H33: =IFS(L33="Grupo 0",0,L33="Grupo 1",F33/E42,L33="Grupo 2",F33/E43,L33="Grupo 3",F33/E44,L33="Grupo 4",F33/E45,L33="Grupo 5",F33/E46) -> 0 | I33: =IFS(L33="Grupo 0",0,L33="Grupo 1",M33/M42,L33="Grupo 2",M33/M43,L33="Grupo 3",M33/M44,L33="Grupo 4",M33/M45,L33="Grupo 5",M33/M46) -> 0 | J33: =IFS(L33="Grupo 0",0,L33="Grupo 1",K33/K42,L33="Grupo 2",K33/K43,L33="Grupo 3",K33/K44,L33="Grupo 4",K33/K45,L33="Grupo 5",K33/K46) -> 0 | K33: =IFS(L33="Grupo 0",0,L33="Grupo 1",(E42*I33-F33)*N33,L33="Grupo 2",(E43*I33-F33)*N33,L33="Grupo 3",(E44*I33-F33)*N33,L33="Grupo 4",(E45*I33-F33)*N33,L33="Grupo 5",(E46*I33-F33)*N33) -> 0 | L33: Grupo 0 | N33: =IF(I33<H33,0,1) -> 1 | O33: =IFS(L33="Grupo 0",0,L33="Grupo 1",J33*D42,L33="Grupo 2",J33*D43,L33="Grupo 3",J33*D44,L33="Grupo 4",J33*D45,L33="Grupo 5",J33*D46) -> 0
A34: 33 | F34: =D34*E34 -> 0 | G34: =IFS(L34="Grupo 0",0,L34="Grupo 1",F34/F42,L34="Grupo 2",F34/F43,L34="Grupo 3",F34/F44,L34="Grupo 4",F34/F45,L34="Grupo 5",F34/F46) -> 0 | H34: =IFS(L34="Grupo 0",0,L34="Grupo 1",F34/E42,L34="Grupo 2",F34/E43,L34="Grupo 3",F34/E44,L34="Grupo 4",F34/E45,L34="Grupo 5",F34/E46) -> 0 | I34: =IFS(L34="Grupo 0",0,L34="Grupo 1",M34/M42,L34="Grupo 2",M34/M43,L34="Grupo 3",M34/M44,L34="Grupo 4",M34/M45,L34="Grupo 5",M34/M46) -> 0 | J34: =IFS(L34="Grupo 0",0,L34="Grupo 1",K34/K42,L34="Grupo 2",K34/K43,L34="Grupo 3",K34/K44,L34="Grupo 4",K34/K45,L34="Grupo 5",K34/K46) -> 0 | K34: =IFS(L34="Grupo 0",0,L34="Grupo 1",(E42*I34-F34)*N34,L34="Grupo 2",(E43*I34-F34)*N34,L34="Grupo 3",(E44*I34-F34)*N34,L34="Grupo 4",(E45*I34-F34)*N34,L34="Grupo 5",(E46*I34-F34)*N34) -> 0 | L34: Grupo 0 | N34: =IF(I34<H34,0,1) -> 1 | O34: =IFS(L34="Grupo 0",0,L34="Grupo 1",J34*D42,L34="Grupo 2",J34*D43,L34="Grupo 3",J34*D44,L34="Grupo 4",J34*D45,L34="Grupo 5",J34*D46) -> 0
A35: 34 | F35: =D35*E35 -> 0 | G35: =IFS(L35="Grupo 0",0,L35="Grupo 1",F35/F42,L35="Grupo 2",F35/F43,L35="Grupo 3",F35/F44,L35="Grupo 4",F35/F45,L35="Grupo 5",F35/F46) -> 0 | H35: =IFS(L35="Grupo 0",0,L35="Grupo 1",F35/E42,L35="Grupo 2",F35/E43,L35="Grupo 3",F35/E44,L35="Grupo 4",F35/E45,L35="Grupo 5",F35/E46) -> 0 | I35: =IFS(L35="Grupo 0",0,L35="Grupo 1",M35/M42,L35="Grupo 2",M35/M43,L35="Grupo 3",M35/M44,L35="Grupo 4",M35/M45,L35="Grupo 5",M35/M46) -> 0 | J35: =IFS(L35="Grupo 0",0,L35="Grupo 1",K35/K42,L35="Grupo 2",K35/K43,L35="Grupo 3",K35/K44,L35="Grupo 4",K35/K45,L35="Grupo 5",K35/K46) -> 0 | K35: =IFS(L35="Grupo 0",0,L35="Grupo 1",(E42*I35-F35)*N35,L35="Grupo 2",(E43*I35-F35)*N35,L35="Grupo 3",(E44*I35-F35)*N35,L35="Grupo 4",(E45*I35-F35)*N35,L35="Grupo 5",(E46*I35-F35)*N35) -> 0 | L35: Grupo 0 | N35: =IF(I35<H35,0,1) -> 1 | O35: =IFS(L35="Grupo 0",0,L35="Grupo 1",J35*D42,L35="Grupo 2",J35*D43,L35="Grupo 3",J35*D44,L35="Grupo 4",J35*D45,L35="Grupo 5",J35*D46) -> 0
A36: 35 | F36: =D36*E36 -> 0 | G36: =IFS(L36="Grupo 0",0,L36="Grupo 1",F36/F42,L36="Grupo 2",F36/F43,L36="Grupo 3",F36/F44,L36="Grupo 4",F36/F45,L36="Grupo 5",F36/F46) -> 0 | H36: =IFS(L36="Grupo 0",0,L36="Grupo 1",F36/E42,L36="Grupo 2",F36/E43,L36="Grupo 3",F36/E44,L36="Grupo 4",F36/E45,L36="Grupo 5",F36/E46) -> 0 | I36: =IFS(L36="Grupo 0",0,L36="Grupo 1",M36/M42,L36="Grupo 2",M36/M43,L36="Grupo 3",M36/M44,L36="Grupo 4",M36/M45,L36="Grupo 5",M36/M46) -> 0 | J36: =IFS(L36="Grupo 0",0,L36="Grupo 1",K36/K42,L36="Grupo 2",K36/K43,L36="Grupo 3",K36/K44,L36="Grupo 4",K36/K45,L36="Grupo 5",K36/K46) -> 0 | K36: =IFS(L36="Grupo 0",0,L36="Grupo 1",(E42*I36-F36)*N36,L36="Grupo 2",(E43*I36-F36)*N36,L36="Grupo 3",(E44*I36-F36)*N36,L36="Grupo 4",(E45*I36-F36)*N36,L36="Grupo 5",(E46*I36-F36)*N36) -> 0 | L36: Grupo 0 | N36: =IF(I36<H36,0,1) -> 1 | O36: =IFS(L36="Grupo 0",0,L36="Grupo 1",J36*D42,L36="Grupo 2",J36*D43,L36="Grupo 3",J36*D44,L36="Grupo 4",J36*D45,L36="Grupo 5",J36*D46) -> 0
A37: 36 | F37: =D37*E37 -> 0 | G37: =IFS(L37="Grupo 0",0,L37="Grupo 1",F37/F42,L37="Grupo 2",F37/F43,L37="Grupo 3",F37/F44,L37="Grupo 4",F37/F45,L37="Grupo 5",F37/F46) -> 0 | H37: =IFS(L37="Grupo 0",0,L37="Grupo 1",F37/E42,L37="Grupo 2",F37/E43,L37="Grupo 3",F37/E44,L37="Grupo 4",F37/E45,L37="Grupo 5",F37/E46) -> 0 | I37: =IFS(L37="Grupo 0",0,L37="Grupo 1",M37/M42,L37="Grupo 2",M37/M43,L37="Grupo 3",M37/M44,L37="Grupo 4",M37/M45,L37="Grupo 5",M37/M46) -> 0 | J37: =IFS(L37="Grupo 0",0,L37="Grupo 1",K37/K42,L37="Grupo 2",K37/K43,L37="Grupo 3",K37/K44,L37="Grupo 4",K37/K45,L37="Grupo 5",K37/K46) -> 0 | K37: =IFS(L37="Grupo 0",0,L37="Grupo 1",(E42*I37-F37)*N37,L37="Grupo 2",(E43*I37-F37)*N37,L37="Grupo 3",(E44*I37-F37)*N37,L37="Grupo 4",(E45*I37-F37)*N37,L37="Grupo 5",(E46*I37-F37)*N37) -> 0 | L37: Grupo 0 | N37: =IF(I37<H37,0,1) -> 1 | O37: =IFS(L37="Grupo 0",0,L37="Grupo 1",J37*D42,L37="Grupo 2",J37*D43,L37="Grupo 3",J37*D44,L37="Grupo 4",J37*D45,L37="Grupo 5",J37*D46) -> 0
A38: 37 | F38: =D38*E38 -> 0 | G38: =IFS(L38="Grupo 0",0,L38="Grupo 1",F38/F42,L38="Grupo 2",F38/F43,L38="Grupo 3",F38/F44,L38="Grupo 4",F38/F45,L38="Grupo 5",F38/F46) -> 0 | H38: =IFS(L38="Grupo 0",0,L38="Grupo 1",F38/E42,L38="Grupo 2",F38/E43,L38="Grupo 3",F38/E44,L38="Grupo 4",F38/E45,L38="Grupo 5",F38/E46) -> 0 | I38: =IFS(L38="Grupo 0",0,L38="Grupo 1",M38/M42,L38="Grupo 2",M38/M43,L38="Grupo 3",M38/M44,L38="Grupo 4",M38/M45,L38="Grupo 5",M38/M46) -> 0 | J38: =IFS(L38="Grupo 0",0,L38="Grupo 1",K38/K42,L38="Grupo 2",K38/K43,L38="Grupo 3",K38/K44,L38="Grupo 4",K38/K45,L38="Grupo 5",K38/K46) -> 0 | K38: =IFS(L38="Grupo 0",0,L38="Grupo 1",(E42*I38-F38)*N38,L38="Grupo 2",(E43*I38-F38)*N38,L38="Grupo 3",(E44*I38-F38)*N38,L38="Grupo 4",(E45*I38-F38)*N38,L38="Grupo 5",(E46*I38-F38)*N38) -> 0 | L38: Grupo 0 | N38: =IF(I38<H38,0,1) -> 1 | O38: =IFS(L38="Grupo 0",0,L38="Grupo 1",J38*D42,L38="Grupo 2",J38*D43,L38="Grupo 3",J38*D44,L38="Grupo 4",J38*D45,L38="Grupo 5",J38*D46) -> 0
A39: 38 | F39: =D39*E39 -> 0 | G39: =IFS(L39="Grupo 0",0,L39="Grupo 1",F39/F42,L39="Grupo 2",F39/F43,L39="Grupo 3",F39/F44,L39="Grupo 4",F39/F45,L39="Grupo 5",F39/F46) -> 0 | H39: =IFS(L39="Grupo 0",0,L39="Grupo 1",F39/E42,L39="Grupo 2",F39/E43,L39="Grupo 3",F39/E44,L39="Grupo 4",F39/E45,L39="Grupo 5",F39/E46) -> 0 | I39: =IFS(L39="Grupo 0",0,L39="Grupo 1",M39/M42,L39="Grupo 2",M39/M43,L39="Grupo 3",M39/M44,L39="Grupo 4",M39/M45,L39="Grupo 5",M39/M46) -> 0 | J39: =IFS(L39="Grupo 0",0,L39="Grupo 1",K39/K42,L39="Grupo 2",K39/K43,L39="Grupo 3",K39/K44,L39="Grupo 4",K39/K45,L39="Grupo 5",K39/K46) -> 0 | K39: =IFS(L39="Grupo 0",0,L39="Grupo 1",(E42*I39-F39)*N39,L39="Grupo 2",(E43*I39-F39)*N39,L39="Grupo 3",(E44*I39-F39)*N39,L39="Grupo 4",(E45*I39-F39)*N39,L39="Grupo 5",(E46*I39-F39)*N39) -> 0 | L39: Grupo 0 | N39: =IF(I39<H39,0,1) -> 1 | O39: =IFS(L39="Grupo 0",0,L39="Grupo 1",J39*D42,L39="Grupo 2",J39*D43,L39="Grupo 3",J39*D44,L39="Grupo 4",J39*D45,L39="Grupo 5",J39*D46) -> 0
A40: 39 | F40: =D40*E40 -> 0 | G40: =IFS(L40="Grupo 0",0,L40="Grupo 1",F40/F42,L40="Grupo 2",F40/F43,L40="Grupo 3",F40/F44,L40="Grupo 4",F40/F45,L40="Grupo 5",F40/F46) -> 0 | H40: =IFS(L40="Grupo 0",0,L40="Grupo 1",F40/E42,L40="Grupo 2",F40/E43,L40="Grupo 3",F40/E44,L40="Grupo 4",F40/E45,L40="Grupo 5",F40/E46) -> 0 | I40: =IFS(L40="Grupo 0",0,L40="Grupo 1",M40/M42,L40="Grupo 2",M40/M43,L40="Grupo 3",M40/M44,L40="Grupo 4",M40/M45,L40="Grupo 5",M40/M46) -> 0 | J40: =IFS(L40="Grupo 0",0,L40="Grupo 1",K40/K42,L40="Grupo 2",K40/K43,L40="Grupo 3",K40/K44,L40="Grupo 4",K40/K45,L40="Grupo 5",K40/K46) -> 0 | K40: =IFS(L40="Grupo 0",0,L40="Grupo 1",(E42*I40-F40)*N40,L40="Grupo 2",(E43*I40-F40)*N40,L40="Grupo 3",(E44*I40-F40)*N40,L40="Grupo 4",(E45*I40-F40)*N40,L40="Grupo 5",(E46*I40-F40)*N40) -> 0 | L40: Grupo 0 | N40: =IF(I40<H40,0,1) -> 1 | O40: =IFS(L40="Grupo 0",0,L40="Grupo 1",J40*D42,L40="Grupo 2",J40*D43,L40="Grupo 3",J40*D44,L40="Grupo 4",J40*D45,L40="Grupo 5",J40*D46) -> 0
B41: TOTAL | C41: =SUM(B42:B46) -> 0.2 | D41: =F41+N1 -> 18166.434 | E41: =SUM(E3:E40) -> 373885.29 | F41: =SUM(F2:F40) -> 14891.838 | I41: =SUM(I2:I40) -> 3 | J41: =SUM(J2:J40) -> 3 | K41: =SUM(K2:K40) -> 6048.8506 | M41: =SUM(M2:M40) -> 47 | O41: =SUM(O2:O40) -> 3274.5956 | P41: =SUM(P2:P40) -> 1
A42: G1 | B42: ='Distruibuição de aporte'!B3 -> 0.05 | C42: Reserva Inv | D42: ='Distruibuição de aporte'!H3 -> 1154.8188 | E42: =D42+F42 -> 1154.8288 | F42: =SUMIF(L2:L40,"Grupo 1",F2:F40) -> 0.01 | G42: =SUMIF(L2:L40,"Grupo 1",G2:G40) -> 1 | K42: =SUMIF(L2:L40,"Grupo 1",K2:K40) -> 1154.8188 | M42: =SUMIF(L2:L40,"Grupo 1",M2:M40) -> 5
A43: G2 | B43: ='Distruibuição de aporte'!B4 -> 0.05 | C43: Reserva Val | D43: ='Distruibuição de aporte'!H4 -> 974.87673 | E43: =D43+F43 -> 2967.6747 | F43: =SUMIF(L2:L40,"Grupo 2",F2:F40) -> 1992.7979 | G43: =SUMIF(L2:L40,"Grupo 2",G2:G40) -> 1 | K43: =SUMIF(L2:L40,"Grupo 2",K2:K40) -> 974.87673 | M43: =SUMIF(L2:L40,"Grupo 2",M2:M40) -> 10
A44: G3 | B44: ='Distruibuição de aporte'!B5 -> 0.1 | C44: Renda fixa | D44: ='Distruibuição de aporte'!H5 -> 1144.9 | E44: =D44+F44 -> 14043.93 | F44: =SUMIF(L2:L40,"Grupo 3",F2:F40) -> 12899.03 | G44: =SUMIF(L2:L40,"Grupo 3",G2:G40) -> 1 | K44: =SUMIF(L2:L40,"Grupo 3",K2:K40) -> 3919.155 | M44: =SUMIF(L2:L40,"Grupo 3",M2:M40) -> 20
A45: G4 | B45: 0 | E45: =D45+F45 -> 0 | F45: =SUMIF(L2:L40,"Grupo 4",F2:F40) -> 0 | G45: =SUMIF(L2:L40,"Grupo 4",G2:G40) -> 0 | K45: =SUMIF(L2:L40,"Grupo 4",K2:K40) -> 0 | M45: =SUMIF(L2:L40,"Grupo 4",M2:M40) -> 0
A46: G5 | B46: 0 | E46: =D46+F46 -> 0 | F46: =SUMIF(L2:L40,"Grupo 5",F2:F40) -> 0 | G46: =SUMIF(L2:L40,"Grupo 5",G2:G40) -> 0 | K46: =SUMIF(L2:L40,"Grupo 5",K2:K40) -> 0 | M46: =SUMIF(L2:L40,"Grupo 5",M2:M40) -> 0 | O46: 1

Sheet FII
B1: Fundos | C1: Setor | D1: Quantidade | E1: Cotação | F1: Saldo | G1: %Carteira | H1: % Ideal | I1: Bal | J1: Bal | K1: Aporte: | L1: ='Distruibuição de aporte'!H6 -> 0 | M1: Vou aportar? | N1: Aporte ideal por ativo | O1: Quantidade | Q1: Valores total | R1: Ultimos prov. | S1: Somat prov.
A2: 1 | B2: BTLG11 | C2: Logistica | D2: 93 | E2: =IFERROR(__xludf.DUMMYFUNCTION("GOOGLEFINANCE(B2)"),103.8) -> 103.8 | F2: =D2*E2 -> 9653.4 | G2: =F2/F23 -> 0.060613032 | H2: =K2/K23 -> 0.18181818 | I2: =J2/J23 -> 0.12491586 | J2: =IF(L2=1,E24*H2-F2,0) -> 19303.469 | K2: =IF(Balanceamentos!C1>=0,Balanceamentos!C15,0) -> -2 | L2: =IFS(M2="Não",0,F2/E24<H2,1,F2/E24>H2,0) -> 1 | M2: Sim | N2: =I2*L1 -> 0 | O2: =IF(N2>0,N2/E2,0) -> 0 | Q2: =IF(O2=0, "" , E2*INT(O2)) | R2: 0.78 | S2: =IF(O2=0, "" , R2*INT(O2))
A3: 2 | B3: XPLG11 | C3: Logistica | D3: 94 | E3: =IFERROR(__xludf.DUMMYFUNCTION("GOOGLEFINANCE(B3)"),101.66) -> 101.66 | F3: =D3*E3 -> 9556.04 | G3: =F3/F23 -> 0.060001715 | H3: =K3/K23 -> 0.90909091 | I3: =J3/J23 -> 0.87508414 | J3: =IF(L3=1,E24*H3-F3,0) -> 135228.31 | K3: =Balanceamentos!D15 -> -10 | L3: =IFS(M3="Não",0,F3/E24<H3,1,F3/E24>H3,0) -> 1 | M3: Sim | N3: =I3*L1 -> 0 | O3: =IF(N3>0,N3/E3,0) -> 0 | Q3: =IF(O3=0, "" , E3*INT(O3)) | R3: 0.82 | S3: =IF(O3=0, "" , R3*INT(O3))
A4: 3 | B4: HGLG11 | C4: Logistica | D4: 59 | E4: =IFERROR(__xludf.DUMMYFUNCTION("GOOGLEFINANCE(B4)"),155.6) -> 155.6 | F4: =D4*E4 -> 9180.4 | G4: =F4/F23 -> 0.057643098 | H4: =K4/K23 -> -0.090909091 | I4: =J4/J23 -> 0 | J4: =IF(L4=1,E24*H4-F4,0) -> 0 | K4: =Balanceamentos!E15 -> 1 | L4: =IFS(M4="Não",0,F4/E24<H4,1,F4/E24>H4,0) -> 0 | M4: Sim | N4: =I4*L1 -> 0 | O4: =IF(N4>0,N4/E4,0) -> 0 | Q4: =IF(O4=0, "" , E4*INT(O4)) | R4: 1.1 | S4: =IF(O4=0, "" , R4*INT(O4))
A5: 4 | B5: GARE11 | C5: Logistica | D5: 1057 | E5: =IFERROR(__xludf.DUMMYFUNCTION("GOOGLEFINANCE(B5)"),8.36) -> 8.36 | F5: =D5*E5 -> 8836.52 | G5: =F5/F23 -> 0.055483899 | H5: =K5/K23 -> 0 | I5: =J5/J23 -> 0 | J5: =IF(L5=1,E24*H5-F5,0) -> 0 | K5: =Balanceamentos!F15 -> 0 | L5: =IFS(M5="Não",0,F5/E24<H5,1,F5/E24>H5,0) -> 0 | M5: Sim | N5: =I5*L1 -> 0 | O5: =IF(N5>0,N5/E5,0) -> 0 | Q5: =IF(O5=0, "" , E5*INT(O5)) | R5: 0.083 | S5: =IF(O5=0, "" , R5*INT(O5))
A6: 5 | B6: GGRC11 | C6: Logistica | D6: 909 | E6: =IFERROR(__xludf.DUMMYFUNCTION("GOOGLEFINANCE(B6)"),10.18) -> 10.18 | F6: =D6*E6 -> 9253.62 | G6: =F6/F23 -> 0.058102841 | H6: =K6/K23 -> 0 | I6: =J6/J23 -> 0 | J6: =IF(L6=1,E24*H6-F6,0) -> 0 | K6: =Balanceamentos!G15 -> 0 | L6: =IFS(M6="Não",0,F6/E24<H6,1,F6/E24>H6,0) -> 0 | M6: Sim | N6: =I6*L1 -> 0 | O6: =IF(N6>0,N6/E6,0) -> 0 | Q6: =IF(O6=0, "" , E6*INT(O6)) | R6: 0.1 | S6: =IF(O6=0, "" , R6*INT(O6))
A7: 6 | B7: HGBS11 | C7: Shopping | D7: 460 | E7: =IFERROR(__xludf.DUMMYFUNCTION("GOOGLEFINANCE(B7)"),20.23) -> 20.23 | F7: =D7*E7 -> 9305.8 | G7: =F7/F23 -> 0.058430476 | H7: =K7/K23 -> 0 | I7: =J7/J23 -> 0 | J7: =IF(L7=1,E24*H7-F7,0) -> 0 | K7: =Balanceamentos!H15 -> 0 | L7: =IFS(M7="Não",0,F7/E24<H7,1,F7/E24>H7,0) -> 0 | M7: Sim | N7: =I7*L1 -> 0 | O7: =IF(N7>0,N7/E7,0) -> 0 | Q7: =IF(O7=0, "" , E7*INT(O7)) | R7: 1.6 | S7: =IF(O7=0, "" , R7*INT(O7))
A8: 7 | B8: HSML11 | C8: Shopping | D8: 109 | E8: =IFERROR(__xludf.DUMMYFUNCTION("GOOGLEFINANCE(B8)"),95.0) -> 95 | F8: =D8*E8 -> 10355 | G8: =F8/F23 -> 0.06501833 | H8: =K8/K23 -> 0 | I8: =J8/J23 -> 0 | J8: =IF(L8=1,E24*H8-F8,0) -> 0 | K8: =Balanceamentos!I15 -> 0 | L8: =IFS(M8="Não",0,F8/E24<H8,1,F8/E24>H8,0) -> 0 | M8: Sim | N8: =I8*L1 -> 0 | O8: =IF(N8>0,N8/E8,0) -> 0 | Q8: =IF(O8=0, "" , E8*INT(O8)) | R8: 0.65 | S8: =IF(O8=0, "" , R8*INT(O8))
A9: 8 | B9: HGRU11 | C9: Varejo | D9: 76 | E9: =IFERROR(__xludf.DUMMYFUNCTION("GOOGLEFINANCE(B9)"),129.27) -> 129.27 | F9: =D9*E9 -> 9824.52 | G9: =F9/F23 -> 0.061687483 | H9: =K9/K23 -> 0 | I9: =J9/J23 -> 0 | J9: =IF(L9=1,E24*H9-F9,0) -> 0 | K9: =Balanceamentos!J15 -> 0 | L9: =IFS(M9="Não",0,F9/E24<H9,1,F9/E24>H9,0) -> 0 | M9: Sim | N9: =I9*L1 -> 0 | O9: =IF(N9>0,N9/E9,0) -> 0 | Q9: =IF(O9=0, "" , E9*INT(O9)) | R9: 0.9 | S9: =IF(O9=0, "" , R9*INT(O9))
A10: 9 | B10: SEQR11 | C10: Varejo | D10: 186 | E10: =IFERROR(__xludf.DUMMYFUNCTION("GOOGLEFINANCE(B10)"),55.69) -> 55.69 | F10: =D10*E10 -> 10358.34 | G10: =F10/F23 -> 0.065039302 | H10: =K10/K23 -> 0 | I10: =J10/J23 -> 0 | J10: =IF(L10=1,E24*H10-F10,0) -> 0 | K10: =Balanceamentos!K15 -> 0 | L10: =IFS(M10="Não",0,F10/E24<H10,1,F10/E24>H10,0) -> 0 | M10: Sim | N10: =I10*L1 -> 0 | O10: =IF(N10>0,N10/E10,0) -> 0 | Q10: =IF(O10=0, "" , E10*INT(O10)) | R10: 0.5823 | S10: =IF(O10=0, "" , R10*INT(O10))
A11: 10 | B11: TRXF11 | C11: Varejo | D11: 90 | E11: =IFERROR(__xludf.DUMMYFUNCTION("GOOGLEFINANCE(B11)"),91.76) -> 91.76 | F11: =D11*E11 -> 8258.4 | G11: =F11/F23 -> 0.051853923 | H11: =K11/K23 -> 0 | I11: =J11/J23 -> 0 | J11: =IF(L11=1,E24*H11-F11,0) -> 0 | K11: =Balanceamentos!L15 -> 0 | L11: =IFS(M11="Não",0,F11/E24<H11,1,F11/E24>H11,0) -> 0 | M11: Sim | N11: =I11*L1 -> 0 | O11: =IF(N11>0,N11/E11,0) -> 0 | Q11: =IF(O11=0, "" , E11*INT(O11)) | R11: 0.93 | S11: =IF(O11=0, "" , R11*INT(O11))
A12: 11 | B12: RZAT11 | C12: Varejo | D12: 120 | E12: =IFERROR(__xludf.DUMMYFUNCTION("GOOGLEFINANCE(B12)"),90.06) -> 90.06 | F12: =D12*E12 -> 10807.2 | G12: =F12/F23 -> 0.067857663 | H12: =K12/K23 -> 0 | I12: =J12/J23 -> 0 | J12: =IF(L12=1,E24*H12-F12,0) -> 0 | K12: =Balanceamentos!M15 -> 0 | L12: =IFS(M12="Não",0,F12/E24<H12,1,F12/E24>H12,0) -> 0 | M12: Sim | N12: =I12*L1 -> 0 | O12: =IF(N12>0,N12/E12,0) -> 0 | Q12: =IF(O12=0, "" , E12*INT(O12)) | R12: 1.1 | S12: =IF(O12=0, "" , R12*INT(O12))
A13: 12 | B13: KNCR11 | C13: Papel | D13: 10 | E13: =IFERROR(__xludf.DUMMYFUNCTION("GOOGLEFINANCE(B13)"),105.03) -> 105.03 | F13: =D13*E13 -> 1050.3 | G13: =F13/F23 -> 0.0065947612 | H13: =K13/K23 -> 0 | I13: =J13/J23 -> 0 | J13: =IF(L13=1,E24*H13-F13,0) -> 0 | K13: =Balanceamentos!N15 -> 0 | L13: =IFS(M13="Não",0,F13/E24<H13,1,F13/E24>H13,0) -> 0 | M13: Sim | N13: =I13*L1 -> 0 | O13: =IF(N13>0,N13/E13,0) -> 0 | Q13: =IF(O13=0, "" , E13*INT(O13)) | R13: 0.95 | S13: =IF(O13=0, "" , R13*INT(O13))
A14: 13 | B14: KNSC11 | C14: Papel | D14: 224 | E14: =IFERROR(__xludf.DUMMYFUNCTION("GOOGLEFINANCE(B14)"),8.88) -> 8.88 | F14: =D14*E14 -> 1989.12 | G14: =F14/F23 -> 0.012489547 | H14: =K14/K23 -> 0 | I14: =J14/J23 -> 0 | J14: =IF(L14=1,E24*H14-F14,0) -> 0 | K14: =Balanceamentos!O15 -> 0 | L14: =IFS(M14="Não",0,F14/E24<H14,1,F14/E24>H14,0) -> 0 | M14: Sim | N14: =I14*L1 -> 0 | O14: =IF(N14>0,N14/E14,0) -> 0 | Q14: =IF(O14=0, "" , E14*INT(O14)) | R14: 0.08 | S14: =IF(O14=0, "" , R14*INT(O14))
A15: 14 | B15: MXRF11 | C15: Papel | D15: 305 | E15: =IFERROR(__xludf.DUMMYFUNCTION("GOOGLEFINANCE(B15)"),9.72) -> 9.72 | F15: =D15*E15 -> 2964.6 | G15: =F15/F23 -> 0.018614519 | H15: =K15/K23 -> 0 | I15: =J15/J23 -> 0 | J15: =IF(L15=1,E24*H15-F15,0) -> 0 | K15: =Balanceamentos!P15 -> 0 | L15: =IFS(M15="Não",0,F15/E24<H15,1,F15/E24>H15,0) -> 0 | M15: Sim | N15: =I15*L1 -> 0 | O15: =IF(N15>0,N15/E15,0) -> 0 | Q15: =IF(O15=0, "" , E15*INT(O15)) | R15: 0.1 | S15: =IF(O15=0, "" , R15*INT(O15))
A16: 15 | B16: PCIP11 | C16: Papel | D16: 62 | E16: =IFERROR(__xludf.DUMMYFUNCTION("GOOGLEFINANCE(""BVMF:PCIP11"")"),85.5) -> 85.5 | F16: =D16*E16 -> 5301 | G16: =F16/F23 -> 0.033284613 | H16: =K16/K23 -> 0 | I16: =J16/J23 -> 0 | J16: =IF(L16=1,E24*H16-F16,0) -> 0 | K16: =Balanceamentos!Q15 -> 0 | L16: =IFS(M16="Não",0,F16/E24<H16,1,F16/E24>H16,0) -> 0 | M16: Sim | N16: =I16*L1 -> 0 | O16: =IF(N16>0,N16/E16,0) -> 0 | Q16: =IF(O16=0, "" , E16*INT(O16)) | R16: 0.9 | S16: =IF(O16=0, "" , R16*INT(O16))
A17: 16 | B17: CPTI11 | C17: Infra | D17: 105 | E17: =IFERROR(__xludf.DUMMYFUNCTION("GOOGLEFINANCE(""BVMF:CPTI11"")"),89.45) -> 89.45 | F17: =D17*E17 -> 9392.25 | G17: =F17/F23 -> 0.058973289 | H17: =K17/K23 -> 0 | I17: =J17/J23 -> 0 | J17: =IF(L17=1,E24*H17-F17,0) -> 0 | K17: =Balanceamentos!R15 -> 0 | L17: =IFS(M17="Não",0,F17/E24<H17,1,F17/E24>H17,0) -> 0 | M17: Sim | N17: =I17*L1 -> 0 | O17: =IF(N17>0,N17/E17,0) -> 0 | Q17: =IF(O17=0, "" , E17*INT(O17)) | R17: 1 | S17: =IF(O17=0, "" , R17*INT(O17))
A18: 17 | B18: JURO11 | C18: Infra | D18: 93 | E18: =IFERROR(__xludf.DUMMYFUNCTION("GOOGLEFINANCE(B18)"),102.99) -> 102.99 | F18: =D18*E18 -> 9578.07 | G18: =F18/F23 -> 0.06014004 | H18: =K18/K23 -> 0 | I18: =J18/J23 -> 0 | J18: =IF(L18=1,E24*H18-F18,0) -> 0 | K18: =Balanceamentos!S15 -> 0 | L18: =IFS(M18="Não",0,F18/E24<H18,1,F18/E24>H18,0) -> 0 | M18: Sim | N18: =I18*L1 -> 0 | O18: =IF(N18>0,N18/E18,0) -> 0 | Q18: =IF(O18=0, "" , E18*INT(O18)) | R18: 1 | S18: =IF(O18=0, "" , R18*INT(O18))
A19: 18 | B19: RZTR11 | C19: Agro | D19: 101 | E19: =IFERROR(__xludf.DUMMYFUNCTION("GOOGLEFINANCE(""BVMF:RZTR11"")"),95.26) -> 95.26 | F19: =D19*E19 -> 9621.26 | G19: =F19/F23 -> 0.060411227 | H19: =K19/K23 -> 0 | I19: =J19/J23 -> 0 | J19: =IF(L19=1,E24*H19-F19,0) -> 0 | K19: =Balanceamentos!T15 -> 0 | L19: =IFS(M19="Não",0,F19/E24<H19,1,F19/E24>H19,0) -> 0 | M19: Sim | N19: =I19*L1 -> 0 | O19: =IF(N19>0,N19/E19,0) -> 0 | Q19: =IF(O19=0, "" , E19*INT(O19)) | R19: 1.05 | S19: =IF(O19=0, "" , R19*INT(O19))
A20: 19 | B20: SNAG11 | C20: Fiagro | D20: 518 | E20: =IFERROR(__xludf.DUMMYFUNCTION("GOOGLEFINANCE(B20)"),10.68) -> 10.68 | F20: =D20*E20 -> 5532.24 | G20: =F20/F23 -> 0.034736553 | H20: =K20/K23 -> 0 | I20: =J20/J23 -> 0 | J20: =IF(L20=1,E24*H20-F20,0) -> 0 | K20: =Balanceamentos!U15 -> 0 | L20: =IFS(M20="Não",0,F20/E24<H20,1,F20/E24>H20,0) -> 0 | M20: Sim | N20: =I20*L1 -> 0 | O20: =IF(N20>0,N20/E20,0) -> 0 | Q20: =IF(O20=0, "" , E20*INT(O20)) | R20: 0.1 | S20: =IF(O20=0, "" , R20*INT(O20))
A21: 20 | B21: SNEL11 | C21: Energia | D21: 990 | E21: =IFERROR(__xludf.DUMMYFUNCTION("GOOGLEFINANCE(B21)"),8.53) -> 8.53 | F21: =D21*E21 -> 8444.7 | G21: =F21/F23 -> 0.053023688 | H21: =K21/K23 -> 0 | I21: =J21/J23 -> 0 | J21: =IF(L21=1,E24*H21-F21,0) -> 0 | K21: =Balanceamentos!V15 -> 0 | L21: =IFS(M21="Não",0,F21/E24<H21,1,F21/E24>H21,0) -> 0 | M21: Sim | N21: =I21*L1 -> 0 | O21: =IF(N21>0,N21/E21,0) -> 0 | Q21: =IF(O21=0, "" , E21*INT(O21)) | R21: 0.1 | S21: =IF(O21=0, "" , R21*INT(O21))
A22: 21 | I22: =J22/J23 -> 0 | J22: =IF(L22=1,E24*H22-F22,0) -> 0 | K22: =Balanceamentos!W15 -> 0 | L22: =IFS(M22="Não",0,F22/E24<H22,1,F22/E24>H22,0) -> 0 | M22: Não | N22: =I22*L1 -> 0 | O22: =IF(N22>0,N22/E22,0) -> 0 | Q22: =IF(O22=0, "" , E22*INT(O22)) | S22: =IF(O22=0, "" , R22*INT(O22))
B23: TOTAL | E23: =SUM(E2:E22) -> 1377.65 | F23: =SUM(F2:F22) -> 159262.78 | G23: =SUM(G2:G22) -> 1 | H23: =SUM(H2:H22) -> 1 | I23: =SUM(I2:I22) -> 1 | J23: =SUM(J2:J22) -> 154531.77 | K23: =SUM(K2:K22) -> -11 | L23: A aportar: | M23: =COUNTIF(M2:M22,"SIM") -> 20 | N23: =SUM(N2:N22) -> 0 | P23: Soma | Q23: =SUM(Q2:Q22) -> 0 | S23: =SUM(S2:S22) -> 0
D24: =L1+F24 -> 19209.44 | E24: =L1+F23 -> 159262.78 | F24: =SUMIFS(F2:F22,L2:L22,1) -> 19209.44 | K24: =SUMIF(L2:L22,1,K2:K22) -> -12 | S24: =S23/Q23 -> #DIV/0!

Sheet Ações
B1: Ação | C1: Quantidade | D1: Cotação | E1: Saldo | F1: %Carteira | G1: % Ideal | H1: Bal | I1: Bal | K1: Aporte: | L1: ='Distruibuição de aporte'!H7 -> 4428.5082 | M1: Aporte ideal por ativo | N1: Quantidade
A2: 1 | B2: VALE3 | C2: 54 | D2: =IFERROR(__xludf.DUMMYFUNCTION("GOOGLEFINANCE(""BVMF:VALE3"")"),77.13) -> 77.13 | E2: =C2*D2 -> 4165.02 | F2: =E2/E102 -> 0.10289023 | G2: =IFS(J2="Grupo 0",0,J2="Grupo 1",K2*H105/100,J2="Grupo 2",K2*I105/100,J2="Grupo 3",K2*J105/100,J2="Grupo 4",K2*K105/100) -> 0.031428571 | H2: =IF(L2=1,I2/I102,0) -> 0 | I2: =IF(L2=1,C102*G2-E2,0) -> 0 | J2: Grupo 1 | K2: =IF(Balanceamentos!C37>0,Balanceamentos!C37,0) -> 11 | L2: =IF(G2>E2/C102,1,0) -> 0 | M2: =IF(L2=1,H2*L1,0) -> 0 | N2: =IF(M2>0,M2/D2,0) -> 0
A3: 2 | B3: BBAS3 | C3: 73 | D3: =IFERROR(__xludf.DUMMYFUNCTION("GOOGLEFINANCE(""BVMF:BBAS3"")"),23.41) -> 23.41 | E3: =C3*D3 -> 1708.93 | F3: =E3/E102 -> 0.04221641 | G3: =IFS(J3="Grupo 0",0,J3="Grupo 1",K3*H105/100,J3="Grupo 2",K3*I105/100,J3="Grupo 3",K3*J105/100,J3="Grupo 4",K3*K105/100) -> 0.031428571 | H3: =IF(L3=1,I3/I102,0) -> 0 | I3: =IF(L3=1,C102*G3-E3,0) -> 0 | J3: Grupo 1 | K3: =IF(Balanceamentos!D37>0,Balanceamentos!D37,0) -> 11 | L3: =IF(G3>E3/C102,1,0) -> 0 | M3: =IF(L3=1,H3*L1,0) -> 0 | N3: =IF(M3>0,M3/D3,0) -> 0
A4: 3 | B4: PETR4 | C4: 37 | D4: =IFERROR(__xludf.DUMMYFUNCTION("GOOGLEFINANCE(B4)"),47.0) -> 47 | E4: =C4*D4 -> 1739 | F4: =E4/E102 -> 0.042959242 | G4: =IFS(J4="Grupo 0",0,J4="Grupo 1",K4*H105/100,J4="Grupo 2",K4*I105/100,J4="Grupo 3",K4*J105/100,J4="Grupo 4",K4*K105/100) -> 0.025714286 | H4: =IF(L4=1,I4/I102,0) -> 0 | I4: =IF(L4=1,C102*G4-E4,0) -> 0 | J4: Grupo 1 | K4: =IF(Balanceamentos!E37>0,Balanceamentos!E37,0) -> 9 | L4: =IF(G4>E4/C102,1,0) -> 0 | M4: =IF(L4=1,H4*L1,0) -> 0 | N4: =IF(M4>0,M4/D4,0) -> 0
A5: 4 | B5: CSMG3 | C5: 11 | D5: =IFERROR(__xludf.DUMMYFUNCTION("GOOGLEFINANCE(B5)"),54.2) -> 54.2 | E5: =C5*D5 -> 596.2 | F5: =E5/E102 -> 0.014728177 | G5: =IFS(J5="Grupo 0",0,J5="Grupo 1",K5*H105/100,J5="Grupo 2",K5*I105/100,J5="Grupo 3",K5*J105/100,J5="Grupo 4",K5*K105/100) -> 0.006 | H5: =IF(L5=1,I5/I102,0) -> 0 | I5: =IF(L5=1,C102*G5-E5,0) -> 0 | J5: Grupo 3 | K5: =IF(Balanceamentos!F37>0,Balanceamentos!F37,0) -> 5 | L5: =IF(G5>E5/C102,1,0) -> 0 | M5: =IF(L5=1,H5*L1,0) -> 0 | N5: =IF(M5>0,M5/D5,0) -> 0
A6: 5 | B6: CMIG4 | C6: 21 | D6: =IFERROR(__xludf.DUMMYFUNCTION("GOOGLEFINANCE(B6)"),11.81) -> 11.81 | E6: =C6*D6 -> 248.01 | F6: =E6/E102 -> 0.0061266944 | G6: =IFS(J6="Grupo 0",0,J6="Grupo 1",K6*H105/100,J6="Grupo 2",K6*I105/100,J6="Grupo 3",K6*J105/100,J6="Grupo 4",K6*K105/100) -> 0 | H6: =IF(L6=1,I6/I102,0) -> 0 | I6: =IF(L6=1,C102*G6-E6,0) -> 0 | J6: Grupo 0 | K6: 0 | L6: =IF(G6>E6/C102,1,0) -> 0 | M6: =IF(L6=1,H6*L1,0) -> 0 | N6: =IF(M6>0,M6/D6,0) -> 0
A7: 6 | B7: ITSA4 | C7: 7 | D7: =IFERROR(__xludf.DUMMYFUNCTION("GOOGLEFINANCE(B7)"),13.37) -> 13.37 | E7: =C7*D7 -> 93.59 | F7: =E7/E102 -> 0.0023119928 | G7: =IFS(J7="Grupo 0",0,J7="Grupo 1",K7*H105/100,J7="Grupo 2",K7*I105/100,J7="Grupo 3",K7*J105/100,J7="Grupo 4",K7*K105/100) -> 0 | H7: =IF(L7=1,I7/I102,0) -> 0 | I7: =IF(L7=1,C102*G7-E7,0) -> 0 | J7: Grupo 0 | K7: 0 | L7: =IF(G7>E7/C102,1,0) -> 0 | M7: =IF(L7=1,H7*L1,0) -> 0 | N7: =IF(M7>0,M7/D7,0) -> 0
A8: 7 | B8: ISAE3 | C8: 14 | D8: =IFERROR(__xludf.DUMMYFUNCTION("GOOGLEFINANCE(B8)"),32.61) -> 32.61 | E8: =C8*D8 -> 456.54 | F8: =E8/E102 -> 0.011278098 | G8: =IFS(J8="Grupo 0",0,J8="Grupo 1",K8*H105/100,J8="Grupo 2",K8*I105/100,J8="Grupo 3",K8*J105/100,J8="Grupo 4",K8*K105/100) -> 0.012162162 | H8: =IF(L8=1,I8/I102,0) -> 0.0097973736 | I8: =IF(L8=1,C102*G8-E8,0) -> 89.647356 | J8: Grupo 2 | K8: =IF(Balanceamentos!G37>0,Balanceamentos!G37,0) -> 9 | L8: =IF(G8>E8/C102,1,0) -> 1 | M8: =IF(L8=1,H8*L1,0) -> 43.387749 | N8: =IF(M8>0,M8/D8,0) -> 1.3305044
A9: 8 | B9: UNIP6 | C9: 1 | D9: =IFERROR(__xludf.DUMMYFUNCTION("GOOGLEFINANCE(B9)"),63.15) -> 63.15 | E9: =C9*D9 -> 63.15 | F9: =E9/E102 -> 0.0015600208 | G9: =IFS(J9="Grupo 0",0,J9="Grupo 1",K9*H105/100,J9="Grupo 2",K9*I105/100,J9="Grupo 3",K9*J105/100,J9="Grupo 4",K9*K105/100) -> 0 | H9: =IF(L9=1,I9/I102,0) -> 0 | I9: =IF(L9=1,C102*G9-E9,0) -> 0 | J9: Grupo 0 | K9: 0 | L9: =IF(G9>E9/C102,1,0) -> 0 | M9: =IF(L9=1,H9*L1,0) -> 0 | N9: =IF(M9>0,M9/D9,0) -> 0
A10: 9 | B10: BBSE3 | C10: 31 | D10: =IFERROR(__xludf.DUMMYFUNCTION("GOOGLEFINANCE(B10)"),34.52) -> 34.52 | E10: =C10*D10 -> 1070.12 | F10: =E10/E102 -> 0.026435621 | G10: =IFS(J10="Grupo 0",0,J10="Grupo 1",K10*H105/100,J10="Grupo 2",K10*I105/100,J10="Grupo 3",K10*J105/100,J10="Grupo 4",K10*K105/100) -> 0.031428571 | H10: =IF(L10=1,I10/I102,0) -> 0.037299694 | I10: =IF(L10=1,C102*G10-E10,0) -> 341.29748 | J10: Grupo 1 | K10: =IF(Balanceamentos!H37>0,Balanceamentos!H37,0) -> 11 | L10: =IF(G10>E10/C102,1,0) -> 1 | M10: =IF(L10=1,H10*L1,0) -> 165.182 | N10: =IF(M10>0,M10/D10,0) -> 4.7851101
A11: 10 | B11: TAEE11 | C11: 1 | D11: =IFERROR(__xludf.DUMMYFUNCTION("GOOGLEFINANCE(B11)"),41.85) -> 41.85 | E11: =C11*D11 -> 41.85 | F11: =E11/E102 -> 0.001033838 | G11: =IFS(J11="Grupo 0",0,J11="Grupo 1",K11*H105/100,J11="Grupo 2",K11*I105/100,J11="Grupo 3",K11*J105/100,J11="Grupo 4",K11*K105/100) -> 0 | H11: =IF(L11=1,I11/I102,0) -> 0 | I11: =IF(L11=1,C102*G11-E11,0) -> 0 | J11: Grupo 0 | K11: 0 | L11: =IF(G11>E11/C102,1,0) -> 0 | M11: =IF(L11=1,H11*L1,0) -> 0 | N11: =IF(M11>0,M11/D11,0) -> 0
A12: 11 | B12: ABCB4 | C12: 15 | D12: =IFERROR(__xludf.DUMMYFUNCTION("GOOGLEFINANCE(B12)"),25.82) -> 25.82 | E12: =C12*D12 -> 387.3 | F12: =E12/E102 -> 0.0095676334 | G12: =IFS(J12="Grupo 0",0,J12="Grupo 1",K12*H105/100,J12="Grupo 2",K12*I105/100,J12="Grupo 3",K12*J105/100,J12="Grupo 4",K12*K105/100) -> 0.0094594595 | H12: =IF(L12=1,I12/I102,0) -> 0.0040996511 | I12: =IF(L12=1,C102*G12-E12,0) -> 37.512388 | J12: Grupo 2 | K12: =IF(Balanceamentos!I37>0,Balanceamentos!I37,0) -> 7 | L12: =IF(G12>E12/C102,1,0) -> 1 | M12: =IF(L12=1,H12*L1,0) -> 18.155338 | N12: =IF(M12>0,M12/D12,0) -> 0.7031502
A13: 12 | B13: CXSE3 | C13: 20 | D13: =IFERROR(__xludf.DUMMYFUNCTION("GOOGLEFINANCE(B13)"),18.05) -> 18.05 | E13: =C13*D13 -> 361 | F13: =E13/E102 -> 0.0089179335 | G13: =IFS(J13="Grupo 0",0,J13="Grupo 1",K13*H105/100,J13="Grupo 2",K13*I105/100,J13="Grupo 3",K13*J105/100,J13="Grupo 4",K13*K105/100) -> 0.0084 | H13: =IF(L13=1,I13/I102,0) -> 0.0017741147 | I13: =IF(L13=1,C102*G13-E13,0) -> 16.2334 | J13: Grupo 3 | K13: =IF(Balanceamentos!J37>0,Balanceamentos!J37,0) -> 7 | L13: =IF(G13>E13/C102,1,0) -> 1 | M13: =IF(L13=1,H13*L1,0) -> 7.8566813 | N13: =IF(M13>0,M13/D13,0) -> 0.4352732
A14: 13 | B14: SAPR4 | C14: 2 | D14: =IFERROR(__xludf.DUMMYFUNCTION("GOOGLEFINANCE(B14)"),7.99) -> 7.99 | E14: =C14*D14 -> 15.98 | F14: =E14/E102 -> 0.0003947606 | G14: =IFS(J14="Grupo 0",0,J14="Grupo 1",K14*H105/100,J14="Grupo 2",K14*I105/100,J14="Grupo 3",K14*J105/100,J14="Grupo 4",K14*K105/100) -> 0 | H14: =IF(L14=1,I14/I102,0) -> 0 | I14: =IF(L14=1,C102*G14-E14,0) -> 0 | J14: Grupo 0 | K14: 0 | L14: =IF(G14>E14/C102,1,0) -> 0 | M14: =IF(L14=1,H14*L1,0) -> 0 | N14: =IF(M14>0,M14/D14,0) -> 0
A15: 14 | B15: KLBN4 | C15: 3 | D15: =IFERROR(__xludf.DUMMYFUNCTION("GOOGLEFINANCE(B15)"),3.8) -> 3.8 | E15: =C15*D15 -> 11.4 | F15: =E15/E102 -> 0.00028161895 | G15: =IFS(J15="Grupo 0",0,J15="Grupo 1",K15*H105/100,J15="Grupo 2",K15*I105/100,J15="Grupo 3",K15*J105/100,J15="Grupo 4",K15*K105/100) -> 0 | H15: =IF(L15=1,I15/I102,0) -> 0 | I15: =IF(L15=1,C102*G15-E15,0) -> 0 | J15: Grupo 0 | K15: 0 | L15: =IF(G15>E15/C102,1,0) -> 0 | M15: =IF(L15=1,H15*L1,0) -> 0 | N15: =IF(M15>0,M15/D15,0) -> 0
A16: 15 | B16: GOAU3 | C16: 20 | D16: =IFERROR(__xludf.DUMMYFUNCTION("GOOGLEFINANCE(""BVMF:GOAU3"")"),7.89) -> 7.89 | E16: =C16*D16 -> 157.8 | F16: =E16/E102 -> 0.0038981992 | G16: =IFS(J16="Grupo 0",0,J16="Grupo 1",K16*H105/100,J16="Grupo 2",K16*I105/100,J16="Grupo 3",K16*J105/100,J16="Grupo 4",K16*K105/100) -> 0.006 | H16: =IF(L16=1,I16/I102,0) -> 0.012202262 | I16: =IF(L16=1,C102*G16-E16,0) -> 111.65243 | J16: Grupo 3 | K16: =IF(Balanceamentos!K37>0,Balanceamentos!K37,0) -> 5 | L16: =IF(G16>E16/C102,1,0) -> 1 | M16: =IF(L16=1,H16*L1,0) -> 54.037818 | N16: =IF(M16>0,M16/D16,0) -> 6.8488996
A17: 16 | B17: CMIG3 | C17: 58 | D17: =IFERROR(__xludf.DUMMYFUNCTION("GOOGLEFINANCE(B17)"),15.6) -> 15.6 | E17: =C17*D17 -> 904.8 | F17: =E17/E102 -> 0.022351652 | G17: =IFS(J17="Grupo 0",0,J17="Grupo 1",K17*H105/100,J16="Grupo 2",K17*I105/100,J17="Grupo 3",K17*J105/100,J17="Grupo 4",K17*K105/100) -> 0.025714286 | H17: =IF(L17=1,I17/I102,0) -> 0.027321558 | I17: =IF(L17=1,C102*G17-E17,0) -> 249.99612 | J17: Grupo 1 | K17: =IF(Balanceamentos!L37>0,Balanceamentos!L37,0) -> 9 | L17: =IF(G17>E17/C102,1,0) -> 1 | M17: =IF(L17=1,H17*L1,0) -> 120.99374 | N17: =IF(M17>0,M17/D17,0) -> 7.7560091
A18: 17 | B18: PRIO3 | C18: 6 | D18: =IFERROR(__xludf.DUMMYFUNCTION("GOOGLEFINANCE(""BVMF:PRIO3"")"),66.03) -> 66.03 | E18: =C18*D18 -> 396.18 | F18: =E18/E102 -> 0.0097869997 | G18: =IFS(J18="Grupo 0",0,J18="Grupo 1",K18*H105/100,J18="Grupo 2",K18*I105/100,J18="Grupo 3",K18*J105/100,J18="Grupo 4",K18*K105/100) -> 0.0067567568 | H18: =IF(L18=1,I18/I102,0) -> 0 | I18: =IF(L18=1,C102*G18-E18,0) -> 0 | J18: Grupo 2 | K18: =IF(Balanceamentos!M37>0,Balanceamentos!M37,0) -> 5 | L18: =IF(G18>E18/C102,1,0) -> 0 | M18: =IF(L18=1,H18*L1,0) -> 0 | N18: =IF(M18>0,M18/D18,0) -> 0
A19: 18 | B19: VBBR3 | C19: 17 | D19: =IFERROR(__xludf.DUMMYFUNCTION("GOOGLEFINANCE(B19)"),29.8) -> 29.8 | E19: =C19*D19 -> 506.6 | F19: =E19/E102 -> 0.012514751 | G19: =IFS(J19="Grupo 0",0,J19="Grupo 1",K19*H105/100,J19="Grupo 2",K19*I105/100,J19="Grupo 3",K19*J105/100,J19="Grupo 4",K19*K105/100) -> 0.0108 | H19: =IF(L19=1,I19/I102,0) -> 0 | I19: =IF(L19=1,C102*G19-E19,0) -> 0 | J19: Grupo 3 | K19: =IF(Balanceamentos!N37>0,Balanceamentos!N37,0) -> 9 | L19: =IF(G19>E19/C102,1,0) -> 0 | M19: =IF(L19=1,H19*L1,0) -> 0 | N19: =IF(M19>0,M19/D19,0) -> 0
A20: 19 | B20: KLBN3 | C20: 123 | D20: =IFERROR(__xludf.DUMMYFUNCTION("GOOGLEFINANCE(B20)"),3.83) -> 3.83 | E20: =C20*D20 -> 471.09 | F20: =E20/E102 -> 0.011637533 | G20: =IFS(J20="Grupo 0",0,J20="Grupo 1",K20*H105/100,J20="Grupo 2",K20*I105/100,J20="Grupo 3",K20*J105/100,J20="Grupo 4",K20*K105/100) -> 0.0132 | H20: =IF(L20=1,I20/I102,0) -> 0.013300925 | I20: =IF(L20=1,C102*G20-E20,0) -> 121.70534 | J20: Grupo 3 | K20: =IF(Balanceamentos!O37>0,Balanceamentos!O37,0) -> 11 | L20: =IF(G20>E20/C102,1,0) -> 1 | M20: =IF(L20=1,H20*L1,0) -> 58.903253 | N20: =IF(M20>0,M20/D20,0) -> 15.379439
A21: 20 | B21: RANI3 | C21: 38 | D21: =IFERROR(__xludf.DUMMYFUNCTION("GOOGLEFINANCE(B21)"),9.23) -> 9.23 | E21: =C21*D21 -> 350.74 | F21: =E21/E102 -> 0.0086644765 | G21: =IFS(J21="Grupo 0",0,J21="Grupo 1",K21*H105/100,J21="Grupo 2",K21*I105/100,J21="Grupo 3",K21*J105/100,J21="Grupo 4",K21*K105/100) -> 0.0094594595 | H21: =IF(L21=1,I21/I102,0) -> 0.0080952176 | I21: =IF(L21=1,C102*G21-E21,0) -> 74.072388 | J21: Grupo 2 | K21: =IF(Balanceamentos!P37>0,Balanceamentos!P37,0) -> 7 | L21: =IF(G21>E21/C102,1,0) -> 1 | M21: =IF(L21=1,H21*L1,0) -> 35.849737 | N21: =IF(M21>0,M21/D21,0) -> 3.8840452
A22: 21 | B22: DEXP3 | C22: 13 | D22: =IFERROR(__xludf.DUMMYFUNCTION("GOOGLEFINANCE(B22)"),7.04) -> 7.04 | E22: =C22*D22 -> 91.52 | F22: =E22/E102 -> 0.0022608567 | G22: =IFS(J22="Grupo 0",0,J22="Grupo 1",K22*H105/100,J22="Grupo 2",K22*I105/100,J22="Grupo 3",K22*J105/100,J22="Grupo 4",K22*K105/100) -> 0.0032051282 | H22: =IF(L22=1,I22/I102,0) -> 0.0057286833 | I22: =IF(L22=1,C102*G22-E22,0) -> 52.418263 | J22: Grupo 4 | K22: =IF(Balanceamentos!Q37>0,Balanceamentos!Q37,0) -> 5 | L22: =IF(G22>E22/C102,1,0) -> 1 | M22: =IF(L22=1,H22*L1,0) -> 25.369521 | N22: =IF(M22>0,M22/D22,0) -> 3.6036251
A23: 22 | B23: GGBR3 | C23: 24 | D23: =IFERROR(__xludf.DUMMYFUNCTION("GOOGLEFINANCE(B23)"),15.71) -> 15.71 | E23: =C23*D23 -> 377.04 | F23: =E23/E102 -> 0.0093141763 | G23: =IFS(J23="Grupo 0",0,J23="Grupo 1",K23*H105/100,J23="Grupo 2",K23*I105/100,J23="Grupo 3",K23*J105/100,J23="Grupo 4",K23*K105/100) -> 0.0108 | H23: =IF(L23=1,I23/I102,0) -> 0.011800295 | I23: =IF(L23=1,C102*G23-E23,0) -> 107.97437 | J23: Grupo 3 | K23: =IF(Balanceamentos!R37>0,Balanceamentos!R37,0) -> 9 | L23: =IF(G23>E23/C102,1,0) -> 1 | M23: =IF(L23=1,H23*L1,0) -> 52.257703 | N23: =IF(M23>0,M23/D23,0) -> 3.3263974
A24: 23 | B24: SAPR3 | C24: 62 | D24: =IFERROR(__xludf.DUMMYFUNCTION("GOOGLEFINANCE(B24)"),9.36) -> 9.36 | E24: =C24*D24 -> 580.32 | F24: =E24/E102 -> 0.014335887 | G24: =IFS(J24="Grupo 0",0,J24="Grupo 1",K24*H105/100,J24="Grupo 2",K24*I105/100,J24="Grupo 3",K24*J105/100,J24="Grupo 4",K24*K105/100) -> 0.014285714 | H24: =IF(L24=1,I24/I102,0) -> 0.0066920715 | I24: =IF(L24=1,C102*G24-E24,0) -> 61.233402 | J24: Grupo 1 | K24: =IF(Balanceamentos!S37>0,Balanceamentos!S37,0) -> 5 | L24: =IF(G24>E24/C102,1,0) -> 1 | M24: =IF(L24=1,H24*L1,0) -> 29.635893 | N24: =IF(M24>0,M24/D24,0) -> 3.1662279
A25: 24 | B25: SBSP3 | C25: 5 | D25: =IFERROR(__xludf.DUMMYFUNCTION("GOOGLEFINANCE(""BVMF:SBSP3"")"),147.25) -> 147.25 | E25: =C25*D25 -> 736.25 | F25: =E25/E102 -> 0.018187891 | G25: =IFS(J25="Grupo 0",0,J25="Grupo 1",K25*H105/100,J25="Grupo 2",K25*I105/100,J25="Grupo 3",K25*J105/100,J25="Grupo 4",K25*K105/100) -> 0.02 | H25: =IF(L25=1,I25/I102,0) -> 0.017696421 | I25: =IF(L25=1,C102*G25-E25,0) -> 161.92476 | J25: Grupo 1 | K25: =IF(Balanceamentos!T37>0,Balanceamentos!T37,0) -> 7 | L25: =IF(G25>E25/C102,1,0) -> 1 | M25: =IF(L25=1,H25*L1,0) -> 78.368747 | N25: =IF(M25>0,M25/D25,0) -> 0.5322156
A26: 25 | B26: ALUP3 | C26: 14 | D26: =IFERROR(__xludf.DUMMYFUNCTION("GOOGLEFINANCE(B26)"),12.37) -> 12.37 | E26: =C26*D26 -> 173.18 | F26: =E26/E102 -> 0.0042781377 | G26: =IFS(J26="Grupo 0",0,J26="Grupo 1",K26*H105/100,J26="Grupo 2",K26*I105/100,J26="Grupo 3",K26*J105/100,J26="Grupo 4",K26*K105/100) -> 0.0044871795 | H26: =IF(L26=1,I26/I102,0) -> 0.0030965169 | I26: =IF(L26=1,C102*G26-E26,0) -> 28.333569 | J26: Grupo 4 | K26: =IF(Balanceamentos!U37>0,Balanceamentos!U37,0) -> 7 | L26: =IF(G26>E26/C102,1,0) -> 1 | M26: =IF(L26=1,H26*L1,0) -> 13.712951 | N26: =IF(M26>0,M26/D26,0) -> 1.1085651
A27: 26 | B27: TAEE3 | C27: 34 | D27: =IFERROR(__xludf.DUMMYFUNCTION("GOOGLEFINANCE(B27)"),13.74) -> 13.74 | E27: =C27*D27 -> 467.16 | F27: =E27/E102 -> 0.011540448 | G27: =IFS(J27="Grupo 0",0,J27="Grupo 1",K27*H105/100,J27="Grupo 2",K27*I105/100,J27="Grupo 3",K27*J105/100,J27="Grupo 4",K27*K105/100) -> 0.012162162 | H27: =IF(L27=1,I27/I102,0) -> 0.0086367358 | I27: =IF(L27=1,C102*G27-E27,0) -> 79.027356 | J27: Grupo 2 | K27: =IF(Balanceamentos!V37>0,Balanceamentos!V37,0) -> 9 | L27: =IF(G27>E27/C102,1,0) -> 1 | M27: =IF(L27=1,H27*L1,0) -> 38.247855 | N27: =IF(M27>0,M27/D27,0) -> 2.7836867
A28: 27 | B28: ENGI3 | C28: 62 | D28: =IFERROR(__xludf.DUMMYFUNCTION("GOOGLEFINANCE(""BVMF:ENGI3"")"),12.54) -> 12.54 | E28: =C28*D28 -> 777.48 | F28: =E28/E102 -> 0.019206413 | G28: =IFS(J28="Grupo 0",0,J28="Grupo 1",K28*H105/100,J28="Grupo 2",K28*I105/100,J28="Grupo 3",K28*J105/100,J28="Grupo 4",K28*K105/100) -> 0.025714286 | H28: =IF(L28=1,I28/I102,0) -> 0.041236096 | I28: =IF(L28=1,C102*G28-E28,0) -> 377.31612 | J28: Grupo 1 | K28: =IF(Balanceamentos!W37>0,Balanceamentos!W37,0) -> 9 | L28: =IF(G28>E28/C102,1,0) -> 1 | M28: =IF(L28=1,H28*L1,0) -> 182.61439 | N28: =IF(M28>0,M28/D28,0) -> 14.562551
A29: 28 | B29: CLSC3 | C29: 1 | D29: =IFERROR(__xludf.DUMMYFUNCTION("GOOGLEFINANCE(B29)"),124.01) -> 124.01 | E29: =C29*D29 -> 124.01 | F29: =E29/E102 -> 0.0030634707 | G29: =IFS(J29="Grupo 0",0,J29="Grupo 1",K29*H105/100,J29="Grupo 2",K29*I105/100,J29="Grupo 3",K29*J105/100,J29="Grupo 4",K29*K105/100) -> 0.0028571429 | H29: =IF(L29=1,I29/I102,0) -> 0.00047001244 | I29: =IF(L29=1,C102*G29-E29,0) -> 4.3006804 | J29: Grupo 1 | K29: =IF(Balanceamentos!X37>0,Balanceamentos!X37,0) -> 1 | L29: =IF(G29>E29/C102,1,0) -> 1 | M29: =IF(L29=1,H29*L1,0) -> 2.0814539 | N29: =IF(M29>0,M29/D29,0) -> 0.016784565
A30: 29 | B30: AXIA3 | C30: 7 | D30: =IFERROR(__xludf.DUMMYFUNCTION("GOOGLEFINANCE(""BVMF:AXIA3"")"),57.6) -> 57.6 | E30: =C30*D30 -> 403.2 | F30: =E30/E102 -> 0.0099604177 | G30: =IFS(J30="Grupo 0",0,J30="Grupo 1",K30*H105/100,J30="Grupo 2",K30*I105/100,J30="Grupo 3",K30*J105/100,J30="Grupo 4",K30*K105/100) -> 0.0108 | H30: =IF(L30=1,I30/I102,0) -> 0.008941323 | I30: =IF(L30=1,C102*G30-E30,0) -> 81.814372 | J30: Grupo 3 | K30: =IF(Balanceamentos!Y37>0,Balanceamentos!Y37,0) -> 9 | L30: =IF(G30>E30/C102,1,0) -> 1 | M30: =IF(L30=1,H30*L1,0) -> 39.596722 | N30: =IF(M30>0,M30/D30,0) -> 0.68744309
A31: 30 | B31: TOTS3 | C31: 4 | D31: =IFERROR(__xludf.DUMMYFUNCTION("GOOGLEFINANCE(B31)"),33.78) -> 33.78 | E31: =C31*D31 -> 135.12 | F31: =E31/E102 -> 0.0033379257 | G31: =IFS(J31="Grupo 0",0,J31="Grupo 1",K31*H105/100,J31="Grupo 2",K31*I105/100,J31="Grupo 3",K31*J105/100,J31="Grupo 4",K31*K105/100) -> 0.0057692308 | H31: =IF(L31=1,I31/I102,0) -> 0.013548301 | I31: =IF(L31=1,C102*G31-E31,0) -> 123.96887 | J31: Grupo 4 | K31: =IF(Balanceamentos!Z37>0,Balanceamentos!Z37,0) -> 9 | L31: =IF(G31>E31/C102,1,0) -> 1 | M31: =IF(L31=1,H31*L1,0) -> 59.998762 | N31: =IF(M31>0,M31/D31,0) -> 1.7761623
A32: 31 | B32: BMOB3 | C32: 5 | D32: =IFERROR(__xludf.DUMMYFUNCTION("GOOGLEFINANCE(B32)"),22.5) -> 22.5 | E32: =C32*D32 -> 112.5 | F32: =E32/E102 -> 0.0027791344 | G32: =IFS(J32="Grupo 0",0,J32="Grupo 1",K32*H105/100,J32="Grupo 2",K32*I105/100,J32="Grupo 3",K32*J105/100,J32="Grupo 4",K32*K105/100) -> 0.0032051282 | H32: =IF(L32=1,I32/I102,0) -> 0.0034358226 | I32: =IF(L32=1,C102*G32-E32,0) -> 31.438263 | J32: Grupo 4 | K32: =IF(Balanceamentos!AA37>0,Balanceamentos!AA37,0) -> 5 | L32: =IF(G32>E32/C102,1,0) -> 1 | M32: =IF(L32=1,H32*L1,0) -> 15.215568 | N32: =IF(M32>0,M32/D32,0) -> 0.67624748
A33: 32 | B33: TIMS3 | C33: 12 | D33: =IFERROR(__xludf.DUMMYFUNCTION("GOOGLEFINANCE(""BVMF:TIMS3"")"),26.34) -> 26.34 | E33: =C33*D33 -> 316.08 | F33: =E33/E102 -> 0.007808256 | G33: =IFS(J33="Grupo 0",0,J33="Grupo 1",K33*H105/100,J33="Grupo 2",K33*I105/100,J33="Grupo 3",K33*J105/100,J33="Grupo 4",K33*K105/100) -> 0.0084 | H33: =IF(L33=1,I33/I102,0) -> 0.0066833283 | I33: =IF(L33=1,C102*G33-E33,0) -> 61.1534 | J33: Grupo 3 | K33: =IF(Balanceamentos!AB37>0,Balanceamentos!AB37,0) -> 7 | L33: =IF(G33>E33/C102,1,0) -> 1 | M33: =IF(L33=1,H33*L1,0) -> 29.597174 | N33: =IF(M33>0,M33/D33,0) -> 1.1236588
A34: 33 | B34: INTB3 | C34: 13 | D34: =IFERROR(__xludf.DUMMYFUNCTION("GOOGLEFINANCE(B34)"),14.74) -> 14.74 | E34: =C34*D34 -> 191.62 | F34: =E34/E102 -> 0.0047336688 | G34: =IFS(J34="Grupo 0",0,J34="Grupo 1",K34*H105/100,J34="Grupo 2",K34*I105/100,J34="Grupo 3",K34*J105/100,J34="Grupo 4",K34*K105/100) -> 0.0044871795 | H34: =IF(L34=1,I34/I102,0) -> 0.0010812476 | I34: =IF(L34=1,C102*G34-E34,0) -> 9.8935686 | J34: Grupo 4 | K34: =IF(Balanceamentos!AC37>0,Balanceamentos!AC37,0) -> 7 | L34: =IF(G34>E34/C102,1,0) -> 1 | M34: =IF(L34=1,H34*L1,0) -> 4.7883138 | N34: =IF(M34>0,M34/D34,0) -> 0.32485168
A35: 34 | B35: CMIN3 | C35: 35 | D35: =IFERROR(__xludf.DUMMYFUNCTION("GOOGLEFINANCE(B35)"),4.81) -> 4.81 | E35: =C35*D35 -> 168.35 | F35: =E35/E102 -> 0.0041588202 | G35: =IFS(J35="Grupo 0",0,J35="Grupo 1",K35*H105/100,J35="Grupo 2",K35*I105/100,J35="Grupo 3",K35*J105/100,J35="Grupo 4",K35*K105/100) -> 0.006 | H35: =IF(L35=1,I35/I102,0) -> 0.011049275 | I35: =IF(L35=1,C102*G35-E35,0) -> 101.10243 | J35: Grupo 3 | K35: =IF(Balanceamentos!AD37>0,Balanceamentos!AD37,0) -> 5 | L35: =IF(G35>E35/C102,1,0) -> 1 | M35: =IF(L35=1,H35*L1,0) -> 48.931803 | N35: =IF(M35>0,M35/D35,0) -> 10.172932
A36: 35 | B36: ARML3 | C36: 19 | D36: =IFERROR(__xludf.DUMMYFUNCTION("GOOGLEFINANCE(B36)"),4.8) -> 4.8 | E36: =C36*D36 -> 91.2 | F36: =E36/E102 -> 0.0022529516 | G36: =IFS(J36="Grupo 0",0,J36="Grupo 1",K36*H105/100,J36="Grupo 2",K36*I105/100,J36="Grupo 3",K36*J105/100,J36="Grupo 4",K36*K105/100) -> 0.0019230769 | H36: =IF(L36=1,I36/I102,0) -> 0 | I36: =IF(L36=1,C102*G36-E36,0) -> 0 | J36: Grupo 4 | K36: =IF(Balanceamentos!AE37>0,Balanceamentos!AE37,0) -> 3 | L36: =IF(G36>E36/C102,1,0) -> 0 | M36: =IF(L36=1,H36*L1,0) -> 0 | N36: =IF(M36>0,M36/D36,0) -> 0
A37: 36 | B37: VLID3 | C37: 13 | D37: =IFERROR(__xludf.DUMMYFUNCTION("GOOGLEFINANCE(B37)"),19.85) -> 19.85 | E37: =C37*D37 -> 258.05 | F37: =E37/E102 -> 0.0063747167 | G37: =IFS(J37="Grupo 0",0,J37="Grupo 1",K37*H105/100,J37="Grupo 2",K37*I105/100,J37="Grupo 3",K37*J105/100,J37="Grupo 4",K37*K105/100) -> 0.0084 | H37: =IF(L37=1,I37/I102,0) -> 0.013025307 | I37: =IF(L37=1,C102*G37-E37,0) -> 119.1834 | J37: Grupo 3 | K37: =IF(Balanceamentos!AF37>0,Balanceamentos!AF37,0) -> 7 | L37: =IF(G37>E37/C102,1,0) -> 1 | M37: =IF(L37=1,H37*L1,0) -> 57.682676 | N37: =IF(M37>0,M37/D37,0) -> 2.9059283
A38: 37 | B38: GGPS3 | C38: 8 | D38: =IFERROR(__xludf.DUMMYFUNCTION("GOOGLEFINANCE(B38)"),16.45) -> 16.45 | E38: =C38*D38 -> 131.6 | F38: =E38/E102 -> 0.0032509697 | G38: =IFS(J38="Grupo 0",0,J38="Grupo 1",K38*H105/100,J38="Grupo 2",K38*I105/100,J38="Grupo 3",K38*J105/100,J38="Grupo 4",K38*K105/100) -> 0.0044871795 | H38: =IF(L38=1,I38/I102,0) -> 0.0076407089 | I38: =IF(L38=1,C102*G38-E38,0) -> 69.913569 | J38: Grupo 4 | K38: =IF(Balanceamentos!AG37>0,Balanceamentos!AG37,0) -> 7 | L38: =IF(G38>E38/C102,1,0) -> 1 | M38: =IF(L38=1,H38*L1,0) -> 33.836942 | N38: =IF(M38>0,M38/D38,0) -> 2.0569569
A39: 38 | B39: WEGE3 | C39: 27 | D39: =IFERROR(__xludf.DUMMYFUNCTION("GOOGLEFINANCE(""BVMF:WEGE3"")"),46.16) -> 46.16 | E39: =C39*D39 -> 1246.32 | F39: =E39/E102 -> 0.030788363 | G39: =IFS(J39="Grupo 0",0,J39="Grupo 1",K39*H105/100,J39="Grupo 2",K39*I105/100,J39="Grupo 3",K39*J105/100,J39="Grupo 4",K39*K105/100) -> 0.031428571 | H39: =IF(L39=1,I39/I102,0) -> 0.018043162 | I39: =IF(L39=1,C102*G39-E39,0) -> 165.09748 | J39: Grupo 1 | K39: =IF(Balanceamentos!AH37>0,Balanceamentos!AH37,0) -> 11 | L39: =IF(G39>E39/C102,1,0) -> 1 | M39: =IF(L39=1,H39*L1,0) -> 79.904288 | N39: =IF(M39>0,M39/D39,0) -> 1.7310288
A40: 39 | B40: KEPL3 | C40: 55 | D40: =IFERROR(__xludf.DUMMYFUNCTION("GOOGLEFINANCE(B40)"),7.72) -> 7.72 | E40: =C40*D40 -> 424.6 | F40: =E40/E102 -> 0.010489071 | G40: =IFS(J40="Grupo 0",0,J40="Grupo 1",K40*H105/100,J40="Grupo 2",K40*I105/100,J40="Grupo 3",K40*J105/100,J40="Grupo 4",K40*K105/100) -> 0.012162162 | H40: =IF(L40=1,I40/I102,0) -> 0.01328803 | I40: =IF(L40=1,C102*G40-E40,0) -> 121.58736 | J40: Grupo 2 | K40: =IF(Balanceamentos!AI37>0,Balanceamentos!AI37,0) -> 9 | L40: =IF(G40>E40/C102,1,0) -> 1 | M40: =IF(L40=1,H40*L1,0) -> 58.846149 | N40: =IF(M40>0,M40/D40,0) -> 7.6225581
A41: 40 | B41: JSLG3 | C41: 25 | D41: =IFERROR(__xludf.DUMMYFUNCTION("GOOGLEFINANCE(B41)"),6.14) -> 6.14 | E41: =C41*D41 -> 153.5 | F41: =E41/E102 -> 0.0037919745 | G41: =IFS(J41="Grupo 0",0,J41="Grupo 1",K41*H105/100,J41="Grupo 2",K41*I105/100,J41="Grupo 3",K41*J105/100,J41="Grupo 4",K41*K105/100) -> 0.0044871795 | H41: =IF(L41=1,I41/I102,0) -> 0.0052473033 | I41: =IF(L41=1,C102*G41-E41,0) -> 48.013569 | J41: Grupo 4 | K41: =IF(Balanceamentos!AJ37>0,Balanceamentos!AJ37,0) -> 7 | L41: =IF(G41>E41/C102,1,0) -> 1 | M41: =IF(L41=1,H41*L1,0) -> 23.237726 | N41: =IF(M41>0,M41/D41,0) -> 3.7846458
A42: 41 | B42: TGMA3 | C42: 10 | D42: =IFERROR(__xludf.DUMMYFUNCTION("GOOGLEFINANCE(B42)"),28.26) -> 28.26 | E42: =C42*D42 -> 282.6 | F42: =E42/E102 -> 0.0069811856 | G42: =IFS(J42="Grupo 0",0,J42="Grupo 1",K42*H105/100,J42="Grupo 2",K42*I105/100,J42="Grupo 3",K42*J105/100,J42="Grupo 4",K42*K105/100) -> 0.0094594595 | H42: =IF(L42=1,I42/I102,0) -> 0.015542097 | I42: =IF(L42=1,C102*G42-E42,0) -> 142.21239 | J42: Grupo 2 | K42: =IF(Balanceamentos!AK37>0,Balanceamentos!AK37,0) -> 7 | L42: =IF(G42>E42/C102,1,0) -> 1 | M42: =IF(L42=1,H42*L1,0) -> 68.828303 | N42: =IF(M42>0,M42/D42,0) -> 2.435538
A43: 42 | E43: =C43*D43 -> 0 | F43: =E43/E102 -> 0 | G43: =IFS(J43="Grupo 0",0,J43="Grupo 1",K43*H105/100,J43="Grupo 2",K43*I105/100,J43="Grupo 3",K43*J105/100,J43="Grupo 4",K43*K105/100) -> 0 | H43: =IF(L43=1,I43/I102,0) -> 0 | I43: =IF(L43=1,C102*G43-E43,0) -> 0 | J43: Grupo 0 | K43: =IF(Balanceamentos!AL37>0,Balanceamentos!AL37,0) -> 7 | L43: =IF(G43>E43/C102,1,0) -> 0 | M43: =IF(L43=1,H43*L1,0) -> 0 | N43: =IF(M43>0,M43/D43,0) -> 0
A44: 43 | B44: ECOR3 | C44: 36 | D44: =IFERROR(__xludf.DUMMYFUNCTION("GOOGLEFINANCE(B44)"),8.79) -> 8.79 | E44: =C44*D44 -> 316.44 | F44: =E44/E102 -> 0.0078171493 | G44: =IFS(J44="Grupo 0",0,J44="Grupo 1",K44*H105/100,J44="Grupo 2",K44*I105/100,J44="Grupo 3",K44*J105/100,J44="Grupo 4",K44*K105/100) -> 0.0084 | H44: =IF(L44=1,I44/I102,0) -> 0.0066439846 | I44: =IF(L44=1,C102*G44-E44,0) -> 60.7934 | J44: Grupo 3 | K44: =IF(Balanceamentos!AM37>0,Balanceamentos!AM37,0) -> 7 | L44: =IF(G44>E44/C102,1,0) -> 1 | M44: =IF(L44=1,H44*L1,0) -> 29.42294 | N44: =IF(M44>0,M44/D44,0) -> 3.3473197
A45: 44 | B45: MOTV3 | C45: 22 | D45: =IFERROR(__xludf.DUMMYFUNCTION("GOOGLEFINANCE(""BVMF:MOTV3"")"),15.15) -> 15.15 | E45: =C45*D45 -> 333.3 | F45: =E45/E102 -> 0.0082336489 | G45: =IFS(J45="Grupo 0",0,J45="Grupo 1",K45*H105/100,J45="Grupo 2",K45*I105/100,J45="Grupo 3",K45*J105/100,J45="Grupo 4",K45*K105/100) -> 0.0094594595 | H45: =IF(L45=1,I45/I102,0) -> 0.010001199 | I45: =IF(L45=1,C102*G45-E45,0) -> 91.512388 | J45: Grupo 2 | K45: =IF(Balanceamentos!AN37>0,Balanceamentos!AN37,0) -> 7 | L45: =IF(G45>E45/C102,1,0) -> 1 | M45: =IF(L45=1,H45*L1,0) -> 44.290391 | N45: =IF(M45>0,M45/D45,0) -> 2.9234582
A46: 45 | B46: CSUD3 | C46: 13 | D46: =IFERROR(__xludf.DUMMYFUNCTION("GOOGLEFINANCE(B46)"),18.08) -> 18.08 | E46: =C46*D46 -> 235.04 | F46: =E46/E102 -> 0.0058062911 | G46: =IFS(J46="Grupo 0",0,J46="Grupo 1",K46*H105/100,J46="Grupo 2",K46*I105/100,J46="Grupo 3",K46*J105/100,J46="Grupo 4",K46*K105/100) -> 0.0067567568 | H46: =IF(L46=1,I46/I102,0) -> 0.0074750121 | I46: =IF(L46=1,C102*G46-E46,0) -> 68.39742 | J46: Grupo 2 | K46: =IF(Balanceamentos!AO37>0,Balanceamentos!AO37,0) -> 5 | L46: =IF(G46>E46/C102,1,0) -> 1 | M46: =IF(L46=1,H46*L1,0) -> 33.103152 | N46: =IF(M46>0,M46/D46,0) -> 1.8309266
A47: 46 | B47: POMO3 | C47: 113 | D47: =IFERROR(__xludf.DUMMYFUNCTION("GOOGLEFINANCE(B47)"),5.56) -> 5.56 | E47: =C47*D47 -> 628.28 | F47: =E47/E102 -> 0.015520663 | G47: =IFS(J47="Grupo 0",0,J47="Grupo 1",K47*H105/100,J47="Grupo 2",K47*I105/100,J47="Grupo 3",K47*J105/100,J47="Grupo 4",K47*K105/100) -> 0.025714286 | H47: =IF(L47=1,I47/I102,0) -> 0.057541855 | I47: =IF(L47=1,C102*G47-E47,0) -> 526.51612 | J47: Grupo 1 | K47: =IF(Balanceamentos!AP37>0,Balanceamentos!AP37,0) -> 9 | L47: =IF(G47>E47/C102,1,0) -> 1 | M47: =IF(L47=1,H47*L1,0) -> 254.82457 | N47: =IF(M47>0,M47/D47,0) -> 45.831758
A48: 47 | B48: FRAS3 | C48: 37 | D48: =IFERROR(__xludf.DUMMYFUNCTION("GOOGLEFINANCE(B48)"),21.21) -> 21.21 | E48: =C48*D48 -> 784.77 | F48: =E48/E102 -> 0.019386501 | G48: =IFS(J48="Grupo 0",0,J48="Grupo 1",K48*H105/100,J48="Grupo 2",K48*I105/100,J48="Grupo 3",K48*J105/100,J48="Grupo 4",K48*K105/100) -> 0.025714286 | H48: =IF(L48=1,I48/I102,0) -> 0.040439387 | I48: =IF(L48=1,C102*G48-E48,0) -> 370.02612 | J48: Grupo 1 | K48: =IF(Balanceamentos!AQ37>0,Balanceamentos!AQ37,0) -> 9 | L48: =IF(G48>E48/C102,1,0) -> 1 | M48: =IF(L48=1,H48*L1,0) -> 179.08616 | N48: =IF(M48>0,M48/D48,0) -> 8.4434775
A49: 48 | B49: VAMO3 | C49: 59 | D49: =IFERROR(__xludf.DUMMYFUNCTION("GOOGLEFINANCE(B49)"),3.48) -> 3.48 | E49: =C49*D49 -> 205.32 | F49: =E49/E102 -> 0.0050721056 | G49: =IFS(J49="Grupo 0",0,J49="Grupo 1",K49*H105/100,J49="Grupo 2",K49*I105/100,J49="Grupo 3",K49*J105/100,J49="Grupo 4",K49*K105/100) -> 0.006 | H49: =IF(L49=1,I49/I102,0) -> 0.0070089001 | I49: =IF(L49=1,C102*G49-E49,0) -> 64.132429 | J49: Grupo 3 | K49: =IF(Balanceamentos!AR37>0,Balanceamentos!AR37,0) -> 5 | L49: =IF(G49>E49/C102,1,0) -> 1 | M49: =IF(L49=1,H49*L1,0) -> 31.038971 | N49: =IF(M49>0,M49/D49,0) -> 8.9192446
A50: 49 | B50: RADL3 | C50: 45 | D50: =IFERROR(__xludf.DUMMYFUNCTION("GOOGLEFINANCE(B50)"),23.18) -> 23.18 | E50: =C50*D50 -> 1043.1 | F50: =E50/E102 -> 0.025768134 | G50: =IFS(J50="Grupo 0",0,J50="Grupo 1",K50*H105/100,J50="Grupo 2",K50*I105/100,J50="Grupo 3",K50*J105/100,J50="Grupo 4",K50*K105/100) -> 0.025714286 | H50: =IF(L50=1,I50/I102,0) -> 0.012207038 | I50: =IF(L50=1,C102*G50-E50,0) -> 111.69612 | J50: Grupo 1 | K50: =IF(Balanceamentos!AS37>0,Balanceamentos!AS37,0) -> 9 | L50: =IF(G50>E50/C102,1,0) -> 1 | M50: =IF(L50=1,H50*L1,0) -> 54.058966 | N50: =IF(M50>0,M50/D50,0) -> 2.3321383
A51: 50 | B51: PGMN3 | C51: 12 | D51: =IFERROR(__xludf.DUMMYFUNCTION("GOOGLEFINANCE(B51)"),6.1) -> 6.1 | E51: =C51*D51 -> 73.2 | F51: =E51/E102 -> 0.0018082901 | G51: =IFS(J51="Grupo 0",0,J51="Grupo 1",K51*H105/100,J51="Grupo 2",K51*I105/100,J51="Grupo 3",K51*J105/100,J51="Grupo 4",K51*K105/100) -> 0.0012 | H51: =IF(L51=1,I51/I102,0) -> 0 | I51: =IF(L51=1,C102*G51-E51,0) -> 0 | J51: Grupo 3 | K51: =IF(Balanceamentos!AT37>0,Balanceamentos!AT37,0) -> 1 | L51: =IF(G51>E51/C102,1,0) -> 0 | M51: =IF(L51=1,H51*L1,0) -> 0 | N51: =IF(M51>0,M51/D51,0) -> 0
A52: 51 | B52: PFRM3 | C52: 17 | D52: =IFERROR(__xludf.DUMMYFUNCTION("GOOGLEFINANCE(B52)"),7.9) -> 7.9 | E52: =C52*D52 -> 134.3 | F52: =E52/E102 -> 0.0033176689 | G52: =IFS(J52="Grupo 0",0,J52="Grupo 1",K52*H105/100,J52="Grupo 2",K52*I105/100,J52="Grupo 3",K52*J105/100,J52="Grupo 4",K52*K105/100) -> 0.0036 | H52: =IF(L52=1,I52/I102,0) -> 0.0029913698 | I52: =IF(L52=1,C102*G52-E52,0) -> 27.371457 | J52: Grupo 3 | K52: =IF(Balanceamentos!AU37>0,Balanceamentos!AU37,0) -> 3 | L52: =IF(G52>E52/C102,1,0) -> 1 | M52: =IF(L52=1,H52*L1,0) -> 13.247306 | N52: =IF(M52>0,M52/D52,0) -> 1.6768741
A53: 52 | B53: FLRY3 | C53: 56 | D53: =IFERROR(__xludf.DUMMYFUNCTION("GOOGLEFINANCE(B53)"),15.34) -> 15.34 | E53: =C53*D53 -> 859.04 | F53: =E53/E102 -> 0.021221223 | G53: =IFS(J53="Grupo 0",0,J53="Grupo 1",K53*H105/100,J53="Grupo 2",K53*I105/100,J53="Grupo 3",K53*J105/100,J53="Grupo 4",K53*K105/100) -> 0.025714286 | H53: =IF(L53=1,I53/I102,0) -> 0.032322573 | I53: =IF(L53=1,C102*G53-E53,0) -> 295.75612 | J53: Grupo 1 | K53: =IF(Balanceamentos!AV37>0,Balanceamentos!AV37,0) -> 9 | L53: =IF(G53>E53/C102,1,0) -> 1 | M53: =IF(L53=1,H53*L1,0) -> 143.14078 | N53: =IF(M53>0,M53/D53,0) -> 9.3312112
A54: 53 | B54: ODPV3 | C54: 25 | D54: =IFERROR(__xludf.DUMMYFUNCTION("GOOGLEFINANCE(B54)"),13.1) -> 13.1 | E54: =C54*D54 -> 327.5 | F54: =E54/E102 -> 0.0080903691 | G54: =IFS(J54="Grupo 0",0,J54="Grupo 1",K54*H105/100,J54="Grupo 2",K54*I105/100,J54="Grupo 3",K54*J105/100,J54="Grupo 4",K54*K105/100) -> 0.0094594595 | H54: =IF(L54=1,I54/I102,0) -> 0.010635069 | I54: =IF(L54=1,C102*G54-E54,0) -> 97.312388 | J54: Grupo 2 | K54: =IF(Balanceamentos!AW37>0,Balanceamentos!AW37,0) -> 7 | L54: =IF(G54>E54/C102,1,0) -> 1 | M54: =IF(L54=1,H54*L1,0) -> 47.09749 | N54: =IF(M54>0,M54/D54,0) -> 3.5952282
A55: 54 | B55: RDOR3 | C55: 25 | D55: =IFERROR(__xludf.DUMMYFUNCTION("GOOGLEFINANCE(B55)"),37.02) -> 37.02 | E55: =C55*D55 -> 925.5 | F55: =E55/E102 -> 0.022863012 | G55: =IFS(J55="Grupo 0",0,J55="Grupo 1",K55*H105/100,J55="Grupo 2",K55*I105/100,J55="Grupo 3",K55*J105/100,J55="Grupo 4",K55*K105/100) -> 0.031428571 | H55: =IF(L55=1,I55/I102,0) -> 0.053104914 | I55: =IF(L55=1,C102*G55-E55,0) -> 485.91748 | J55: Grupo 1 | K55: =IF(Balanceamentos!AX37>0,Balanceamentos!AX37,0) -> 11 | L55: =IF(G55>E55/C102,1,0) -> 1 | M55: =IF(L55=1,H55*L1,0) -> 235.17554 | N55: =IF(M55>0,M55/D55,0) -> 6.3526619
A56: 55 | B56: BLAU3 | C56: 32 | D56: =IFERROR(__xludf.DUMMYFUNCTION("GOOGLEFINANCE(B56)"),9.67) -> 9.67 | E56: =C56*D56 -> 309.44 | F56: =E56/E102 -> 0.0076442253 | G56: =IFS(J56="Grupo 0",0,J56="Grupo 1",K56*H105/100,J56="Grupo 2",K56*I105/100,J56="Grupo 3",K56*J105/100,J56="Grupo 4",K56*K105/100) -> 0.012162162 | H56: =IF(L56=1,I56/I102,0) -> 0.025873627 | I56: =IF(L56=1,C102*G56-E56,0) -> 236.74736 | J56: Grupo 2 | K56: =IF(Balanceamentos!AY37>0,Balanceamentos!AY37,0) -> 9 | L56: =IF(G56>E56/C102,1,0) -> 1 | M56: =IF(L56=1,H56*L1,0) -> 114.58157 | N56: =IF(M56>0,M56/D56,0) -> 11.84918
A57: 56 | B57: OFSA3 | C57: 6 | D57: =IFERROR(__xludf.DUMMYFUNCTION("GOOGLEFINANCE(B57)"),28.1) -> 28.1 | E57: =C57*D57 -> 168.6 | F57: =E57/E102 -> 0.0041649961 | G57: =IFS(J57="Grupo 0",0,J57="Grupo 1",K57*H105/100,J57="Grupo 2",K57*I105/100,J57="Grupo 3",K57*J105/100,J57="Grupo 4",K57*K105/100) -> 0.0040540541 | H57: =IF(L57=1,I57/I102,0) -> 0.0014712834 | I57: =IF(L57=1,C102*G57-E57,0) -> 13.462452 | J57: Grupo 2 | K57: =IF(Balanceamentos!AZ37>0,Balanceamentos!AZ37,0) -> 3 | L57: =IF(G57>E57/C102,1,0) -> 1 | M57: =IF(L57=1,H57*L1,0) -> 6.5155908 | N57: =IF(M57>0,M57/D57,0) -> 0.23187156
A58: 57 | B58: AGRO3 | C58: 6 | D58: =IFERROR(__xludf.DUMMYFUNCTION("GOOGLEFINANCE(B58)"),20.61) -> 20.61 | E58: =C58*D58 -> 123.66 | F58: =E58/E102 -> 0.0030548245 | G58: =IFS(J58="Grupo 0",0,J58="Grupo 1",K58*H105/100,J58="Grupo 2",K58*I105/100,J58="Grupo 3",K58*J105/100,J58="Grupo 4",K58*K105/100) -> 0.0040540541 | H58: =IF(L58=1,I58/I102,0) -> 0.0063826828 | I58: =IF(L58=1,C102*G58-E58,0) -> 58.402452 | J58: Grupo 2 | K58: =IF(Balanceamentos!BA37>0,Balanceamentos!BA37,0) -> 3 | L58: =IF(G58>E58/C102,1,0) -> 1 | M58: =IF(L58=1,H58*L1,0) -> 28.265763 | N58: =IF(M58>0,M58/D58,0) -> 1.3714587
A59: 58 | B59: SOJA3 | C59: 31 | D59: =IFERROR(__xludf.DUMMYFUNCTION("GOOGLEFINANCE(B59)"),8.12) -> 8.12 | E59: =C59*D59 -> 251.72 | F59: =E59/E102 -> 0.0062183441 | G59: =IFS(J59="Grupo 0",0,J59="Grupo 1",K59*H105/100,J59="Grupo 2",K59*I105/100,J59="Grupo 3",K59*J105/100,J59="Grupo 4",K59*K105/100) -> 0.0094594595 | H59: =IF(L59=1,I59/I102,0) -> 0.018916908 | I59: =IF(L59=1,C102*G59-E59,0) -> 173.09239 | J59: Grupo 2 | K59: =IF(Balanceamentos!BB37>0,Balanceamentos!BB37,0) -> 7 | L59: =IF(G59>E59/C102,1,0) -> 1 | M59: =IF(L59=1,H59*L1,0) -> 83.773681 | N59: =IF(M59>0,M59/D59,0) -> 10.316956
A60: 59 | E60: =C60*D60 -> 0 | F60: =E60/E102 -> 0 | G60: =IFS(J60="Grupo 0",0,J60="Grupo 1",K60*H105/100,J60="Grupo 2",K60*I105/100,J60="Grupo 3",K60*J105/100,J60="Grupo 4",K60*K105/100) -> 0 | H60: =IF(L60=1,I60/I102,0) -> 0 | I60: =IF(L60=1,C102*G60-E60,0) -> 0 | J60: Grupo 0 | K60: =IF(Balanceamentos!BC37>0,Balanceamentos!BC37,0) -> 7 | L60: =IF(G60>E60/C102,1,0) -> 0 | M60: =IF(L60=1,H60*L1,0) -> 0 | N60: =IF(M60>0,M60/D60,0) -> 0
A61: 60 | B61: SMTO3 | C61: 41 | D61: =IFERROR(__xludf.DUMMYFUNCTION("GOOGLEFINANCE(B61)"),18.18) -> 18.18 | E61: =C61*D61 -> 745.38 | F61: =E61/E102 -> 0.018413433 | G61: =IFS(J61="Grupo 0",0,J61="Grupo 1",K61*H105/100,J61="Grupo 2",K61*I105/100,J61="Grupo 3",K61*J105/100,J61="Grupo 4",K61*K105/100) -> 0.02 | H61: =IF(L61=1,I61/I102,0) -> 0.016698623 | I61: =IF(L61=1,C102*G61-E61,0) -> 152.79476 | J61: Grupo 1 | K61: =IF(Balanceamentos!BD37>0,Balanceamentos!BD37,0) -> 7 | L61: =IF(G61>E61/C102,1,0) -> 1 | M61: =IF(L61=1,H61*L1,0) -> 73.949987 | N61: =IF(M61>0,M61/D61,0) -> 4.067656
A62: 61 | B62: MDIA3 | C62: 17 | D62: =IFERROR(__xludf.DUMMYFUNCTION("GOOGLEFINANCE(B62)"),21.66) -> 21.66 | E62: =C62*D62 -> 368.22 | F62: =E62/E102 -> 0.0090962922 | G62: =IFS(J62="Grupo 0",0,J62="Grupo 1",K62*H105/100,J62="Grupo 2",K62*I105/100,J62="Grupo 3",K62*J105/100,J62="Grupo 4",K62*K105/100) -> 0.014285714 | H62: =IF(L62=1,I62/I102,0) -> 0.02987204 | I62: =IF(L62=1,C102*G62-E62,0) -> 273.3334 | J62: Grupo 1 | K62: =IF(Balanceamentos!BE37>0,Balanceamentos!BE37,0) -> 5 | L62: =IF(G62>E62/C102,1,0) -> 1 | M62: =IF(L62=1,H62*L1,0) -> 132.28857 | N62: =IF(M62>0,M62/D62,0) -> 6.1075058
A63: 62 | B63: ABEV3 | C63: 69 | D63: =IFERROR(__xludf.DUMMYFUNCTION("GOOGLEFINANCE(""BVMF:ABEV3"")"),14.74) -> 14.74 | E63: =C63*D63 -> 1017.06 | F63: =E63/E102 -> 0.025124857 | G63: =IFS(J63="Grupo 0",0,J63="Grupo 1",K63*H105/100,J63="Grupo 2",K63*I105/100,J63="Grupo 3",K63*J105/100,J63="Grupo 4",K63*K105/100) -> 0.025714286 | H63: =IF(L63=1,I63/I102,0) -> 0.015052895 | I63: =IF(L63=1,C102*G63-E63,0) -> 137.73612 | J63: Grupo 1 | K63: =IF(Balanceamentos!BF37>0,Balanceamentos!BF37,0) -> 9 | L63: =IF(G63>E63/C102,1,0) -> 1 | M63: =IF(L63=1,H63*L1,0) -> 66.661869 | N63: =IF(M63>0,M63/D63,0) -> 4.5225149
A64: 63 | B64: GMAT3 | C64: 22 | D64: =IFERROR(__xludf.DUMMYFUNCTION("GOOGLEFINANCE(B64)"),4.85) -> 4.85 | E64: =C64*D64 -> 106.7 | F64: =E64/E102 -> 0.0026358546 | G64: =IFS(J64="Grupo 0",0,J64="Grupo 1",K64*H105/100,J64="Grupo 2",K64*I105/100,J64="Grupo 3",K64*J105/100,J64="Grupo 4",K64*K105/100) -> 0.0044871795 | H64: =IF(L64=1,I64/I102,0) -> 0.010361978 | I64: =IF(L64=1,C102*G64-E64,0) -> 94.813569 | J64: Grupo 4 | K64: =IF(Balanceamentos!BG37>0,Balanceamentos!BG37,0) -> 7 | L64: =IF(G64>E64/C102,1,0) -> 1 | M64: =IF(L64=1,H64*L1,0) -> 45.888105 | N64: =IF(M64>0,M64/D64,0) -> 9.461465
A65: 64 | B65: GRND3 | C65: 125 | D65: =IFERROR(__xludf.DUMMYFUNCTION("GOOGLEFINANCE(B65)"),4.57) -> 4.57 | E65: =C65*D65 -> 571.25 | F65: =E65/E102 -> 0.014111827 | G65: =IFS(J65="Grupo 0",0,J65="Grupo 1",K65*H105/100,J65="Grupo 2",K65*I105/100,J65="Grupo 3",K65*J105/100,J65="Grupo 4",K65*K105/100) -> 0.02 | H65: =IF(L65=1,I65/I102,0) -> 0.035728929 | I65: =IF(L65=1,C102*G65-E65,0) -> 326.92476 | J65: Grupo 1 | K65: =IF(Balanceamentos!BH37>0,Balanceamentos!BH37,0) -> 7 | L65: =IF(G65>E65/C102,1,0) -> 1 | M65: =IF(L65=1,H65*L1,0) -> 158.22585 | N65: =IF(M65>0,M65/D65,0) -> 34.622725
A66: 65 | B66: VULC3 | C66: 41 | D66: =IFERROR(__xludf.DUMMYFUNCTION("GOOGLEFINANCE(B66)"),16.33) -> 16.33 | E66: =C66*D66 -> 669.53 | F66: =E66/E102 -> 0.016539679 | G66: =IFS(J66="Grupo 0",0,J66="Grupo 1",K66*H105/100,J66="Grupo 2",K66*I105/100,J66="Grupo 3",K66*J105/100,J66="Grupo 4",K66*K105/100) -> 0.025714286 | H66: =IF(L66=1,I66/I102,0) -> 0.053033728 | I66: =IF(L66=1,C102*G66-E66,0) -> 485.26612 | J66: Grupo 1 | K66: =IF(Balanceamentos!BI37>0,Balanceamentos!BI37,0) -> 9 | L66: =IF(G66>E66/C102,1,0) -> 1 | M66: =IF(L66=1,H66*L1,0) -> 234.8603 | N66: =IF(M66>0,M66/D66,0) -> 14.382137
A67: 66 | B67: VIVA3 | C67: 11 | D67: =IFERROR(__xludf.DUMMYFUNCTION("GOOGLEFINANCE(B67)"),24.69) -> 24.69 | E67: =C67*D67 -> 271.59 | F67: =E67/E102 -> 0.006709201 | G67: =IFS(J67="Grupo 0",0,J67="Grupo 1",K67*H105/100,J67="Grupo 2",K67*I105/100,J67="Grupo 3",K67*J105/100,J67="Grupo 4",K67*K105/100) -> 0.0094594595 | H67: =IF(L67=1,I67/I102,0) -> 0.016745357 | I67: =IF(L67=1,C102*G67-E67,0) -> 153.22239 | J67: Grupo 2 | K67: =IF(Balanceamentos!BJ37>0,Balanceamentos!BJ37,0) -> 7 | L67: =IF(G67>E67/C102,1,0) -> 1 | M67: =IF(L67=1,H67*L1,0) -> 74.15695 | N67: =IF(M67>0,M67/D67,0) -> 3.0035217
A68: 67 | B68: LEVE3 | C68: 13 | D68: =IFERROR(__xludf.DUMMYFUNCTION("GOOGLEFINANCE(B68)"),34.32) -> 34.32 | E68: =C68*D68 -> 446.16 | F68: =E68/E102 -> 0.011021677 | G68: =IFS(J68="Grupo 0",0,J68="Grupo 1",K68*H105/100,J68="Grupo 2",K68*I105/100,J68="Grupo 3",K68*J105/100,J68="Grupo 4",K68*K105/100) -> 0.0108 | H68: =IF(L68=1,I68/I102,0) -> 0.0042463137 | I68: =IF(L68=1,C102*G68-E68,0) -> 38.854372 | J68: Grupo 3 | K68: =IF(Balanceamentos!BK37>0,Balanceamentos!BK37,0) -> 9 | L68: =IF(G68>E68/C102,1,0) -> 1 | M68: =IF(L68=1,H68*L1,0) -> 18.804835 | N68: =IF(M68>0,M68/D68,0) -> 0.54792643
A69: 68 | B69: CGRA3 | C69: 9 | D69: =IFERROR(__xludf.DUMMYFUNCTION("GOOGLEFINANCE(B69)"),27.6) -> 27.6 | E69: =C69*D69 -> 248.4 | F69: =E69/E102 -> 0.0061363288 | G69: =IFS(J69="Grupo 0",0,J69="Grupo 1",K69*H105/100,J69="Grupo 2",K69*I105/100,J69="Grupo 3",K69*J105/100,J69="Grupo 4",K69*K105/100) -> 0.0085714286 | H69: =IF(L69=1,I69/I102,0) -> 0.014921304 | I69: =IF(L69=1,C102*G69-E69,0) -> 136.53204 | J69: Grupo 1 | K69: =IF(Balanceamentos!BL37>0,Balanceamentos!BL37,0) -> 3 | L69: =IF(G69>E69/C102,1,0) -> 1 | M69: =IF(L69=1,H69*L1,0) -> 66.079114 | N69: =IF(M69>0,M69/D69,0) -> 2.3941708
A70: 69 | B70: LREN3 | C70: 43 | D70: =IFERROR(__xludf.DUMMYFUNCTION("GOOGLEFINANCE(""BVMF:LREN3"")"),15.09) -> 15.09 | E70: =C70*D70 -> 648.87 | F70: =E70/E102 -> 0.016029306 | G70: =IFS(J70="Grupo 0",0,J70="Grupo 1",K70*H105/100,J70="Grupo 2",K70*I105/100,J70="Grupo 3",K70*J105/100,J70="Grupo 4",K70*K105/100) -> 0.02 | H70: =IF(L70=1,I70/I102,0) -> 0.027246 | I70: =IF(L70=1,C102*G70-E70,0) -> 249.30476 | J70: Grupo 1 | K70: =IF(Balanceamentos!BM37>0,Balanceamentos!BM37,0) -> 7 | L70: =IF(G70>E70/C102,1,0) -> 1 | M70: =IF(L70=1,H70*L1,0) -> 120.65913 | N70: =IF(M70>0,M70/D70,0) -> 7.9959665
A71: 70 | B71: JHSF3 | C71: 11 | D71: =IFERROR(__xludf.DUMMYFUNCTION("GOOGLEFINANCE(B71)"),8.9) -> 8.9 | E71: =C71*D71 -> 97.9 | F71: =E71/E102 -> 0.0024184645 | G71: =IFS(J71="Grupo 0",0,J71="Grupo 1",K71*H105/100,J71="Grupo 2",K71*I105/100,J71="Grupo 3",K71*J105/100,J71="Grupo 4",K71*K105/100) -> 0.0019230769 | H71: =IF(L71=1,I71/I102,0) -> 0 | I71: =IF(L71=1,C102*G71-E71,0) -> 0 | J71: Grupo 4 | K71: =IF(Balanceamentos!BN37>0,Balanceamentos!BN37,0) -> 3 | L71: =IF(G71>E71/C102,1,0) -> 0 | M71: =IF(L71=1,H71*L1,0) -> 0 | N71: =IF(M71>0,M71/D71,0) -> 0
A72: 71 | B72: LAVV3 | C72: 10 | D72: =IFERROR(__xludf.DUMMYFUNCTION("GOOGLEFINANCE(B72)"),14.84) -> 14.84 | E72: =C72*D72 -> 148.4 | F72: =E72/E102 -> 0.0036659871 | G72: =IFS(J72="Grupo 0",0,J72="Grupo 1",K72*H105/100,J72="Grupo 2",K72*I105/100,J72="Grupo 3",K72*J105/100,J72="Grupo 4",K72*K105/100) -> 0.0040540541 | H72: =IF(L72=1,I72/I102,0) -> 0.0036788995 | I72: =IF(L72=1,C102*G72-E72,0) -> 33.662452 | J72: Grupo 2 | K72: =IF(Balanceamentos!BO37>0,Balanceamentos!BO37,0) -> 3 | L72: =IF(G72>E72/C102,1,0) -> 1 | M72: =IF(L72=1,H72*L1,0) -> 16.292037 | N72: =IF(M72>0,M72/D72,0) -> 1.0978461
A73: 72 | B73: CURY3 | C73: 7 | D73: =IFERROR(__xludf.DUMMYFUNCTION("GOOGLEFINANCE(B73)"),35.24) -> 35.24 | E73: =C73*D73 -> 246.68 | F73: =E73/E102 -> 0.0060938389 | G73: =IFS(J73="Grupo 0",0,J73="Grupo 1",K73*H105/100,J73="Grupo 2",K73*I105/100,J73="Grupo 3",K73*J105/100,J73="Grupo 4",K73*K105/100) -> 0.0067567568 | H73: =IF(L73=1,I73/I102,0) -> 0.0062029007 | I73: =IF(L73=1,C102*G73-E73,0) -> 56.75742 | J73: Grupo 2 | K73: =IF(Balanceamentos!BP37>0,Balanceamentos!BP37,0) -> 5 | L73: =IF(G73>E73/C102,1,0) -> 1 | M73: =IF(L73=1,H73*L1,0) -> 27.469596 | N73: =IF(M73>0,M73/D73,0) -> 0.77950046
A74: 73 | B74: EZTC3 | C74: 17 | D74: =IFERROR(__xludf.DUMMYFUNCTION("GOOGLEFINANCE(B74)"),13.51) -> 13.51 | E74: =C74*D74 -> 229.67 | F74: =E74/E102 -> 0.0056736338 | G74: =IFS(J74="Grupo 0",0,J74="Grupo 1",K74*H105/100,J74="Grupo 2",K74*I105/100,J74="Grupo 3",K74*J105/100,J74="Grupo 4",K74*K105/100) -> 0.0067567568 | H74: =IF(L74=1,I74/I102,0) -> 0.0080618883 | I74: =IF(L74=1,C102*G74-E74,0) -> 73.76742 | J74: Grupo 2 | K74: =IF(Balanceamentos!BQ37>0,Balanceamentos!BQ37,0) -> 5 | L74: =IF(G74>E74/C102,1,0) -> 1 | M74: =IF(L74=1,H74*L1,0) -> 35.702138 | N74: =IF(M74>0,M74/D74,0) -> 2.6426453
A75: 74 | B75: DIRR3 | C75: 11 | D75: =IFERROR(__xludf.DUMMYFUNCTION("GOOGLEFINANCE(B75)"),13.9) -> 13.9 | E75: =C75*D75 -> 152.9 | F75: =E75/E102 -> 0.0037771525 | G75: =IFS(J75="Grupo 0",0,J75="Grupo 1",K75*H105/100,J75="Grupo 2",K75*I105/100,J75="Grupo 3",K75*J105/100,J75="Grupo 4",K75*K105/100) -> 0.0044871795 | H75: =IF(L75=1,I75/I102,0) -> 0.0053128761 | I75: =IF(L75=1,C102*G75-E75,0) -> 48.613569 | J75: Grupo 4 | K75: =IF(Balanceamentos!BR37>0,Balanceamentos!BR37,0) -> 7 | L75: =IF(G75>E75/C102,1,0) -> 1 | M75: =IF(L75=1,H75*L1,0) -> 23.528115 | N75: =IF(M75>0,M75/D75,0) -> 1.6926701
A76: 75 | B76: SYNE3 | C76: 12 | D76: =IFERROR(__xludf.DUMMYFUNCTION("GOOGLEFINANCE(B76)"),4.62) -> 4.62 | E76: =C76*D76 -> 55.44 | F76: =E76/E102 -> 0.0013695574 | G76: =IFS(J76="Grupo 0",0,J76="Grupo 1",K76*H105/100,J76="Grupo 2",K76*I105/100,J76="Grupo 3",K76*J105/100,J76="Grupo 4",K76*K105/100) -> 0.0019230769 | H76: =IF(L76=1,I76/I102,0) -> 0.0033795059 | I76: =IF(L76=1,C102*G76-E76,0) -> 30.922958 | J76: Grupo 4 | K76: =IF(Balanceamentos!BS37>0,Balanceamentos!BS37,0) -> 3 | L76: =IF(G76>E76/C102,1,0) -> 1 | M76: =IF(L76=1,H76*L1,0) -> 14.96617 | N76: =IF(M76>0,M76/D76,0) -> 3.2394306
A77: 76 | B77: LOGG3 | C77: 3 | D77: =IFERROR(__xludf.DUMMYFUNCTION("GOOGLEFINANCE(B77)"),26.67) -> 26.67 | E77: =C77*D77 -> 80.01 | F77: =E77/E102 -> 0.0019765204 | G77: =IFS(J77="Grupo 0",0,J77="Grupo 1",K77*H105/100,J77="Grupo 2",K77*I105/100,J77="Grupo 3",K77*J105/100,J77="Grupo 4",K77*K105/100) -> 0.0019230769 | H77: =IF(L77=1,I77/I102,0) -> 0.0006943016 | I77: =IF(L77=1,C102*G77-E77,0) -> 6.352958 | J77: Grupo 4 | K77: =IF(Balanceamentos!BT37>0,Balanceamentos!BT37,0) -> 3 | L77: =IF(G77>E77/C102,1,0) -> 1 | M77: =IF(L77=1,H77*L1,0) -> 3.0747203 | N77: =IF(M77>0,M77/D77,0) -> 0.1152876
A78: 77 | B78: PLPL3 | C78: 15 | D78: =IFERROR(__xludf.DUMMYFUNCTION("GOOGLEFINANCE(B78)"),14.2) -> 14.2 | E78: =C78*D78 -> 213 | F78: =E78/E102 -> 0.0052618278 | G78: =IFS(J78="Grupo 0",0,J78="Grupo 1",K78*H105/100,J78="Grupo 2",K78*I105/100,J78="Grupo 3",K78*J105/100,J78="Grupo 4",K78*K105/100) -> 0.0067567568 | H78: =IF(L78=1,I78/I102,0) -> 0.009883718 | I78: =IF(L78=1,C102*G78-E78,0) -> 90.43742 | J78: Grupo 2 | K78: =IF(Balanceamentos!BU37>0,Balanceamentos!BU37,0) -> 5 | L78: =IF(G78>E78/C102,1,0) -> 1 | M78: =IF(L78=1,H78*L1,0) -> 43.770126 | N78: =IF(M78>0,M78/D78,0) -> 3.0824032
A79: 78 | B79: ITSA3 | C79: 75 | D79: =IFERROR(__xludf.DUMMYFUNCTION("GOOGLEFINANCE(B79)"),13.4) -> 13.4 | E79: =C79*D79 -> 1005 | F79: =E79/E102 -> 0.024826934 | G79: =IFS(J79="Grupo 0",0,J79="Grupo 1",K79*H105/100,J79="Grupo 2",K79*I105/100,J79="Grupo 3",K79*J105/100,J79="Grupo 4",K79*K105/100) -> 0.025714286 | H79: =IF(L79=1,I79/I102,0) -> 0.016370908 | I79: =IF(L79=1,C102*G79-E79,0) -> 149.79612 | J79: Grupo 1 | K79: =IF(Balanceamentos!BV37>0,Balanceamentos!BV37,0) -> 9 | L79: =IF(G79>E79/C102,1,0) -> 1 | M79: =IF(L79=1,H79*L1,0) -> 72.498698 | N79: =IF(M79>0,M79/D79,0) -> 5.4103506
A80: 79 | B80: BRAP3 | C80: 2 | D80: =IFERROR(__xludf.DUMMYFUNCTION("GOOGLEFINANCE(B80)"),19.2) -> 19.2 | E80: =C80*D80 -> 38.4 | F80: =E80/E102 -> 0.00094861121 | G80: =IFS(J80="Grupo 0",0,J80="Grupo 1",K80*H105/100,J80="Grupo 2",K80*I105/100,J80="Grupo 3",K80*J105/100,J80="Grupo 4",K80*K105/100) -> 0.0012 | H80: =IF(L80=1,I80/I102,0) -> 0.0016929231 | I80: =IF(L80=1,C102*G80-E80,0) -> 15.490486 | J80: Grupo 3 | K80: =IF(Balanceamentos!BW37>0,Balanceamentos!BW37,0) -> 1 | L80: =IF(G80>E80/C102,1,0) -> 1 | M80: =IF(L80=1,H80*L1,0) -> 7.4971236 | N80: =IF(M80>0,M80/D80,0) -> 0.39047519
A81: 80 | B81: ITUB3 | C81: 30 | D81: =IFERROR(__xludf.DUMMYFUNCTION("GOOGLEFINANCE(""BVMF:ITUB3"")"),41.14) -> 41.14 | E81: =C81*D81 -> 1234.2 | F81: =E81/E102 -> 0.030488957 | G81: =IFS(J81="Grupo 0",0,J81="Grupo 1",K81*H105/100,J81="Grupo 2",K81*I105/100,J81="Grupo 3",K81*J105/100,J81="Grupo 4",K81*K105/100) -> 0.031428571 | H81: =IF(L81=1,I81/I102,0) -> 0.019367731 | I81: =IF(L81=1,C102*G81-E81,0) -> 177.21748 | J81: Grupo 1 | K81: =IF(Balanceamentos!BX37>0,Balanceamentos!BX37,0) -> 11 | L81: =IF(G81>E81/C102,1,0) -> 1 | M81: =IF(L81=1,H81*L1,0) -> 85.770156 | N81: =IF(M81>0,M81/D81,0) -> 2.0848361
A82: 81 | B82: BBDC3 | C82: 19 | D82: =IFERROR(__xludf.DUMMYFUNCTION("GOOGLEFINANCE(""BVMF:BBDC3"")"),16.08) -> 16.08 | E82: =C82*D82 -> 305.52 | F82: =E82/E102 -> 0.0075473879 | G82: =IFS(J82="Grupo 0",0,J82="Grupo 1",K82*H105/100,J82="Grupo 2",K82*I105/100,J82="Grupo 3",K82*J105/100,J82="Grupo 4",K82*K105/100) -> 0.0084 | H82: =IF(L82=1,I82/I102,0) -> 0.0078374088 | I82: =IF(L82=1,C102*G82-E82,0) -> 71.713401 | J82: Grupo 3 | K82: =IF(Balanceamentos!BY37>0,Balanceamentos!BY37,0) -> 7 | L82: =IF(G82>E82/C102,1,0) -> 1 | M82: =IF(L82=1,H82*L1,0) -> 34.708029 | N82: =IF(M82>0,M82/D82,0) -> 2.1584595
A83: 82 | B83: SANB3 | C83: 20 | D83: =IFERROR(__xludf.DUMMYFUNCTION("GOOGLEFINANCE(""BVMF:SANB3"")"),14.68) -> 14.68 | E83: =C83*D83 -> 293.6 | F83: =E83/E102 -> 0.0072529232 | G83: =IFS(J83="Grupo 0",0,J83="Grupo 1",K83*H105/100,J83="Grupo 2",K83*I105/100,J83="Grupo 3",K83*J105/100,J83="Grupo 4",K83*K105/100) -> 0.0084 | H83: =IF(L83=1,I83/I102,0) -> 0.0091401208 | I83: =IF(L83=1,C102*G83-E83,0) -> 83.6334 | J83: Grupo 3 | K83: =IF(Balanceamentos!BZ37>0,Balanceamentos!BZ37,0) -> 7 | L83: =IF(G83>E83/C102,1,0) -> 1 | M83: =IF(L83=1,H83*L1,0) -> 40.4771 | N83: =IF(M83>0,M83/D83,0) -> 2.7572956
A84: 83 | B84: BRSR3 | C84: 10 | D84: =IFERROR(__xludf.DUMMYFUNCTION("GOOGLEFINANCE(B84)"),18.8) -> 18.8 | E84: =C84*D84 -> 188 | F84: =E84/E102 -> 0.0046442424 | G84: =IFS(J84="Grupo 0",0,J84="Grupo 1",K84*H105/100,J84="Grupo 2",K84*I105/100,J84="Grupo 3",K84*J105/100,J84="Grupo 4",K84*K105/100) -> 0.0040540541 | H84: =IF(L84=1,I84/I102,0) -> 0 | I84: =IF(L84=1,C102*G84-E84,0) -> 0 | J84: Grupo 2 | K84: =IF(Balanceamentos!CA37>0,Balanceamentos!CA37,0) -> 3 | L84: =IF(G84>E84/C102,1,0) -> 0 | M84: =IF(L84=1,H84*L1,0) -> 0 | N84: =IF(M84>0,M84/D84,0) -> 0
A85: 84 | B85: BEES3 | C85: 17 | D85: =IFERROR(__xludf.DUMMYFUNCTION("GOOGLEFINANCE(B85)"),8.56) -> 8.56 | E85: =C85*D85 -> 145.52 | F85: =E85/E102 -> 0.0035948412 | G85: =IFS(J85="Grupo 0",0,J85="Grupo 1",K85*H105/100,J85="Grupo 2",K85*I105/100,J85="Grupo 3",K85*J105/100,J85="Grupo 4",K85*K105/100) -> 0.0040540541 | H85: =IF(L85=1,I85/I102,0) -> 0.0039936488 | I85: =IF(L85=1,C102*G85-E85,0) -> 36.542452 | J85: Grupo 2 | K85: =IF(Balanceamentos!CB37>0,Balanceamentos!CB37,0) -> 3 | L85: =IF(G85>E85/C102,1,0) -> 1 | M85: =IF(L85=1,H85*L1,0) -> 17.685906 | N85: =IF(M85>0,M85/D85,0) -> 2.0661105
A86: 85 | B86: BPAC3 | C86: 20 | D86: =IFERROR(__xludf.DUMMYFUNCTION("GOOGLEFINANCE(B86)"),39.86) -> 39.86 | E86: =C86*D86 -> 797.2 | F86: =E86/E102 -> 0.019693564 | G86: =IFS(J86="Grupo 0",0,J86="Grupo 1",K86*H105/100,J86="Grupo 2",K86*I105/100,J86="Grupo 3",K86*J105/100,J86="Grupo 4",K86*K105/100) -> 0.014864865 | H86: =IF(L86=1,I86/I102,0) -> 0 | I86: =IF(L86=1,C102*G86-E86,0) -> 0 | J86: Grupo 2 | K86: =IF(Balanceamentos!CC37>0,Balanceamentos!CC37,0) -> 11 | L86: =IF(G86>E86/C102,1,0) -> 0 | M86: =IF(L86=1,H86*L1,0) -> 0 | N86: =IF(M86>0,M86/D86,0) -> 0
A87: 86 | B87: BGIP3 | C87: 2 | D87: =IFERROR(__xludf.DUMMYFUNCTION("GOOGLEFINANCE(B87)"),62.24) -> 62.24 | E87: =C87*D87 -> 124.48 | F87: =E87/E102 -> 0.0030750813 | G87: =IFS(J87="Grupo 0",0,J87="Grupo 1",K87*H105/100,J87="Grupo 2",K87*I105/100,J87="Grupo 3",K87*J105/100,J87="Grupo 4",K87*K105/100) -> 0.0028571429 | H87: =IF(L87=1,I87/I102,0) -> 0.00041864712 | I87: =IF(L87=1,C102*G87-E87,0) -> 3.8306804 | J87: Grupo 1 | K87: =IF(Balanceamentos!CD37>0,Balanceamentos!CD37,0) -> 1 | L87: =IF(G87>E87/C102,1,0) -> 1 | M87: =IF(L87=1,H87*L1,0) -> 1.8539822 | N87: =IF(M87>0,M87/D87,0) -> 0.029787631
A88: 87 | B88: PSSA3 | C88: 21 | D88: =IFERROR(__xludf.DUMMYFUNCTION("GOOGLEFINANCE(""BVMF:PSSA3"")"),47.65) -> 47.65 | E88: =C88*D88 -> 1000.65 | F88: =E88/E102 -> 0.024719474 | G88: =IFS(J88="Grupo 0",0,J88="Grupo 1",K88*H105/100,J88="Grupo 2",K88*I105/100,J88="Grupo 3",K88*J105/100,J88="Grupo 4",K88*K105/100) -> 0.031428571 | H88: =IF(L88=1,I88/I102,0) -> 0.044891926 | I88: =IF(L88=1,C102*G88-E88,0) -> 410.76748 | J88: Grupo 1 | K88: =IF(Balanceamentos!CE37>0,Balanceamentos!CE37,0) -> 11 | L88: =IF(G88>E88/C102,1,0) -> 1 | M88: =IF(L88=1,H88*L1,0) -> 198.80426 | N88: =IF(M88>0,M88/D88,0) -> 4.1721776
A89: 88 | B89: WIZC3 | C89: 19 | D89: =IFERROR(__xludf.DUMMYFUNCTION("GOOGLEFINANCE(""BVMF:WIZC3"")"),8.89) -> 8.89 | E89: =C89*D89 -> 168.91 | F89: =E89/E102 -> 0.0041726542 | G89: =IFS(J89="Grupo 0",0,J89="Grupo 1",K89*H105/100,J89="Grupo 2",K89*I105/100,J89="Grupo 3",K89*J105/100,J89="Grupo 4",K89*K105/100) -> 0.0040540541 | H89: =IF(L89=1,I89/I102,0) -> 0.0014374042 | I89: =IF(L89=1,C102*G89-E89,0) -> 13.152452 | J89: Grupo 2 | K89: =IF(Balanceamentos!CF37>0,Balanceamentos!CF37,0) -> 3 | L89: =IF(G89>E89/C102,1,0) -> 1 | M89: =IF(L89=1,H89*L1,0) -> 6.3655562 | N89: =IF(M89>0,M89/D89,0) -> 0.71603557
A90: 89 | B90: B3SA3 | C90: 34 | D90: =IFERROR(__xludf.DUMMYFUNCTION("GOOGLEFINANCE(B90)"),17.12) -> 17.12 | E90: =C90*D90 -> 582.08 | F90: =E90/E102 -> 0.014379365 | G90: =IFS(J90="Grupo 0",0,J90="Grupo 1",K90*H105/100,J90="Grupo 2",K90*I105/100,J90="Grupo 3",K90*J105/100,J90="Grupo 4",K90*K105/100) -> 0.0132 | H90: =IF(L90=1,I90/I102,0) -> 0.0011710577 | I90: =IF(L90=1,C102*G90-E90,0) -> 10.715344 | J90: Grupo 3 | K90: =IF(Balanceamentos!CG37>0,Balanceamentos!CG37,0) -> 11 | L90: =IF(G90>E90/C102,1,0) -> 1 | M90: =IF(L90=1,H90*L1,0) -> 5.1860385 | N90: =IF(M90>0,M90/D90,0) -> 0.30292281
A91: 90 | B91: TTEN3 | C91: 8 | D91: =IFERROR(__xludf.DUMMYFUNCTION("GOOGLEFINANCE(B91)"),14.82) -> 14.82 | E91: =C91*D91 -> 118.56 | F91: =E91/E102 -> 0.0029288371 | G91: =IFS(J91="Grupo 0",0,J91="Grupo 1",K91*H105/100,J91="Grupo 2",K91*I105/100,J91="Grupo 3",K91*J105/100,J91="Grupo 4",K91*K105/100) -> 0.0032051282 | H91: =IF(L91=1,I91/I102,0) -> 0.0027735378 | I91: =IF(L91=1,C102*G91-E91,0) -> 25.378263 | J91: Grupo 4 | K91: =IF(Balanceamentos!CH37>0,Balanceamentos!CH37,0) -> 5 | L91: =IF(G91>E91/C102,1,0) -> 1 | M91: =IF(L91=1,H91*L1,0) -> 12.282635 | N91: =IF(M91>0,M91/D91,0) -> 0.82878776
A92: 91 | B92: CAML3 | C92: 78 | D92: =IFERROR(__xludf.DUMMYFUNCTION("GOOGLEFINANCE(B92)"),5.83) -> 5.83 | E92: =C92*D92 -> 454.74 | F92: =E92/E102 -> 0.011233632 | G92: =IFS(J92="Grupo 0",0,J92="Grupo 1",K92*H105/100,J92="Grupo 2",K92*I105/100,J92="Grupo 3",K92*J105/100,J92="Grupo 4",K92*K105/100) -> 0.012162162 | H92: =IF(L92=1,I92/I102,0) -> 0.0099940918 | I92: =IF(L92=1,C102*G92-E92,0) -> 91.447356 | J92: Grupo 2 | K92: =IF(Balanceamentos!CI37>0,Balanceamentos!CI37,0) -> 9 | L92: =IF(G92>E92/C102,1,0) -> 1 | M92: =IF(L92=1,H92*L1,0) -> 44.258917 | N92: =IF(M92>0,M92/D92,0) -> 7.591581
A93: 92 | G93: =IFS(J93="Grupo 0",0,J93="Grupo 1",K93*H105/100,J93="Grupo 2",K93*I105/100,J93="Grupo 3",K93*J105/100,J93="Grupo 4",K93*K105/100) -> 0 | H93: =IF(L93=1,I93/I102,0) -> 0 | I93: =IF(L93=1,C102*G93-E93,0) -> 0 | J93: Grupo 0 | L93: =IF(G93>E93/C102,1,0) -> 0 | M93: =IF(L93=1,H93*L1,0) -> 0 | N93: =IF(M93>0,M93/D93,0) -> 0
A94: 93 | G94: =IFS(J94="Grupo 0",0,J94="Grupo 1",K94*H105/100,J94="Grupo 2",K94*I105/100,J94="Grupo 3",K94*J105/100,J94="Grupo 4",K94*K105/100) -> 0 | H94: =IF(L94=1,I94/I102,0) -> 0 | I94: =IF(L94=1,C102*G94-E94,0) -> 0 | J94: Grupo 0 | L94: =IF(G94>E94/C102,1,0) -> 0 | M94: =IF(L94=1,H94*L1,0) -> 0 | N94: =IF(M94>0,M94/D94,0) -> 0
A95: 94 | G95: =IFS(J95="Grupo 0",0,J95="Grupo 1",K95*H105/100,J95="Grupo 2",K95*I105/100,J95="Grupo 3",K95*J105/100,J95="Grupo 4",K95*K105/100) -> 0 | H95: =IF(L95=1,I95/I102,0) -> 0 | I95: =IF(L95=1,C102*G95-E95,0) -> 0 | J95: Grupo 0 | L95: =IF(G95>E95/C102,1,0) -> 0 | M95: =IF(L95=1,H95*L1,0) -> 0 | N95: =IF(M95>0,M95/D95,0) -> 0
A96: 95 | G96: =IFS(J96="Grupo 0",0,J96="Grupo 1",K96*H105/100,J96="Grupo 2",K96*I105/100,J96="Grupo 3",K96*J105/100,J96="Grupo 4",K96*K105/100) -> 0 | H96: =IF(L96=1,I96/I102,0) -> 0 | I96: =IF(L96=1,C102*G96-E96,0) -> 0 | J96: Grupo 0 | L96: =IF(G96>E96/C102,1,0) -> 0 | M96: =IF(L96=1,H96*L1,0) -> 0 | N96: =IF(M96>0,M96/D96,0) -> 0
A97: 96 | G97: =IFS(J97="Grupo 0",0,J97="Grupo 1",K97*H105/100,J97="Grupo 2",K97*I105/100,J97="Grupo 3",K97*J105/100,J97="Grupo 4",K97*K105/100) -> 0 | H97: =IF(L97=1,I97/I102,0) -> 0 | I97: =IF(L97=1,C102*G97-E97,0) -> 0 | J97: Grupo 0 | L97: =IF(G97>E97/C102,1,0) -> 0 | M97: =IF(L97=1,H97*L1,0) -> 0 | N97: =IF(M97>0,M97/D97,0) -> 0
A98: 97 | G98: =IFS(J98="Grupo 0",0,J98="Grupo 1",K98*H105/100,J98="Grupo 2",K98*I105/100,J98="Grupo 3",K98*J105/100,J98="Grupo 4",K98*K105/100) -> 0 | H98: =IF(L98=1,I98/I102,0) -> 0 | I98: =IF(L98=1,C102*G98-E98,0) -> 0 | J98: Grupo 0 | L98: =IF(G98>E98/C102,1,0) -> 0 | M98: =IF(L98=1,H98*L1,0) -> 0 | N98: =IF(M98>0,M98/D98,0) -> 0
A99: 98 | G99: =IFS(J99="Grupo 0",0,J99="Grupo 1",K99*H105/100,J99="Grupo 2",K99*I105/100,J99="Grupo 3",K99*J105/100,J99="Grupo 4",K99*K105/100) -> 0 | H99: =IF(L99=1,I99/I102,0) -> 0 | I99: =IF(L99=1,C102*G99-E99,0) -> 0 | J99: Grupo 0 | L99: =IF(G99>E99/C102,1,0) -> 0 | M99: =IF(L99=1,H99*L1,0) -> 0 | N99: =IF(M99>0,M99/D99,0) -> 0
A100: 99 | G100: =IFS(J100="Grupo 0",0,J100="Grupo 1",K100*H105/100,J100="Grupo 2",K100*I105/100,J100="Grupo 3",K100*J105/100,J100="Grupo 4",K100*K105/100) -> 0 | H100: =IF(L100=1,I100/I102,0) -> 0 | I100: =IF(L100=1,C102*G100-E100,0) -> 0 | J100: Grupo 0 | L100: =IF(G100>E100/C102,1,0) -> 0 | M100: =IF(L100=1,H100*L1,0) -> 0 | N100: =IF(M100>0,M100/D100,0) -> 0
...

Sheet Exterior
B1: Ativo | C1: Cotação Brl | D1: Quantidade | E1: Cotação | F1: Saldo | G1: %Carteira | H1: %C/aporte | I1: % Ideal | J1: Bal | K1: Bal | M1: Aporte: | N1: =SUM(D42:D46) -> 816.29519 | O1: Aporte ideal por ativo | P1: % após aport
A2: 1 | B2: VOO | C2: =F2*I46 -> 3051.9363 | D2: 0.953 | E2: =IFERROR(__xludf.DUMMYFUNCTION("GOOGLEFINANCE(B2)"),608.38) -> 608.38 | F2: =D2*E2 -> 579.78614 | G2: =IFS(L2="Grupo 0",0,L2="Grupo 1",F2/F42,L2="Grupo 2",F2/F43,L2="Grupo 3",F2/F44,L2="Grupo 4",F2/F45,L2="Grupo 5",F2/F46) -> 0.31913181 | H2: =IFS(L2="Grupo 0",0,L2="Grupo 1",F2/E42,L2="Grupo 2",F2/E43,L2="Grupo 3",F2/E44,L2="Grupo 4",F2/E45,L2="Grupo 5",F2/E46) -> 0.27721294 | I2: =IFS(L2="Grupo 0",0,L2="Grupo 1",M2/M42,L2="Grupo 2",M2/M43,L2="Grupo 3",M2/M44,L2="Grupo 4",M2/M45,L2="Grupo 5",M2/M46) -> 0.33333333 | J2: =IFS(L2="Grupo 0",0,L2="Grupo 1",K2/K42,L2="Grupo 2",K2/K43,L2="Grupo 3",K2/K44,L2="Grupo 4",K2/K45,L2="Grupo 5",K2/K46) -> 0.4272492 | K2: =IFS(L2="Grupo 0",0,L2="Grupo 1",(E42*I2-F2)*N2,L2="Grupo 2",(E43*I2-F2)*N2,L2="Grupo 3",(E44*I2-F2)*N2,L2="Grupo 4",(E45*I2-F2)*N2,L2="Grupo 5",(E46*I2-F2)*N2) -> 117.37484 | L2: Grupo 1 | M2: 10 | N2: =IF(I2<H2,0,1) -> 1 | O2: =IFS(L2="Grupo 0",0,L2="Grupo 1",J2*D42,L2="Grupo 2",J2*D43,L2="Grupo 3",J2*D44,L2="Grupo 4",J2*D45,L2="Grupo 5",J2*D46) -> 117.37484 | P2: =(F2+O2)/D41 -> 0.10972434
A3: 2 | B3: QQQM | C3: =F3*I46 -> 3012.1434 | D3: 2.336 | E3: =IFERROR(__xludf.DUMMYFUNCTION("GOOGLEFINANCE(B3)"),244.96) -> 244.96 | F3: =D3*E3 -> 572.22656 | G3: =IFS(L3="Grupo 0",0,L3="Grupo 1",F3/F42,L3="Grupo 2",F3/F43,L3="Grupo 3",F3/F44,L3="Grupo 4",F3/F45,L3="Grupo 5",F3/F46) -> 0.31497079 | H3: =IFS(L3="Grupo 0",0,L3="Grupo 1",F3/E42,L3="Grupo 2",F3/E43,L3="Grupo 3",F3/E44,L3="Grupo 4",F3/E45,L3="Grupo 5",F3/E46) -> 0.27359848 | I3: =IFS(L3="Grupo 0",0,L3="Grupo 1",M3/M42,L3="Grupo 2",M3/M43,L3="Grupo 3",M3/M44,L3="Grupo 4",M3/M45,L3="Grupo 5",M3/M46) -> 0.33333333 | J3: =IFS(L3="Grupo 0",0,L3="Grupo 1",K3/K42,L3="Grupo 2",K3/K43,L3="Grupo 3",K3/K44,L3="Grupo 4",K3/K45,L3="Grupo 5",K3/K46) -> 0.45476638 | K3: =IFS(L3="Grupo 0",0,L3="Grupo 1",(E42*I3-F3)*N3,L3="Grupo 2",(E43*I3-F3)*N3,L3="Grupo 3",(E44*I3-F3)*N3,L3="Grupo 4",(E45*I3-F3)*N3,L3="Grupo 5",(E46*I3-F3)*N3) -> 124.93442 | L3: Grupo 1 | M3: 10 | N3: =IF(I3<H3,0,1) -> 1 | O3: =IFS(L3="Grupo 0",0,L3="Grupo 1",J3*D42,L3="Grupo 2",J3*D43,L3="Grupo 3",J3*D44,L3="Grupo 4",J3*D45,L3="Grupo 5",J3*D46) -> 124.93442 | P3: =(F3+O3)/D41 -> 0.10972434
A4: 3 | B4: SCHD | C4: =F4*I46 -> 3499.1672 | D4: 21.738 | E4: =IFERROR(__xludf.DUMMYFUNCTION("GOOGLEFINANCE(B4)"),30.58) -> 30.58 | F4: =D4*E4 -> 664.74804 | G4: =IFS(L4="Grupo 0",0,L4="Grupo 1",F4/F42,L4="Grupo 2",F4/F43,L4="Grupo 3",F4/F44,L4="Grupo 4",F4/F45,L4="Grupo 5",F4/F46) -> 0.3658974 | H4: =IFS(L4="Grupo 0",0,L4="Grupo 1",F4/E42,L4="Grupo 2",F4/E43,L4="Grupo 3",F4/E44,L4="Grupo 4",F4/E45,L4="Grupo 5",F4/E46) -> 0.31783575 | I4: =IFS(L4="Grupo 0",0,L4="Grupo 1",M4/M42,L4="Grupo 2",M4/M43,L4="Grupo 3",M4/M44,L4="Grupo 4",M4/M45,L4="Grupo 5",M4/M46) -> 0.33333333 | J4: =IFS(L4="Grupo 0",0,L4="Grupo 1",K4/K42,L4="Grupo 2",K4/K43,L4="Grupo 3",K4/K44,L4="Grupo 4",K4/K45,L4="Grupo 5",K4/K46) -> 0.11798441 | K4: =IFS(L4="Grupo 0",0,L4="Grupo 1",(E42*I4-F4)*N4,L4="Grupo 2",(E43*I4-F4)*N4,L4="Grupo 3",(E44*I4-F4)*N4,L4="Grupo 4",(E45*I4-F4)*N4,L4="Grupo 5",(E46*I4-F4)*N4) -> 32.412936 | L4: Grupo 1 | M4: 10 | N4: =IF(I4<H4,0,1) -> 1 | O4: =IFS(L4="Grupo 0",0,L4="Grupo 1",J4*D42,L4="Grupo 2",J4*D43,L4="Grupo 3",J4*D44,L4="Grupo 4",J4*D45,L4="Grupo 5",J4*D46) -> 32.412936 | P4: =(F4+O4)/D41 -> 0.10972434
A5: 4 | B5: BND | C5: =F5*I46 -> 1452.4763 | D5: 3.745 | E5: =IFERROR(__xludf.DUMMYFUNCTION("GOOGLEFINANCE(B5)"),73.68) -> 73.68 | F5: =D5*E5 -> 275.9316 | G5: =IFS(L5="Grupo 0",0,L5="Grupo 1",F5/F42,L5="Grupo 2",F5/F43,L5="Grupo 3",F5/F44,L5="Grupo 4",F5/F45,L5="Grupo 5",F5/F46) -> 0.29312796 | H5: =IFS(L5="Grupo 0",0,L5="Grupo 1",F5/E42,L5="Grupo 2",F5/E43,L5="Grupo 3",F5/E44,L5="Grupo 4",F5/E45,L5="Grupo 5",F5/E46) -> 0.25650867 | I5: =IFS(L5="Grupo 0",0,L5="Grupo 1",M5/M42,L5="Grupo 2",M5/M43,L5="Grupo 3",M5/M44,L5="Grupo 4",M5/M45,L5="Grupo 5",M5/M46) -> 0.3125 | J5: =IFS(L5="Grupo 0",0,L5="Grupo 1",K5/K42,L5="Grupo 2",K5/K43,L5="Grupo 3",K5/K44,L5="Grupo 4",K5/K45,L5="Grupo 5",K5/K46) -> 0.44819615 | K5: =IFS(L5="Grupo 0",0,L5="Grupo 1",(E42*I5-F5)*N5,L5="Grupo 2",(E43*I5-F5)*N5,L5="Grupo 3",(E44*I5-F5)*N5,L5="Grupo 4",(E45*I5-F5)*N5,L5="Grupo 5",(E46*I5-F5)*N5) -> 60.231019 | L5: Grupo 3 | M5: 10 | N5: =IF(I5<H5,0,1) -> 1 | O5: =IFS(L5="Grupo 0",0,L5="Grupo 1",J5*D42,L5="Grupo 2",J5*D43,L5="Grupo 3",J5*D44,L5="Grupo 4",J5*D45,L5="Grupo 5",J5*D46) -> 60.231019 | P5: =(F5+O5)/D41 -> 0.052907753
A6: 5 | B6: IAU | C6: =F6*I46 -> 1759.8233 | D6: 3.669 | E6: =IFERROR(__xludf.DUMMYFUNCTION("GOOGLEFINANCE(B6)"),91.12) -> 91.12 | F6: =D6*E6 -> 334.31928 | G6: =IFS(L6="Grupo 0",0,L6="Grupo 1",F6/F42,L6="Grupo 2",F6/F43,L6="Grupo 3",F6/F44,L6="Grupo 4",F6/F45,L6="Grupo 5",F6/F46) -> 0.35515442 | H6: =IFS(L6="Grupo 0",0,L6="Grupo 1",F6/E42,L6="Grupo 2",F6/E43,L6="Grupo 3",F6/E44,L6="Grupo 4",F6/E45,L6="Grupo 5",F6/E46) -> 0.31078641 | I6: =IFS(L6="Grupo 0",0,L6="Grupo 1",M6/M42,L6="Grupo 2",M6/M43,L6="Grupo 3",M6/M44,L6="Grupo 4",M6/M45,L6="Grupo 5",M6/M46) -> 0.3125 | J6: =IFS(L6="Grupo 0",0,L6="Grupo 1",K6/K42,L6="Grupo 2",K6/K43,L6="Grupo 3",K6/K44,L6="Grupo 4",K6/K45,L6="Grupo 5",K6/K46) -> 0.013716813 | K6: =IFS(L6="Grupo 0",0,L6="Grupo 1",(E42*I6-F6)*N6,L6="Grupo 2",(E43*I6-F6)*N6,L6="Grupo 3",(E44*I6-F6)*N6,L6="Grupo 4",(E45*I6-F6)*N6,L6="Grupo 5",(E46*I6-F6)*N6) -> 1.8433395 | L6: Grupo 3 | M6: 10 | N6: =IF(I6<H6,0,1) -> 1 | O6: =IFS(L6="Grupo 0",0,L6="Grupo 1",J6*D42,L6="Grupo 2",J6*D43,L6="Grupo 3",J6*D44,L6="Grupo 4",J6*D45,L6="Grupo 5",J6*D46) -> 1.8433395 | P6: =(F6+O6)/D41 -> 0.052907753
A7: 6 | B7: SCHP | C7: =F7*I46 -> 1169.9276 | D7: 8.29 | E7: =IFERROR(__xludf.DUMMYFUNCTION("GOOGLEFINANCE(B7)"),26.81) -> 26.81 | F7: =D7*E7 -> 222.2549 | G7: =IFS(L7="Grupo 0",0,L7="Grupo 1",F7/F42,L7="Grupo 2",F7/F43,L7="Grupo 3",F7/F44,L7="Grupo 4",F7/F45,L7="Grupo 5",F7/F46) -> 0.23610607 | H7: =IFS(L7="Grupo 0",0,L7="Grupo 1",F7/E42,L7="Grupo 2",F7/E43,L7="Grupo 3",F7/E44,L7="Grupo 4",F7/E45,L7="Grupo 5",F7/E46) -> 0.20661029 | I7: =IFS(L7="Grupo 0",0,L7="Grupo 1",M7/M42,L7="Grupo 2",M7/M43,L7="Grupo 3",M7/M44,L7="Grupo 4",M7/M45,L7="Grupo 5",M7/M46) -> 0.25 | J7: =IFS(L7="Grupo 0",0,L7="Grupo 1",K7/K42,L7="Grupo 2",K7/K43,L7="Grupo 3",K7/K44,L7="Grupo 4",K7/K45,L7="Grupo 5",K7/K46) -> 0.34732341 | K7: =IFS(L7="Grupo 0",0,L7="Grupo 1",(E42*I7-F7)*N7,L7="Grupo 2",(E43*I7-F7)*N7,L7="Grupo 3",(E44*I7-F7)*N7,L7="Grupo 4",(E45*I7-F7)*N7,L7="Grupo 5",(E46*I7-F7)*N7) -> 46.675196 | L7: Grupo 3 | M7: 8 | N7: =IF(I7<H7,0,1) -> 1 | O7: =IFS(L7="Grupo 0",0,L7="Grupo 1",J7*D42,L7="Grupo 2",J7*D43,L7="Grupo 3",J7*D44,L7="Grupo 4",J7*D45,L7="Grupo 5",J7*D46) -> 46.675196 | P7: =(F7+O7)/D41 -> 0.042326202
A8: 7 | B8: FALN | C8: =F8*I46 -> 572.86603 | D8: 4.076 | E8: =IFERROR(__xludf.DUMMYFUNCTION("GOOGLEFINANCE(B8)"),26.7) -> 26.7 | F8: =D8*E8 -> 108.8292 | G8: =IFS(L8="Grupo 0",0,L8="Grupo 1",F8/F42,L8="Grupo 2",F8/F43,L8="Grupo 3",F8/F44,L8="Grupo 4",F8/F45,L8="Grupo 5",F8/F46) -> 0.11561155 | H8: =IFS(L8="Grupo 0",0,L8="Grupo 1",F8/E42,L8="Grupo 2",F8/E43,L8="Grupo 3",F8/E44,L8="Grupo 4",F8/E45,L8="Grupo 5",F8/E46) -> 0.10116867 | I8: =IFS(L8="Grupo 0",0,L8="Grupo 1",M8/M42,L8="Grupo 2",M8/M43,L8="Grupo 3",M8/M44,L8="Grupo 4",M8/M45,L8="Grupo 5",M8/M46) -> 0.125 | J8: =IFS(L8="Grupo 0",0,L8="Grupo 1",K8/K42,L8="Grupo 2",K8/K43,L8="Grupo 3",K8/K44,L8="Grupo 4",K8/K45,L8="Grupo 5",K8/K46) -> 0.19076363 | K8: =IFS(L8="Grupo 0",0,L8="Grupo 1",(E42*I8-F8)*N8,L8="Grupo 2",(E43*I8-F8)*N8,L8="Grupo 3",(E44*I8-F8)*N8,L8="Grupo 4",(E45*I8-F8)*N8,L8="Grupo 5",(E46*I8-F8)*N8) -> 25.635848 | L8: Grupo 3 | M8: 4 | N8: =IF(I8<H8,0,1) -> 1 | O8: =IFS(L8="Grupo 0",0,L8="Grupo 1",J8*D42,L8="Grupo 2",J8*D43,L8="Grupo 3",J8*D44,L8="Grupo 4",J8*D45,L8="Grupo 5",J8*D46) -> 25.635848 | P8: =(F8+O8)/D41 -> 0.021163101
A9: 8 | C9: =F9*I46 -> 0 | F9: =D9*E9 -> 0 | G9: =IFS(L9="Grupo 0",0,L9="Grupo 1",F9/F42,L9="Grupo 2",F9/F43,L9="Grupo 3",F9/F44,L9="Grupo 4",F9/F45,L9="Grupo 5",F9/F46) -> 0 | H9: =IFS(L9="Grupo 0",0,L9="Grupo 1",F9/E42,L9="Grupo 2",F9/E43,L9="Grupo 3",F9/E44,L9="Grupo 4",F9/E45,L9="Grupo 5",F9/E46) -> 0 | I9: =IFS(L9="Grupo 0",0,L9="Grupo 1",M9/M42,L9="Grupo 2",M9/M43,L9="Grupo 3",M9/M44,L9="Grupo 4",M9/M45,L9="Grupo 5",M9/M46) -> 0 | J9: =IFS(L9="Grupo 0",0,L9="Grupo 1",K9/K42,L9="Grupo 2",K9/K43,L9="Grupo 3",K9/K44,L9="Grupo 4",K9/K45,L9="Grupo 5",K9/K46) -> 0 | K9: =IFS(L9="Grupo 0",0,L9="Grupo 1",(E42*I9-F9)*N9,L9="Grupo 2",(E43*I9-F9)*N9,L9="Grupo 3",(E44*I9-F9)*N9,L9="Grupo 4",(E45*I9-F9)*N9,L9="Grupo 5",(E46*I9-F9)*N9) -> 0 | L9: Grupo 0 | M9: 10 | N9: =IF(I9<H9,0,1) -> 1 | O9: =IFS(L9="Grupo 0",0,L9="Grupo 1",J9*D42,L9="Grupo 2",J9*D43,L9="Grupo 3",J9*D44,L9="Grupo 4",J9*D45,L9="Grupo 5",J9*D46) -> 0 | P9: =(F9+O9)/D41 -> 0
A10: 9 | B10: HAUZ | C10: =F10*I46 -> 1289.1028 | D10: 10.497 | E10: =IFERROR(__xludf.DUMMYFUNCTION("GOOGLEFINANCE(B10)"),23.33) -> 23.33 | F10: =D10*E10 -> 244.89501 | G10: =IFS(L10="Grupo 0",0,L10="Grupo 1",F10/F42,L10="Grupo 2",F10/F43,L10="Grupo 3",F10/F44,L10="Grupo 4",F10/F45,L10="Grupo 5",F10/F46) -> 0.28303147 | H10: =IFS(L10="Grupo 0",0,L10="Grupo 1",F10/E42,L10="Grupo 2",F10/E43,L10="Grupo 3",F10/E44,L10="Grupo 4",F10/E45,L10="Grupo 5",F10/E46) -> 0.24331054 | I10: =IFS(L10="Grupo 0",0,L10="Grupo 1",M10/M42,L10="Grupo 2",M10/M43,L10="Grupo 3",M10/M44,L10="Grupo 4",M10/M45,L10="Grupo 5",M10/M46) -> 0.28571429 | J10: =IFS(L10="Grupo 0",0,L10="Grupo 1",K10/K42,L10="Grupo 2",K10/K43,L10="Grupo 3",K10/K44,L10="Grupo 4",K10/K45,L10="Grupo 5",K10/K46) -> 0.30214786 | K10: =IFS(L10="Grupo 0",0,L10="Grupo 1",(E42*I10-F10)*N10,L10="Grupo 2",(E43*I10-F10)*N10,L10="Grupo 3",(E44*I10-F10)*N10,L10="Grupo 4",(E45*I10-F10)*N10,L10="Grupo 5",(E46*I10-F10)*N10) -> 42.679889 | L10: Grupo 2 | M10: 4 | N10: =IF(I10<H10,0,1) -> 1 | O10: =IFS(L10="Grupo 0",0,L10="Grupo 1",J10*D42,L10="Grupo 2",J10*D43,L10="Grupo 3",J10*D44,L10="Grupo 4",J10*D45,L10="Grupo 5",J10*D46) -> 42.679889 | P10: =(F10+O10)/D41 -> 0.045260659
A11: 10 | B11: VNQ | C11: =F11*I46 -> 3265.5244 | D11: 6.746 | E11: =IFERROR(__xludf.DUMMYFUNCTION("GOOGLEFINANCE(B11)"),91.96) -> 91.96 | F11: =D11*E11 -> 620.36216 | G11: =IFS(L11="Grupo 0",0,L11="Grupo 1",F11/F42,L11="Grupo 2",F11/F43,L11="Grupo 3",F11/F44,L11="Grupo 4",F11/F45,L11="Grupo 5",F11/F46) -> 0.71696853 | H11: =IFS(L11="Grupo 0",0,L11="Grupo 1",F11/E42,L11="Grupo 2",F11/E43,L11="Grupo 3",F11/E44,L11="Grupo 4",F11/E45,L11="Grupo 5",F11/E46) -> 0.61634841 | I11: =IFS(L11="Grupo 0",0,L11="Grupo 1",M11/M42,L11="Grupo 2",M11/M43,L11="Grupo 3",M11/M44,L11="Grupo 4",M11/M45,L11="Grupo 5",M11/M46) -> 0.71428571 | J11: =IFS(L11="Grupo 0",0,L11="Grupo 1",K11/K42,L11="Grupo 2",K11/K43,L11="Grupo 3",K11/K44,L11="Grupo 4",K11/K45,L11="Grupo 5",K11/K46) -> 0.69785214 | K11: =IFS(L11="Grupo 0",0,L11="Grupo 1",(E42*I11-F11)*N11,L11="Grupo 2",(E43*I11-F11)*N11,L11="Grupo 3",(E44*I10-F11)*N11,L11="Grupo 4",(E45*I11-F11)*N11,L11="Grupo 5",(E46*I11-F11)*N11) -> 98.575087 | L11: Grupo 2 | M11: 10 | N11: =IF(I11<H11,0,1) -> 1 | O11: =IFS(L11="Grupo 0",0,L11="Grupo 1",J11*D42,L11="Grupo 2",J11*D43,L11="Grupo 3",J11*D44,L11="Grupo 4",J11*D45,L11="Grupo 5",J11*D46) -> 98.575087 | P11: =(F11+O11)/D41 -> 0.11315165
A12: 11 | C12: =F12*I46 -> 0 | F12: =D12*E12 -> 0 | G12: =IFS(L12="Grupo 0",0,L12="Grupo 1",F12/F42,L12="Grupo 2",F12/F43,L12="Grupo 3",F12/F44,L12="Grupo 4",F12/F45,L12="Grupo 5",F12/F46) -> 0 | H12: =IFS(L12="Grupo 0",0,L12="Grupo 1",F12/E42,L12="Grupo 2",F12/E43,L12="Grupo 3",F12/E44,L12="Grupo 4",F12/E45,L12="Grupo 5",F12/E46) -> 0 | I12: =IFS(L12="Grupo 0",0,L12="Grupo 1",M12/M42,L12="Grupo 2",M12/M43,L12="Grupo 3",M12/M44,L12="Grupo 4",M12/M45,L12="Grupo 5",M12/M46) -> 0 | J12: =IFS(L12="Grupo 0",0,L12="Grupo 1",K12/K42,L12="Grupo 2",K12/K43,L12="Grupo 3",K12/K44,L12="Grupo 4",K12/K45,L12="Grupo 5",K12/K46) -> 0 | K12: =IFS(L12="Grupo 0",0,L12="Grupo 1",(E42*I12-F12)*N12,L12="Grupo 2",(E43*I12-F12)*N12,L12="Grupo 3",(E44*I12-F12)*N12,L12="Grupo 4",(E45*I12-F12)*N12,L12="Grupo 5",(E46*I12-F12)*N12) -> 0 | L12: Grupo 0 | N12: =IF(I12<H12,0,1) -> 1 | O12: =IFS(L12="Grupo 0",0,L12="Grupo 1",J12*D42,L12="Grupo 2",J12*D43,L12="Grupo 3",J12*D44,L12="Grupo 4",J12*D45,L12="Grupo 5",J12*D46) -> 0 | P12: =(F12+O12)/D41 -> 0
A13: 12 | C13: =F13*I46 -> 0 | F13: =D13*E13 -> 0 | G13: =IFS(L13="Grupo 0",0,L13="Grupo 1",F13/F42,L13="Grupo 2",F13/F43,L13="Grupo 3",F13/F44,L13="Grupo 4",F13/F45,L13="Grupo 5",F13/F46) -> 0 | H13: =IFS(L13="Grupo 0",0,L13="Grupo 1",F13/E42,L13="Grupo 2",F13/E43,L13="Grupo 3",F13/E44,L13="Grupo 4",F13/E45,L13="Grupo 5",F13/E46) -> 0 | I13: =IFS(L13="Grupo 0",0,L13="Grupo 1",M13/M42,L13="Grupo 2",M13/M43,L13="Grupo 3",M13/M44,L13="Grupo 4",M13/M45,L13="Grupo 5",M13/M46) -> 0 | J13: =IFS(L13="Grupo 0",0,L13="Grupo 1",K13/K42,L13="Grupo 2",K13/K43,L13="Grupo 3",K13/K44,L13="Grupo 4",K13/K45,L13="Grupo 5",K13/K46) -> 0 | K13: =IFS(L13="Grupo 0",0,L13="Grupo 1",(E42*I13-F13)*N13,L13="Grupo 2",(E43*I13-F13)*N13,L13="Grupo 3",(E44*I13-F13)*N13,L13="Grupo 4",(E45*I13-F13)*N13,L13="Grupo 5",(E46*I13-F13)*N13) -> 0 | L13: Grupo 0 | M13: 10 | N13: =IF(I13<H13,0,1) -> 1 | O13: =IFS(L13="Grupo 0",0,L13="Grupo 1",J13*D42,L13="Grupo 2",J13*D43,L13="Grupo 3",J13*D44,L13="Grupo 4",J13*D45,L13="Grupo 5",J13*D46) -> 0 | P13: =(F13+O13)/D41 -> 0
A14: 13 | B14: IVLU | C14: =F14*I46 -> 1914.6939 | D14: 9.272 | E14: =IFERROR(__xludf.DUMMYFUNCTION("GOOGLEFINANCE(B14)"),39.23) -> 39.23 | F14: =D14*E14 -> 363.74056 | G14: =IFS(L14="Grupo 0",0,L14="Grupo 1",F14/F42,L14="Grupo 2",F14/F43,L14="Grupo 3",F14/F44,L14="Grupo 4",F14/F45,L14="Grupo 5",F14/F46) -> 0.39447413 | H14: =IFS(L14="Grupo 0",0,L14="Grupo 1",F14/E42,L14="Grupo 2",F14/E43,L14="Grupo 3",F14/E44,L14="Grupo 4",F14/E45,L14="Grupo 5",F14/E46) -> 0.34373096 | I14: =IFS(L14="Grupo 0",0,L14="Grupo 1",M14/M42,L14="Grupo 2",M14/M43,L14="Grupo 3",M14/M44,L14="Grupo 4",M14/M45,L14="Grupo 5",M14/M46) -> 0.375 | J14: =IFS(L14="Grupo 0",0,L14="Grupo 1",K14/K42,L14="Grupo 2",K14/K43,L14="Grupo 3",K14/K44,L14="Grupo 4",K14/K45,L14="Grupo 5",K14/K46) -> 0.24308351 | K14: =IFS(L14="Grupo 0",0,L14="Grupo 1",(E42*I14-F14)*N14,L14="Grupo 2",(E43*I14-F14)*N14,L14="Grupo 3",(E44*I14-F14)*N14,L14="Grupo 4",(E45*I14-F14)*N14,L14="Grupo 5",(E46*I14-F14)*N14) -> 33.0893 | L14: Grupo 4 | M14: 6 | N14: =IF(I14<H14,0,1) -> 1 | O14: =IFS(L14="Grupo 0",0,L14="Grupo 1",J14*D42,L14="Grupo 2",J14*D43,L14="Grupo 3",J14*D44,L14="Grupo 4",J14*D45,L14="Grupo 5",J14*D46) -> 33.0893 | P14: =(F14+O14)/D41 -> 0.06245601
A15: 14 | B15: SPEU | C15: =F15*I46 -> 2939.0945 | D15: 10.901 | E15: =IFERROR(__xludf.DUMMYFUNCTION("GOOGLEFINANCE(B15)"),51.22) -> 51.22 | F15: =D15*E15 -> 558.34922 | G15: =IFS(L15="Grupo 0",0,L15="Grupo 1",F15/F42,L15="Grupo 2",F15/F43,L15="Grupo 3",F15/F44,L15="Grupo 4",F15/F45,L15="Grupo 5",F15/F46) -> 0.60552587 | H15: =IFS(L15="Grupo 0",0,L15="Grupo 1",F15/E42,L15="Grupo 2",F15/E43,L15="Grupo 3",F15/E44,L15="Grupo 4",F15/E45,L15="Grupo 5",F15/E46) -> 0.52763408 | I15: =IFS(L15="Grupo 0",0,L15="Grupo 1",M15/M42,L15="Grupo 2",M15/M43,L15="Grupo 3",M15/M44,L15="Grupo 4",M15/M45,L15="Grupo 5",M15/M46) -> 0.625 | J15: =IFS(L15="Grupo 0",0,L15="Grupo 1",K15/K42,L15="Grupo 2",K15/K43,L15="Grupo 3",K15/K44,L15="Grupo 4",K15/K45,L15="Grupo 5",K15/K46) -> 0.75691649 | K15: =IFS(L15="Grupo 0",0,L15="Grupo 1",(E42*I15-F15)*N15,L15="Grupo 2",(E43*I15-F15)*N15,L15="Grupo 3",(E44*I15-F15)*N15,L15="Grupo 4",(E45*I15-F15)*N15,L15="Grupo 5",(E46*I15-F15)*N15) -> 103.03388 | L15: Grupo 4 | M15: 10 | N15: =IF(I15<H15,0,1) -> 1 | O15: =IFS(L15="Grupo 0",0,L15="Grupo 1",J15*D42,L15="Grupo 2",J15*D43,L15="Grupo 3",J15*D44,L15="Grupo 4",J15*D45,L15="Grupo 5",J15*D46) -> 103.03388 | P15: =(F15+O15)/D41 -> 0.10409335
A16: 15 | C16: =F16*I46 -> 0 | F16: =D16*E16 -> 0 | G16: =IFS(L16="Grupo 0",0,L16="Grupo 1",F16/F42,L16="Grupo 2",F16/F43,L16="Grupo 3",F16/F44,L16="Grupo 4",F16/F45,L16="Grupo 5",F16/F46) -> 0 | H16: =IFS(L16="Grupo 0",0,L16="Grupo 1",F16/E42,L16="Grupo 2",F16/E43,L16="Grupo 3",F16/E44,L16="Grupo 4",F16/E45,L16="Grupo 5",F16/E46) -> 0 | I16: =IFS(L16="Grupo 0",0,L16="Grupo 1",M16/M42,L16="Grupo 2",M16/M43,L16="Grupo 3",M16/M44,L16="Grupo 4",M16/M45,L16="Grupo 5",M16/M46) -> 0 | J16: =IFS(L16="Grupo 0",0,L16="Grupo 1",K16/K42,L16="Grupo 2",K16/K43,L16="Grupo 3",K16/K44,L16="Grupo 4",K16/K45,L16="Grupo 5",K16/K46) -> 0 | K16: =IFS(L16="Grupo 0",0,L16="Grupo 1",(E42*I16-F16)*N16,L16="Grupo 2",(E43*I16-F16)*N16,L16="Grupo 3",(E44*I16-F16)*N16,L16="Grupo 4",(E45*I16-F16)*N16,L16="Grupo 5",(E46*I16-F16)*N16) -> 0 | L16: Grupo 0 | N16: =IF(I16<H16,0,1) -> 1 | O16: =IFS(L16="Grupo 0",0,L16="Grupo 1",J16*D42,L16="Grupo 2",J16*D43,L16="Grupo 3",J16*D44,L16="Grupo 4",J16*D45,L16="Grupo 5",J16*D46) -> 0 | P16: =(F16+O16)/D41 -> 0
A17: 16 | C17: =F17*I46 -> 0 | F17: =D17*E17 -> 0 | G17: =IFS(L17="Grupo 0",0,L17="Grupo 1",F17/F42,L17="Grupo 2",F17/F43,L17="Grupo 3",F17/F44,L17="Grupo 4",F17/F45,L17="Grupo 5",F17/F46) -> 0 | H17: =IFS(L17="Grupo 0",0,L17="Grupo 1",F17/E42,L17="Grupo 2",F17/E43,L17="Grupo 3",F17/E44,L17="Grupo 4",F17/E45,L17="Grupo 5",F17/E46) -> 0 | I17: =IFS(L17="Grupo 0",0,L17="Grupo 1",M17/M42,L17="Grupo 2",M17/M43,L17="Grupo 3",M17/M44,L17="Grupo 4",M17/M45,L17="Grupo 5",M17/M46) -> 0 | J17: =IFS(L17="Grupo 0",0,L17="Grupo 1",K17/K42,L17="Grupo 2",K17/K43,L17="Grupo 3",K17/K44,L17="Grupo 4",K17/K45,L17="Grupo 5",K17/K46) -> 0 | K17: =IFS(L17="Grupo 0",0,L17="Grupo 1",(E42*I17-F17)*N17,L17="Grupo 2",(E43*I17-F17)*N17,L17="Grupo 3",(E44*I17-F17)*N17,L17="Grupo 4",(E45*I17-F17)*N17,L17="Grupo 5",(E46*I17-F17)*N17) -> 0 | L17: Grupo 0 | N17: =IF(I17<H17,0,1) -> 1 | O17: =IFS(L17="Grupo 0",0,L17="Grupo 1",J17*D42,L17="Grupo 2",J17*D43,L17="Grupo 3",J17*D44,L17="Grupo 4",J17*D45,L17="Grupo 5",J17*D46) -> 0 | P17: =(F17+O17)/D41 -> 0
A18: 17 | C18: =F18*I46 -> 0 | F18: =D18*E18 -> 0 | G18: =IFS(L18="Grupo 0",0,L18="Grupo 1",F18/F42,L18="Grupo 2",F18/F43,L18="Grupo 3",F18/F44,L18="Grupo 4",F18/F45,L18="Grupo 5",F18/F46) -> 0 | H18: =IFS(L18="Grupo 0",0,L18="Grupo 1",F18/E42,L18="Grupo 2",F18/E43,L18="Grupo 3",F18/E44,L18="Grupo 4",F18/E45,L18="Grupo 5",F18/E46) -> 0 | I18: =IFS(L18="Grupo 0",0,L18="Grupo 1",M18/M42,L18="Grupo 2",M18/M43,L18="Grupo 3",M18/M44,L18="Grupo 4",M18/M45,L18="Grupo 5",M18/M46) -> 0 | J18: =IFS(L18="Grupo 0",0,L18="Grupo 1",K18/K42,L18="Grupo 2",K18/K43,L18="Grupo 3",K18/K44,L18="Grupo 4",K18/K45,L18="Grupo 5",K18/K46) -> 0 | K18: =IFS(L18="Grupo 0",0,L18="Grupo 1",(E42*I18-F18)*N18,L18="Grupo 2",(E43*I18-F18)*N18,L18="Grupo 3",(E44*I18-F18)*N18,L18="Grupo 4",(E45*I18-F18)*N18,L18="Grupo 5",(E46*I18-F18)*N18) -> 0 | L18: Grupo 0 | N18: =IF(I18<H18,0,1) -> 1 | O18: =IFS(L18="Grupo 0",0,L18="Grupo 1",J18*D42,L18="Grupo 2",J18*D43,L18="Grupo 3",J18*D44,L18="Grupo 4",J18*D45,L18="Grupo 5",J18*D46) -> 0 | P18: =(F18+O18)/D41 -> 0
A19: 18 | B19: FLCH | C19: =F19*I46 -> 1057.5401 | D19: 8.754 | E19: =IFERROR(__xludf.DUMMYFUNCTION("GOOGLEFINANCE(B19)"),22.95) -> 22.95 | F19: =D19*E19 -> 200.9043 | G19: =IFS(L19="Grupo 0",0,L19="Grupo 1",F19/F42,L19="Grupo 2",F19/F43,L19="Grupo 3",F19/F44,L19="Grupo 4",F19/F45,L19="Grupo 5",F19/F46) -> 0.20252207 | H19: =IFS(L19="Grupo 0",0,L19="Grupo 1",F19/E42,L19="Grupo 2",F19/E43,L19="Grupo 3",F19/E44,L19="Grupo 4",F19/E45,L19="Grupo 5",F19/E46) -> 0.17908761 | I19: =IFS(L19="Grupo 0",0,L19="Grupo 1",M19/M42,L19="Grupo 2",M19/M43,L19="Grupo 3",M19/M44,L19="Grupo 4",M19/M45,L19="Grupo 5",M19/M46) -> 0.24390244 | J19: =IFS(L19="Grupo 0",0,L19="Grupo 1",K19/K42,L19="Grupo 2",K19/K43,L19="Grupo 3",K19/K44,L19="Grupo 4",K19/K45,L19="Grupo 5",K19/K46) -> 0.46105379 | K19: =IFS(L19="Grupo 0",0,L19="Grupo 1",(E42*I19-F19)*N19,L19="Grupo 2",(E43*I19-F19)*N19,L19="Grupo 3",(E44*I19-F19)*N19,L19="Grupo 4",(E45*I19-F19)*N19,L19="Grupo 5",(E46*I19-F19)*N19) -> 72.710656 | L19: Grupo 5 | M19: 10 | N19: =IF(I19<H19,0,1) -> 1 | O19: =IFS(L19="Grupo 0",0,L19="Grupo 1",J19*D42,L19="Grupo 2",J19*D43,L19="Grupo 3",J19*D44,L19="Grupo 4",J19*D45,L19="Grupo 5",J19*D46) -> 59.849138 | P19: =(F19+O19)/D41 -> 0.041039299
A20: 19 | B20: FLKR | C20: =F20*I46 -> 1299.0667 | D20: 5.758 | E20: =IFERROR(__xludf.DUMMYFUNCTION("GOOGLEFINANCE(B20)"),42.86) -> 42.86 | F20: =D20*E20 -> 246.78788 | G20: =IFS(L20="Grupo 0",0,L20="Grupo 1",F20/F42,L20="Grupo 2",F20/F43,L20="Grupo 3",F20/F44,L20="Grupo 4",F20/F45,L20="Grupo 5",F20/F46) -> 0.24877513 | H20: =IFS(L20="Grupo 0",0,L20="Grupo 1",F20/E42,L20="Grupo 2",F20/E43,L20="Grupo 3",F20/E44,L20="Grupo 4",F20/E45,L20="Grupo 5",F20/E46) -> 0.21998858 | I20: =IFS(L20="Grupo 0",0,L20="Grupo 1",M20/M42,L20="Grupo 2",M20/M43,L20="Grupo 3",M20/M44,L20="Grupo 4",M20/M45,L20="Grupo 5",M20/M46) -> 0.19512195 | J20: =IFS(L20="Grupo 0",0,L20="Grupo 1",K20/K42,L20="Grupo 2",K20/K43,L20="Grupo 3",K20/K44,L20="Grupo 4",K20/K45,L20="Grupo 5",K20/K46) -> 0 | K20: =IFS(L20="Grupo 0",0,L20="Grupo 1",(E42*I20-F20)*N20,L20="Grupo 2",(E43*I20-F20)*N20,L20="Grupo 3",(E44*I20-F20)*N20,L20="Grupo 4",(E45*I20-F20)*N20,L20="Grupo 5",(E46*I20-F20)*N20) -> 0 | L20: Grupo 5 | M20: 8 | N20: =IF(I20<H20,0,1) -> 0 | O20: =IFS(L20="Grupo 0",0,L20="Grupo 1",J20*D42,L20="Grupo 2",J20*D43,L20="Grupo 3",J20*D44,L20="Grupo 4",J20*D45,L20="Grupo 5",J20*D46) -> 0 | P20: =(F20+O20)/D41 -> 0.038841297
A21: 20 | B21: VPL | C21: =F21*I46 -> 1135.9401 | D21: 2.18 | E21: =IFERROR(__xludf.DUMMYFUNCTION("GOOGLEFINANCE(B21)"),98.99) -> 98.99 | F21: =D21*E21 -> 215.7982 | G21: =IFS(L21="Grupo 0",0,L21="Grupo 1",F21/F42,L21="Grupo 2",F21/F43,L21="Grupo 3",F21/F44,L21="Grupo 4",F21/F45,L21="Grupo 5",F21/F46) -> 0.21753591 | H21: =IFS(L21="Grupo 0",0,L21="Grupo 1",F21/E42,L21="Grupo 2",F21/E43,L21="Grupo 3",F21/E44,L21="Grupo 4",F21/E45,L21="Grupo 5",F21/E46) -> 0.19236415 | I21: =IFS(L21="Grupo 0",0,L21="Grupo 1",M21/M42,L21="Grupo 2",M21/M43,L21="Grupo 3",M21/M44,L21="Grupo 4",M21/M45,L21="Grupo 5",M21/M46) -> 0.2195122 | J21: =IFS(L21="Grupo 0",0,L21="Grupo 1",K21/K42,L21="Grupo 2",K21/K43,L21="Grupo 3",K21/K44,L21="Grupo 4",K21/K45,L21="Grupo 5",K21/K46) -> 0.19311493 | K21: =IFS(L21="Grupo 0",0,L21="Grupo 1",(E42*I21-F21)*N21,L21="Grupo 2",(E43*I21-F21)*N21,L21="Grupo 3",(E44*I20-F21)*N21,L21="Grupo 4",(E45*I21-F21)*N21,L21="Grupo 5",(E46*I21-F21)*N21) -> 30.45526 | L21: Grupo 5 | M21: 9 | N21: =IF(I21<H21,0,1) -> 1 | O21: =IFS(L21="Grupo 0",0,L21="Grupo 1",J21*D42,L21="Grupo 2",J21*D43,L21="Grupo 3",J21*D44,L21="Grupo 4",J21*D45,L21="Grupo 5",J21*D46) -> 25.068142 | P21: =(F21+O21)/D41 -> 0.037909322
A22: 21 | B22: FLTW | C22: =F22*I46 -> 1038.2903 | D22: 2.843 | E22: =IFERROR(__xludf.DUMMYFUNCTION("GOOGLEFINANCE(B22)"),69.38) -> 69.38 | F22: =D22*E22 -> 197.24734 | G22: =IFS(L22="Grupo 0",0,L22="Grupo 1",F22/F42,L22="Grupo 2",F22/F43,L22="Grupo 3",F22/F44,L22="Grupo 4",F22/F45,L22="Grupo 5",F22/F46) -> 0.19883567 | H22: =IFS(L22="Grupo 0",0,L22="Grupo 1",F22/E42,L22="Grupo 2",F22/E43,L22="Grupo 3",F22/E44,L22="Grupo 4",F22/E45,L22="Grupo 5",F22/E46) -> 0.17582777 | I22: =IFS(L22="Grupo 0",0,L22="Grupo 1",M22/M42,L22="Grupo 2",M22/M43,L22="Grupo 3",M22/M44,L22="Grupo 4",M22/M45,L22="Grupo 5",M22/M46) -> 0.19512195 | J22: =IFS(L22="Grupo 0",0,L22="Grupo 1",K22/K42,L22="Grupo 2",K22/K43,L22="Grupo 3",K22/K44,L22="Grupo 4",K22/K45,L22="Grupo 5",K22/K46) -> 0.13724723 | K22: =IFS(L22="Grupo 0",0,L22="Grupo 1",(E42*I22-F22)*N22,L22="Grupo 2",(E43*I22-F22)*N22,L22="Grupo 3",(E44*I22-F22)*N22,L22="Grupo 4",(E45*I22-F22)*N22,L22="Grupo 5",(E46*I22-F22)*N22) -> 21.644624 | L22: Grupo 5 | M22: 8 | N22: =IF(I22<H22,0,1) -> 1 | O22: =IFS(L22="Grupo 0",0,L22="Grupo 1",J22*D42,L22="Grupo 2",J22*D43,L22="Grupo 3",J22*D44,L22="Grupo 4",J22*D45,L22="Grupo 5",J22*D46) -> 17.815987
A23: 22 | B23: FLJH | C23: =F23*I46 -> 691.014 | D23: 3.255 | E23: =IFERROR(__xludf.DUMMYFUNCTION("GOOGLEFINANCE(B23)"),40.33) -> 40.33 | F23: =D23*E23 -> 131.27415 | G23: =IFS(L23="Grupo 0",0,L23="Grupo 1",F23/F42,L23="Grupo 2",F23/F43,L23="Grupo 3",F23/F44,L23="Grupo 4",F23/F45,L23="Grupo 5",F23/F46) -> 0.13233123 | H23: =IFS(L23="Grupo 0",0,L23="Grupo 1",F23/E42,L23="Grupo 2",F23/E43,L23="Grupo 3",F23/E44,L23="Grupo 4",F23/E45,L23="Grupo 5",F23/E46) -> 0.11701877 | I23: =IFS(L23="Grupo 0",0,L23="Grupo 1",M23/M42,L23="Grupo 2",M23/M43,L23="Grupo 3",M23/M44,L23="Grupo 4",M23/M45,L23="Grupo 5",M23/M46) -> 0.14634146 | J23: =IFS(L23="Grupo 0",0,L23="Grupo 1",K23/K42,L23="Grupo 2",K23/K43,L23="Grupo 3",K23/K44,L23="Grupo 4",K23/K45,L23="Grupo 5",K23/K46) -> 0.20858405 | K23: =IFS(L23="Grupo 0",0,L23="Grupo 1",(E42*I23-F23)*N23,L23="Grupo 2",(E43*I23-F23)*N23,L23="Grupo 3",(E44*I23-F23)*N23,L23="Grupo 4",(E45*I23-F23)*N23,L23="Grupo 5",(E46*I23-F23)*N23) -> 32.894823 | L23: Grupo 5 | M23: 6 | N23: =IF(I23<H23,0,1) -> 1 | O23: =IFS(L23="Grupo 0",0,L23="Grupo 1",J23*D42,L23="Grupo 2",J23*D43,L23="Grupo 3",J23*D44,L23="Grupo 4",J23*D45,L23="Grupo 5",J23*D46) -> 27.07618
A24: 23 | C24: =F24*I46 -> 0 | F24: =D24*E24 -> 0 | G24: =IFS(L24="Grupo 0",0,L24="Grupo 1",F24/F42,L24="Grupo 2",F24/F43,L24="Grupo 3",F24/F44,L24="Grupo 4",F24/F45,L24="Grupo 5",F24/F46) -> 0 | H24: =IFS(L24="Grupo 0",0,L24="Grupo 1",F24/E42,L24="Grupo 2",F24/E43,L24="Grupo 3",F24/E44,L24="Grupo 4",F24/E45,L24="Grupo 5",F24/E46) -> 0 | I24: =IFS(L24="Grupo 0",0,L24="Grupo 1",M24/M42,L24="Grupo 2",M24/M43,L24="Grupo 3",M24/M44,L24="Grupo 4",M24/M45,L24="Grupo 5",M24/M46) -> 0 | J24: =IFS(L24="Grupo 0",0,L24="Grupo 1",K24/K42,L24="Grupo 2",K24/K43,L24="Grupo 3",K24/K44,L24="Grupo 4",K24/K45,L24="Grupo 5",K24/K46) -> 0 | K24: =IFS(L24="Grupo 0",0,L24="Grupo 1",(E42*I24-F24)*N24,L24="Grupo 2",(E43*I24-F24)*N24,L24="Grupo 3",(E44*I24-F24)*N24,L24="Grupo 4",(E45*I24-F24)*N24,L24="Grupo 5",(E46*I24-F24)*N24) -> 0 | L24: Grupo 0 | N24: =IF(I24<H24,0,1) -> 1 | O24: =IFS(L24="Grupo 0",0,L24="Grupo 1",J24*D42,L24="Grupo 2",J24*D43,L24="Grupo 3",J24*D44,L24="Grupo 4",J24*D45,L24="Grupo 5",J24*D46) -> 0
A25: 24 | C25: =F25*I46 -> 0 | F25: =D25*E25 -> 0 | G25: =IFS(L25="Grupo 0",0,L25="Grupo 1",F25/F42,L25="Grupo 2",F25/F43,L25="Grupo 3",F25/F44,L25="Grupo 4",F25/F45,L25="Grupo 5",F25/F46) -> 0 | H25: =IFS(L25="Grupo 0",0,L25="Grupo 1",F25/E42,L25="Grupo 2",F25/E43,L25="Grupo 3",F25/E44,L25="Grupo 4",F25/E45,L25="Grupo 5",F25/E46) -> 0 | I25: =IFS(L25="Grupo 0",0,L25="Grupo 1",M25/M42,L25="Grupo 2",M25/M43,L25="Grupo 3",M25/M44,L25="Grupo 4",M25/M45,L25="Grupo 5",M25/M46) -> 0 | J25: =IFS(L25="Grupo 0",0,L25="Grupo 1",K25/K42,L25="Grupo 2",K25/K43,L25="Grupo 3",K25/K44,L25="Grupo 4",K25/K45,L25="Grupo 5",K25/K46) -> 0 | K25: =IFS(L25="Grupo 0",0,L25="Grupo 1",(E42*I25-F25)*N25,L25="Grupo 2",(E43*I25-F25)*N25,L25="Grupo 3",(E44*I25-F25)*N25,L25="Grupo 4",(E45*I25-F25)*N25,L25="Grupo 5",(E46*I25-F25)*N25) -> 0 | L25: Grupo 0 | N25: =IF(I25<H25,0,1) -> 1 | O25: =IFS(L25="Grupo 0",0,L25="Grupo 1",J25*D42,L25="Grupo 2",J25*D43,L25="Grupo 3",J25*D44,L25="Grupo 4",J25*D45,L25="Grupo 5",J25*D46) -> 0
A26: 25 | C26: =F26*I46 -> 0 | F26: =D26*E26 -> 0 | G26: =IFS(L26="Grupo 0",0,L26="Grupo 1",F26/F42,L26="Grupo 2",F26/F43,L26="Grupo 3",F26/F44,L26="Grupo 4",F26/F45,L26="Grupo 5",F26/F46) -> 0 | H26: =IFS(L26="Grupo 0",0,L26="Grupo 1",F26/E42,L26="Grupo 2",F26/E43,L26="Grupo 3",F26/E44,L26="Grupo 4",F26/E45,L26="Grupo 5",F26/E46) -> 0 | I26: =IFS(L26="Grupo 0",0,L26="Grupo 1",M26/M42,L26="Grupo 2",M26/M43,L26="Grupo 3",M26/M44,L26="Grupo 4",M26/M45,L26="Grupo 5",M26/M46) -> 0 | J26: =IFS(L26="Grupo 0",0,L26="Grupo 1",K26/K42,L26="Grupo 2",K26/K43,L26="Grupo 3",K26/K44,L26="Grupo 4",K26/K45,L26="Grupo 5",K26/K46) -> 0 | K26: =IFS(L26="Grupo 0",0,L26="Grupo 1",(E42*I26-F26)*N26,L26="Grupo 2",(E43*I26-F26)*N26,L26="Grupo 3",(E44*I26-F26)*N26,L26="Grupo 4",(E45*I26-F26)*N26,L26="Grupo 5",(E46*I26-F26)*N26) -> 0 | L26: Grupo 0 | N26: =IF(I26<H26,0,1) -> 1 | O26: =IFS(L26="Grupo 0",0,L26="Grupo 1",J26*D42,L26="Grupo 2",J26*D43,L26="Grupo 3",J26*D44,L26="Grupo 4",J26*D45,L26="Grupo 5",J26*D46) -> 0
A27: 26 | C27: =F27*I46 -> 0 | F27: =D27*E27 -> 0 | G27: =IFS(L27="Grupo 0",0,L27="Grupo 1",F27/F42,L27="Grupo 2",F27/F43,L27="Grupo 3",F27/F44,L27="Grupo 4",F27/F45,L27="Grupo 5",F27/F46) -> 0 | H27: =IFS(L27="Grupo 0",0,L27="Grupo 1",F27/E42,L27="Grupo 2",F27/E43,L27="Grupo 3",F27/E44,L27="Grupo 4",F27/E45,L27="Grupo 5",F27/E46) -> 0 | I27: =IFS(L27="Grupo 0",0,L27="Grupo 1",M27/M42,L27="Grupo 2",M27/M43,L27="Grupo 3",M27/M44,L27="Grupo 4",M27/M45,L27="Grupo 5",M27/M46) -> 0 | J27: =IFS(L27="Grupo 0",0,L27="Grupo 1",K27/K42,L27="Grupo 2",K27/K43,L27="Grupo 3",K27/K44,L27="Grupo 4",K27/K45,L27="Grupo 5",K27/K46) -> 0 | K27: =IFS(L27="Grupo 0",0,L27="Grupo 1",(E42*I27-F27)*N27,L27="Grupo 2",(E43*I27-F27)*N27,L27="Grupo 3",(E44*I27-F27)*N27,L27="Grupo 4",(E45*I27-F27)*N27,L27="Grupo 5",(E46*I27-F27)*N27) -> 0 | L27: Grupo 0 | N27: =IF(I27<H27,0,1) -> 1 | O27: =IFS(L27="Grupo 0",0,L27="Grupo 1",J27*D42,L27="Grupo 2",J27*D43,L27="Grupo 3",J27*D44,L27="Grupo 4",J27*D45,L27="Grupo 5",J27*D46) -> 0
A28: 27 | C28: =F28*I46 -> 0 | F28: =D28*E28 -> 0 | G28: =IFS(L28="Grupo 0",0,L28="Grupo 1",F28/F42,L28="Grupo 2",F28/F43,L28="Grupo 3",F28/F44,L28="Grupo 4",F28/F45,L28="Grupo 5",F28/F46) -> 0 | H28: =IFS(L28="Grupo 0",0,L28="Grupo 1",F28/E42,L28="Grupo 2",F28/E43,L28="Grupo 3",F28/E44,L28="Grupo 4",F28/E45,L28="Grupo 5",F28/E46) -> 0 | I28: =IFS(L28="Grupo 0",0,L28="Grupo 1",M28/M42,L28="Grupo 2",M28/M43,L28="Grupo 3",M28/M44,L28="Grupo 4",M28/M45,L28="Grupo 5",M28/M46) -> 0 | J28: =IFS(L28="Grupo 0",0,L28="Grupo 1",K28/K42,L28="Grupo 2",K28/K43,L28="Grupo 3",K28/K44,L28="Grupo 4",K28/K45,L28="Grupo 5",K28/K46) -> 0 | K28: =IFS(L28="Grupo 0",0,L28="Grupo 1",(E42*I28-F28)*N28,L28="Grupo 2",(E43*I28-F28)*N28,L28="Grupo 3",(E44*I28-F28)*N28,L28="Grupo 4",(E45*I28-F28)*N28,L28="Grupo 5",(E46*I28-F28)*N28) -> 0 | L28: Grupo 0 | N28: =IF(I28<H28,0,1) -> 1 | O28: =IFS(L28="Grupo 0",0,L28="Grupo 1",J28*D42,L28="Grupo 2",J28*D43,L28="Grupo 3",J28*D44,L28="Grupo 4",J28*D45,L28="Grupo 5",J28*D46) -> 0
A29: 28 | C29: =F29*I46 -> 0 | F29: =D29*E29 -> 0 | G29: =IFS(L29="Grupo 0",0,L29="Grupo 1",F29/F42,L29="Grupo 2",F29/F43,L29="Grupo 3",F29/F44,L29="Grupo 4",F29/F45,L29="Grupo 5",F29/F46) -> 0 | H29: =IFS(L29="Grupo 0",0,L29="Grupo 1",F29/E42,L29="Grupo 2",F29/E43,L29="Grupo 3",F29/E44,L29="Grupo 4",F29/E45,L29="Grupo 5",F29/E46) -> 0 | I29: =IFS(L29="Grupo 0",0,L29="Grupo 1",M29/M42,L29="Grupo 2",M29/M43,L29="Grupo 3",M29/M44,L29="Grupo 4",M29/M45,L29="Grupo 5",M29/M46) -> 0 | J29: =IFS(L29="Grupo 0",0,L29="Grupo 1",K29/K42,L29="Grupo 2",K29/K43,L29="Grupo 3",K29/K44,L29="Grupo 4",K29/K45,L29="Grupo 5",K29/K46) -> 0 | K29: =IFS(L29="Grupo 0",0,L29="Grupo 1",(E42*I29-F29)*N29,L29="Grupo 2",(E43*I29-F29)*N29,L29="Grupo 3",(E44*I29-F29)*N29,L29="Grupo 4",(E45*I29-F29)*N29,L29="Grupo 5",(E46*I29-F29)*N29) -> 0 | L29: Grupo 0 | N29: =IF(I29<H29,0,1) -> 1 | O29: =IFS(L29="Grupo 0",0,L29="Grupo 1",J29*D42,L29="Grupo 2",J29*D43,L29="Grupo 3",J29*D44,L29="Grupo 4",J29*D45,L29="Grupo 5",J29*D46) -> 0
A30: 29 | C30: =F30*I46 -> 0 | F30: =D30*E30 -> 0 | G30: =IFS(L30="Grupo 0",0,L30="Grupo 1",F30/F42,L30="Grupo 2",F30/F43,L30="Grupo 3",F30/F44,L30="Grupo 4",F30/F45,L30="Grupo 5",F30/F46) -> 0 | H30: =IFS(L30="Grupo 0",0,L30="Grupo 1",F30/E42,L30="Grupo 2",F30/E43,L30="Grupo 3",F30/E44,L30="Grupo 4",F30/E45,L30="Grupo 5",F30/E46) -> 0 | I30: =IFS(L30="Grupo 0",0,L30="Grupo 1",M30/M42,L30="Grupo 2",M30/M43,L30="Grupo 3",M30/M44,L30="Grupo 4",M30/M45,L30="Grupo 5",M30/M46) -> 0 | J30: =IFS(L30="Grupo 0",0,L30="Grupo 1",K30/K42,L30="Grupo 2",K30/K43,L30="Grupo 3",K30/K44,L30="Grupo 4",K30/K45,L30="Grupo 5",K30/K46) -> 0 | K30: =IFS(L30="Grupo 0",0,L30="Grupo 1",(E42*I30-F30)*N30,L30="Grupo 2",(E43*I30-F30)*N30,L30="Grupo 3",(E44*I30-F30)*N30,L30="Grupo 4",(E45*I30-F30)*N30,L30="Grupo 5",(E46*I30-F30)*N30) -> 0 | L30: Grupo 0 | N30: =IF(I30<H30,0,1) -> 1 | O30: =IFS(L30="Grupo 0",0,L30="Grupo 1",J30*D42,L30="Grupo 2",J30*D43,L30="Grupo 3",J30*D44,L30="Grupo 4",J30*D45,L30="Grupo 5",J30*D46) -> 0
A31: 30 | C31: =F31*I46 -> 0 | F31: =D31*E31 -> 0 | G31: =IFS(L31="Grupo 0",0,L31="Grupo 1",F31/F42,L31="Grupo 2",F31/F43,L31="Grupo 3",F31/F44,L31="Grupo 4",F31/F45,L31="Grupo 5",F31/F46) -> 0 | H31: =IFS(L31="Grupo 0",0,L31="Grupo 1",F31/E42,L31="Grupo 2",F31/E43,L31="Grupo 3",F31/E44,L31="Grupo 4",F31/E45,L31="Grupo 5",F31/E46) -> 0 | I31: =IFS(L31="Grupo 0",0,L31="Grupo 1",M31/M42,L31="Grupo 2",M31/M43,L31="Grupo 3",M31/M44,L31="Grupo 4",M31/M45,L31="Grupo 5",M31/M46) -> 0 | J31: =IFS(L31="Grupo 0",0,L31="Grupo 1",K31/K42,L31="Grupo 2",K31/K43,L31="Grupo 3",K31/K44,L31="Grupo 4",K31/K45,L31="Grupo 5",K31/K46) -> 0 | K31: =IFS(L31="Grupo 0",0,L31="Grupo 1",(E42*I31-F31)*N31,L31="Grupo 2",(E43*I31-F31)*N31,L31="Grupo 3",(E44*I30-F31)*N31,L31="Grupo 4",(E45*I31-F31)*N31,L31="Grupo 5",(E46*I31-F31)*N31) -> 0 | L31: Grupo 0 | N31: =IF(I31<H31,0,1) -> 1 | O31: =IFS(L31="Grupo 0",0,L31="Grupo 1",J31*D42,L31="Grupo 2",J31*D43,L31="Grupo 3",J31*D44,L31="Grupo 4",J31*D45,L31="Grupo 5",J31*D46) -> 0
A32: 31 | C32: =F32*I46 -> 0 | F32: =D32*E32 -> 0 | G32: =IFS(L32="Grupo 0",0,L32="Grupo 1",F32/F42,L32="Grupo 2",F32/F43,L32="Grupo 3",F32/F44,L32="Grupo 4",F32/F45,L32="Grupo 5",F32/F46) -> 0 | H32: =IFS(L32="Grupo 0",0,L32="Grupo 1",F32/E42,L32="Grupo 2",F32/E43,L32="Grupo 3",F32/E44,L32="Grupo 4",F32/E45,L32="Grupo 5",F32/E46) -> 0 | I32: =IFS(L32="Grupo 0",0,L32="Grupo 1",M32/M42,L32="Grupo 2",M32/M43,L32="Grupo 3",M32/M44,L32="Grupo 4",M32/M45,L32="Grupo 5",M32/M46) -> 0 | J32: =IFS(L32="Grupo 0",0,L32="Grupo 1",K32/K42,L32="Grupo 2",K32/K43,L32="Grupo 3",K32/K44,L32="Grupo 4",K32/K45,L32="Grupo 5",K32/K46) -> 0 | K32: =IFS(L32="Grupo 0",0,L32="Grupo 1",(E42*I32-F32)*N32,L32="Grupo 2",(E43*I32-F32)*N32,L32="Grupo 3",(E44*I32-F32)*N32,L32="Grupo 4",(E45*I32-F32)*N32,L32="Grupo 5",(E46*I32-F32)*N32) -> 0 | L32: Grupo 0 | N32: =IF(I32<H32,0,1) -> 1 | O32: =IFS(L32="Grupo 0",0,L32="Grupo 1",J32*D42,L32="Grupo 2",J32*D43,L32="Grupo 3",J32*D44,L32="Grupo 4",J32*D45,L32="Grupo 5",J32*D46) -> 0
A33: 32 | C33: =F33*I46 -> 0 | F33: =D33*E33 -> 0 | G33: =IFS(L33="Grupo 0",0,L33="Grupo 1",F33/F42,L33="Grupo 2",F33/F43,L33="Grupo 3",F33/F44,L33="Grupo 4",F33/F45,L33="Grupo 5",F33/F46) -> 0 | H33: =IFS(L33="Grupo 0",0,L33="Grupo 1",F33/E42,L33="Grupo 2",F33/E43,L33="Grupo 3",F33/E44,L33="Grupo 4",F33/E45,L33="Grupo 5",F33/E46) -> 0 | I33: =IFS(L33="Grupo 0",0,L33="Grupo 1",M33/M42,L33="Grupo 2",M33/M43,L33="Grupo 3",M33/M44,L33="Grupo 4",M33/M45,L33="Grupo 5",M33/M46) -> 0 | J33: =IFS(L33="Grupo 0",0,L33="Grupo 1",K33/K42,L33="Grupo 2",K33/K43,L33="Grupo 3",K33/K44,L33="Grupo 4",K33/K45,L33="Grupo 5",K33/K46) -> 0 | K33: =IFS(L33="Grupo 0",0,L33="Grupo 1",(E42*I33-F33)*N33,L33="Grupo 2",(E43*I33-F33)*N33,L33="Grupo 3",(E44*I33-F33)*N33,L33="Grupo 4",(E45*I33-F33)*N33,L33="Grupo 5",(E46*I33-F33)*N33) -> 0 | L33: Grupo 0 | N33: =IF(I33<H33,0,1) -> 1 | O33: =IFS(L33="Grupo 0",0,L33="Grupo 1",J33*D42,L33="Grupo 2",J33*D43,L33="Grupo 3",J33*D44,L33="Grupo 4",J33*D45,L33="Grupo 5",J33*D46) -> 0
A34: 33 | C34: =F34*I46 -> 0 | F34: =D34*E34 -> 0 | G34: =IFS(L34="Grupo 0",0,L34="Grupo 1",F34/F42,L34="Grupo 2",F34/F43,L34="Grupo 3",F34/F44,L34="Grupo 4",F34/F45,L34="Grupo 5",F34/F46) -> 0 | H34: =IFS(L34="Grupo 0",0,L34="Grupo 1",F34/E42,L34="Grupo 2",F34/E43,L34="Grupo 3",F34/E44,L34="Grupo 4",F34/E45,L34="Grupo 5",F34/E46) -> 0 | I34: =IFS(L34="Grupo 0",0,L34="Grupo 1",M34/M42,L34="Grupo 2",M34/M43,L34="Grupo 3",M34/M44,L34="Grupo 4",M34/M45,L34="Grupo 5",M34/M46) -> 0 | J34: =IFS(L34="Grupo 0",0,L34="Grupo 1",K34/K42,L34="Grupo 2",K34/K43,L34="Grupo 3",K34/K44,L34="Grupo 4",K34/K45,L34="Grupo 5",K34/K46) -> 0 | K34: =IFS(L34="Grupo 0",0,L34="Grupo 1",(E42*I34-F34)*N34,L34="Grupo 2",(E43*I34-F34)*N34,L34="Grupo 3",(E44*I34-F34)*N34,L34="Grupo 4",(E45*I34-F34)*N34,L34="Grupo 5",(E46*I34-F34)*N34) -> 0 | L34: Grupo 0 | N34: =IF(I34<H34,0,1) -> 1 | O34: =IFS(L34="Grupo 0",0,L34="Grupo 1",J34*D42,L34="Grupo 2",J34*D43,L34="Grupo 3",J34*D44,L34="Grupo 4",J34*D45,L34="Grupo 5",J34*D46) -> 0
A35: 34 | C35: =F35*I46 -> 0 | F35: =D35*E35 -> 0 | G35: =IFS(L35="Grupo 0",0,L35="Grupo 1",F35/F42,L35="Grupo 2",F35/F43,L35="Grupo 3",F35/F44,L35="Grupo 4",F35/F45,L35="Grupo 5",F35/F46) -> 0 | H35: =IFS(L35="Grupo 0",0,L35="Grupo 1",F35/E42,L35="Grupo 2",F35/E43,L35="Grupo 3",F35/E44,L35="Grupo 4",F35/E45,L35="Grupo 5",F35/E46) -> 0 | I35: =IFS(L35="Grupo 0",0,L35="Grupo 1",M35/M42,L35="Grupo 2",M35/M43,L35="Grupo 3",M35/M44,L35="Grupo 4",M35/M45,L35="Grupo 5",M35/M46) -> 0 | J35: =IFS(L35="Grupo 0",0,L35="Grupo 1",K35/K42,L35="Grupo 2",K35/K43,L35="Grupo 3",K35/K44,L35="Grupo 4",K35/K45,L35="Grupo 5",K35/K46) -> 0 | K35: =IFS(L35="Grupo 0",0,L35="Grupo 1",(E42*I35-F35)*N35,L35="Grupo 2",(E43*I35-F35)*N35,L35="Grupo 3",(E44*I35-F35)*N35,L35="Grupo 4",(E45*I35-F35)*N35,L35="Grupo 5",(E46*I35-F35)*N35) -> 0 | L35: Grupo 0 | N35: =IF(I35<H35,0,1) -> 1 | O35: =IFS(L35="Grupo 0",0,L35="Grupo 1",J35*D42,L35="Grupo 2",J35*D43,L35="Grupo 3",J35*D44,L35="Grupo 4",J35*D45,L35="Grupo 5",J35*D46) -> 0
A36: 35 | C36: =F36*I46 -> 0 | F36: =D36*E36 -> 0 | G36: =IFS(L36="Grupo 0",0,L36="Grupo 1",F36/F42,L36="Grupo 2",F36/F43,L36="Grupo 3",F36/F44,L36="Grupo 4",F36/F45,L36="Grupo 5",F36/F46) -> 0 | H36: =IFS(L36="Grupo 0",0,L36="Grupo 1",F36/E42,L36="Grupo 2",F36/E43,L36="Grupo 3",F36/E44,L36="Grupo 4",F36/E45,L36="Grupo 5",F36/E46) -> 0 | I36: =IFS(L36="Grupo 0",0,L36="Grupo 1",M36/M42,L36="Grupo 2",M36/M43,L36="Grupo 3",M36/M44,L36="Grupo 4",M36/M45,L36="Grupo 5",M36/M46) -> 0 | J36: =IFS(L36="Grupo 0",0,L36="Grupo 1",K36/K42,L36="Grupo 2",K36/K43,L36="Grupo 3",K36/K44,L36="Grupo 4",K36/K45,L36="Grupo 5",K36/K46) -> 0 | K36: =IFS(L36="Grupo 0",0,L36="Grupo 1",(E42*I36-F36)*N36,L36="Grupo 2",(E43*I36-F36)*N36,L36="Grupo 3",(E44*I36-F36)*N36,L36="Grupo 4",(E45*I36-F36)*N36,L36="Grupo 5",(E46*I36-F36)*N36) -> 0 | L36: Grupo 0 | N36: =IF(I36<H36,0,1) -> 1 | O36: =IFS(L36="Grupo 0",0,L36="Grupo 1",J36*D42,L36="Grupo 2",J36*D43,L36="Grupo 3",J36*D44,L36="Grupo 4",J36*D45,L36="Grupo 5",J36*D46) -> 0
A37: 36 | C37: =F37*I46 -> 0 | F37: =D37*E37 -> 0 | G37: =IFS(L37="Grupo 0",0,L37="Grupo 1",F37/F42,L37="Grupo 2",F37/F43,L37="Grupo 3",F37/F44,L37="Grupo 4",F37/F45,L37="Grupo 5",F37/F46) -> 0 | H37: =IFS(L37="Grupo 0",0,L37="Grupo 1",F37/E42,L37="Grupo 2",F37/E43,L37="Grupo 3",F37/E44,L37="Grupo 4",F37/E45,L37="Grupo 5",F37/E46) -> 0 | I37: =IFS(L37="Grupo 0",0,L37="Grupo 1",M37/M42,L37="Grupo 2",M37/M43,L37="Grupo 3",M37/M44,L37="Grupo 4",M37/M45,L37="Grupo 5",M37/M46) -> 0 | J37: =IFS(L37="Grupo 0",0,L37="Grupo 1",K37/K42,L37="Grupo 2",K37/K43,L37="Grupo 3",K37/K44,L37="Grupo 4",K37/K45,L37="Grupo 5",K37/K46) -> 0 | K37: =IFS(L37="Grupo 0",0,L37="Grupo 1",(E42*I37-F37)*N37,L37="Grupo 2",(E43*I37-F37)*N37,L37="Grupo 3",(E44*I37-F37)*N37,L37="Grupo 4",(E45*I37-F37)*N37,L37="Grupo 5",(E46*I37-F37)*N37) -> 0 | L37: Grupo 0 | N37: =IF(I37<H37,0,1) -> 1 | O37: =IFS(L37="Grupo 0",0,L37="Grupo 1",J37*D42,L37="Grupo 2",J37*D43,L37="Grupo 3",J37*D44,L37="Grupo 4",J37*D45,L37="Grupo 5",J37*D46) -> 0
A38: 37 | C38: =F38*I46 -> 0 | F38: =D38*E38 -> 0 | G38: =IFS(L38="Grupo 0",0,L38="Grupo 1",F38/F42,L38="Grupo 2",F38/F43,L38="Grupo 3",F38/F44,L38="Grupo 4",F38/F45,L38="Grupo 5",F38/F46) -> 0 | H38: =IFS(L38="Grupo 0",0,L38="Grupo 1",F38/E42,L38="Grupo 2",F38/E43,L38="Grupo 3",F38/E44,L38="Grupo 4",F38/E45,L38="Grupo 5",F38/E46) -> 0 | I38: =IFS(L38="Grupo 0",0,L38="Grupo 1",M38/M42,L38="Grupo 2",M38/M43,L38="Grupo 3",M38/M44,L38="Grupo 4",M38/M45,L38="Grupo 5",M38/M46) -> 0 | J38: =IFS(L38="Grupo 0",0,L38="Grupo 1",K38/K42,L38="Grupo 2",K38/K43,L38="Grupo 3",K38/K44,L38="Grupo 4",K38/K45,L38="Grupo 5",K38/K46) -> 0 | K38: =IFS(L38="Grupo 0",0,L38="Grupo 1",(E42*I38-F38)*N38,L38="Grupo 2",(E43*I38-F38)*N38,L38="Grupo 3",(E44*I38-F38)*N38,L38="Grupo 4",(E45*I38-F38)*N38,L38="Grupo 5",(E46*I38-F38)*N38) -> 0 | L38: Grupo 0 | N38: =IF(I38<H38,0,1) -> 1 | O38: =IFS(L38="Grupo 0",0,L38="Grupo 1",J38*D42,L38="Grupo 2",J38*D43,L38="Grupo 3",J38*D44,L38="Grupo 4",J38*D45,L38="Grupo 5",J38*D46) -> 0
A39: 38 | C39: =F39*I46 -> 0 | F39: =D39*E39 -> 0 | G39: =IFS(L39="Grupo 0",0,L39="Grupo 1",F39/F42,L39="Grupo 2",F39/F43,L39="Grupo 3",F39/F44,L39="Grupo 4",F39/F45,L39="Grupo 5",F39/F46) -> 0 | H39: =IFS(L39="Grupo 0",0,L39="Grupo 1",F39/E42,L39="Grupo 2",F39/E43,L39="Grupo 3",F39/E44,L39="Grupo 4",F39/E45,L39="Grupo 5",F39/E46) -> 0 | I39: =IFS(L39="Grupo 0",0,L39="Grupo 1",M39/M42,L39="Grupo 2",M39/M43,L39="Grupo 3",M39/M44,L39="Grupo 4",M39/M45,L39="Grupo 5",M39/M46) -> 0 | J39: =IFS(L39="Grupo 0",0,L39="Grupo 1",K39/K42,L39="Grupo 2",K39/K43,L39="Grupo 3",K39/K44,L39="Grupo 4",K39/K45,L39="Grupo 5",K39/K46) -> 0 | K39: =IFS(L39="Grupo 0",0,L39="Grupo 1",(E42*I39-F39)*N39,L39="Grupo 2",(E43*I39-F39)*N39,L39="Grupo 3",(E44*I39-F39)*N39,L39="Grupo 4",(E45*I39-F39)*N39,L39="Grupo 5",(E46*I39-F39)*N39) -> 0 | L39: Grupo 0 | N39: =IF(I39<H39,0,1) -> 1 | O39: =IFS(L39="Grupo 0",0,L39="Grupo 1",J39*D42,L39="Grupo 2",J39*D43,L39="Grupo 3",J39*D44,L39="Grupo 4",J39*D45,L39="Grupo 5",J39*D46) -> 0
A40: 39 | C40: =F40*I46 -> 0 | F40: =D40*E40 -> 0 | G40: =IFS(L40="Grupo 0",0,L40="Grupo 1",F40/F42,L40="Grupo 2",F40/F43,L40="Grupo 3",F40/F44,L40="Grupo 4",F40/F45,L40="Grupo 5",F40/F46) -> 0 | H40: =IFS(L40="Grupo 0",0,L40="Grupo 1",F40/E42,L40="Grupo 2",F40/E43,L40="Grupo 3",F40/E44,L40="Grupo 4",F40/E45,L40="Grupo 5",F40/E46) -> 0 | I40: =IFS(L40="Grupo 0",0,L40="Grupo 1",M40/M42,L40="Grupo 2",M40/M43,L40="Grupo 3",M40/M44,L40="Grupo 4",M40/M45,L40="Grupo 5",M40/M46) -> 0 | J40: =IFS(L40="Grupo 0",0,L40="Grupo 1",K40/K42,L40="Grupo 2",K40/K43,L40="Grupo 3",K40/K44,L40="Grupo 4",K40/K45,L40="Grupo 5",K40/K46) -> 0 | K40: =IFS(L40="Grupo 0",0,L40="Grupo 1",(E42*I40-F40)*N40,L40="Grupo 2",(E43*I40-F40)*N40,L40="Grupo 3",(E44*I40-F40)*N40,L40="Grupo 4",(E45*I40-F40)*N40,L40="Grupo 5",(E46*I40-F40)*N40) -> 0 | L40: Grupo 0 | N40: =IF(I40<H40,0,1) -> 1 | O40: =IFS(L40="Grupo 0",0,L40="Grupo 1",J40*D42,L40="Grupo 2",J40*D43,L40="Grupo 3",J40*D44,L40="Grupo 4",J40*D45,L40="Grupo 5",J40*D46) -> 0
B41: TOTAL | C41: =SUM(B42:B46) -> 0.3 | D41: =F41+N1 -> 6353.7497 | E41: =SUM(E3:E40) -> 974.1 | F41: =SUM(F2:F40) -> 5537.4545 | I41: =SUM(I2:I40) -> 5 | J41: =SUM(J2:J40) -> 5 | K41: =SUM(K2:K40) -> 844.19111 | M41: =SUM(M2:M40) -> 153 | O41: =SUM(O2:O40) -> 816.29519 | P41: =SUM(P2:P40) -> 0.9412294
A42: G1 | B42: ='Distruibuição de aporte'!B8 -> 0.1 | C42: Ações US | D42: ='Distruibuição de aporte'!H8/I46 -> 274.72219 | E42: =D42+F42 -> 2091.4829 | F42: =SUMIF(L2:L40,"Grupo 1",F2:F40) -> 1816.7607 | G42: =SUMIF(L2:L40,"Grupo 1",G2:G40) -> 1 | H42: =F42*I46 -> 9563.2469 | K42: =SUMIF(L2:L40,"Grupo 1",K2:K40) -> 274.72219 | M42: =SUMIF(L2:L40,"Grupo 1",M2:M40) -> 30
A43: G2 | B43: ='Distruibuição de aporte'!B9 -> 0.05 | C43: REITs | D43: ='Distruibuição de aporte'!H9/I46 -> 141.25498 | E43: =D43+F43 -> 1006.5121 | F43: =SUMIF(L2:L40,"Grupo 2",F2:F40) -> 865.25717 | G43: =SUMIF(L2:L40,"Grupo 2",G2:G40) -> 1 | H43: =F43*I46 -> 4554.6272 | K43: =SUMIF(L2:L40,"Grupo 2",K2:K40) -> 141.25498 | M43: =SUMIF(L2:L40,"Grupo 2",M2:M40) -> 14
A44: G3 | B44: ='Distruibuição de aporte'!B10 -> 0.05 | C44: Renda fixa EUA | D44: ='Distruibuição de aporte'!H10/I46 -> 134.3854 | E44: =D44+F44 -> 1075.7204 | F44: =SUMIF(L2:L40,"Grupo 3",F2:F40) -> 941.33498 | G44: =SUMIF(L2:L40,"Grupo 3",G2:G40) -> 1 | H44: =F44*I46 -> 4955.0932 | K44: =SUMIF(L2:L40,"Grupo 3",K2:K40) -> 134.3854 | M44: =SUMIF(L2:L40,"Grupo 3",M2:M40) -> 32
A45: G4 | B45: ='Distruibuição de aporte'!B11 -> 0.05 | C45: Ações europa | D45: ='Distruibuição de aporte'!H11/I46 -> 136.12318 | E45: =D45+F45 -> 1058.213 | F45: =SUMIF(L2:L40,"Grupo 4",F2:F40) -> 922.08978 | G45: =SUMIF(L2:L40,"Grupo 4",G2:G40) -> 1 | H45: =F45*I46 -> 4853.7884 | K45: =SUMIF(L2:L40,"Grupo 4",K2:K40) -> 136.12318 | M45: =SUMIF(L2:L40,"Grupo 4",M2:M40) -> 16
A46: G5 | B46: ='Distruibuição de aporte'!B12 -> 0.05 | C46: Ações asia | D46: ='Distruibuição de aporte'!H12/I46 -> 129.80945 | E46: =D46+F46 -> 1121.8213 | F46: =SUMIF(L2:L40,"Grupo 5",F2:F40) -> 992.01187 | G46: =SUMIF(L2:L40,"Grupo 5",G2:G40) -> 1 | H46: =F46*I46 -> 5221.8513 | I46: =IFERROR(__xludf.DUMMYFUNCTION("GOOGLEFINANCE(""CURRENCY:USDBRL"")"),5.2639) -> 5.2639 | K46: =SUMIF(L2:L40,"Grupo 5",K2:K40) -> 157.70536 | M46: =SUMIF(L2:L40,"Grupo 5",M2:M40) -> 41 | O46: 1

Sheet Balanceamentos
B1: Ações | C1: BTLG11 | D1: XPLG11 | E1: HGLG11 | F1: GARE11 | G1: GGRC11 | H1: HGBS11 | I1: HSML11 | J1: HGRU11 | K1: SEQR11 | L1: TRXF11 | M1: RZAT11 | N1: KNCR11 | O1: KNSC11 | P1: MXRF11 | Q1: CVBI11 | R1: CPTI11 | S1: JURO11 | T1: RZTR11 | U1: SNAG11 | V1: SNEL11
A2: Pergunta para balanceamento das ações
A3: Nenhum ativo concentra a renda em mais que 20%? | C3: SIM | D3: NÃO
A4: Nenhum credor concentra a renda em mais que 20%? | C4: NÃO | D4: NÃO
A5: Tem 05 ou mais imóveis? | C5: NÃO | D5: NÃO | F5: SIM
A6: Tenho menos de 03 fundos dessa gestão na carteira? | C6: NÃO | D6: NÃO | F6: NÃO
A7: Tem liquidez diária maior que 1 milhão? | C7: NÃO | D7: NÃO | E7: SIM
A8: Tem mais de 05 anos de mercado? | C8: NÃO | D8: NÃO
A9: Tem distribuição de rendimentos consistente? | C9: SIM | D9: NÃO
A10: Os imoveis/ativos tem baixo risco associado? (localidade/credor/taxas) | C10: NÃO | D10: NÃO
A11: P/VP está menor que 01? | C11: SIM | D11: NÃO
A12: O Dividend Yield está dentro ou acima da média para fundos do mesmo tipo? | C12: SIM | D12: NÃO
C13: =COUNTIF(C3:C12,"SIM") -> 4 | D13: =COUNTIF(D3:D12,"SIM") -> 0 | E13: =COUNTIF(E3:E12,"SIM") -> 1 | F13: =COUNTIF(F3:F12,"SIM") -> 1 | G13: =COUNTIF(G3:G12,"SIM") -> 0 | H13: =COUNTIF(H3:H12,"SIM") -> 0 | I13: =COUNTIF(I3:I12,"SIM") -> 0 | J13: =COUNTIF(J3:J12,"SIM") -> 0 | ... CK13: =COUNTIF(CK3:CK12,"SIM") -> 0
A14: Total | B14: =SUMIF(C15:CK15,">=0",C15:CK15) -> 1 | C14: =-COUNTIF(C3:C12,"NÃO") -> -6 | D14: =-COUNTIF(D3:D12,"NÃO") -> -10 | E14: =-COUNTIF(E3:E12,"NÃO") -> 0 | F14: =-COUNTIF(F3:F12,"NÃO") -> -1 | G14: =-COUNTIF(G3:G12,"NÃO") -> 0 | H14: =-COUNTIF(H3:H12,"NÃO") -> 0 | I14: =-COUNTIF(I3:I12,"NÃO") -> 0 | J14: =-COUNTIF(J3:J12,"NÃO") -> 0 | ... CK14: =-COUNTIF(CK3:CK12,"NÃO") -> 0
A15: Soma | C15: =C13+C14 -> -2 | D15: =D13+D14 -> -10 | E15: =E13+E14 -> 1 | F15: =F13+F14 -> 0 | G15: =G13+G14 -> 0 | H15: =H13+H14 -> 0 | I15: =I13+I14 -> 0 | J15: =J13+J14 -> 0 | ... CK15: =CK13+CK14 -> 0
B22: Ações | C22: VALE3 | D22: BBAS3 | E22: PETR4 | F22: CSMG3 | G22: ISAE3 | H22: BBSE3 | I22: ABCB4 | J22: CXSE3 | K22: GOAU3 | L22: CMIG3 | M22: PRIO3 | N22: VBBR3 | O22: KLBN3 | P22: RANI3 | Q22: DEXP3 | R22: GGBR3 | S22: SAPR3 | T22: SBSP3 | U22: ALUP3 | V22: TAEE3 | W22: ENGI3 | X22: CLSC3 | Y22: ELET3 | Z22: TOTS3 | AA22: BMOB3 | AB22: TIMS3 | AC22: INTB3 | AD22: CMIN3 | AE22: ARML3 | AF22: VLID3 | AG22: GGPS3 | AH22: WEGE3 | AI22: KEPL3 | AJ22: JSLG3 | AK22: TGMA3 | AL22: PORT3 | AM22: ECOR3 | AN22: MOTV3 | AO22: CSUD3 | AP22: POMO3 | AQ22: FRAS3 | AR22: VAMO3 | AS22: RADL3 | AT22: PGMN3 | AU22: PFRM3 | AV22: FLRY3 | AW22: ODPV3 | AX22: RDOR3 | AY22: BLAU3 | AZ22: OFSA3 | BA22: AGRO3 | BB22: SOJA3 | BC22: JBSS3 | BD22: SMTO3 | BE22: MDIA3 | BF22: ABEV3 | BG22: GMAT3 | BH22: GRND3 | BI22: VULC3 | BJ22: VIVA3 | BK22: LEVE3 | BL22: CGRA3 | BM22: LREN3 | BN22: JHSF3 | BO22: LAVV3 | BP22: CURY3 | BQ22: EZTC3 | BR22: DIRR3 | BS22: SYNE3 | BT22: LOGG3 | BU22: PLPL3 | BV22: ITSA3 | BW22: BRAP3 | BX22: ITUB3 | BY22: BBDC3 | BZ22: SANB3 | CA22: BRSR3 | CB22: BEES3 | CC22: BPAC3 | CD22: BGIP3 | CE22: PSSA3 | CF22: WIZC3 | CG22: B3SA3 | CH22: TTEN3 | CI22: CAML3
A23: Pergunta para balanceamento das ações
A24: Tem mais de 30 anos de mercado? (fundação) | C24: SIM | D24: SIM | E24: SIM | F24: SIM | G24: SIM | H24: SIM | I24: SIM | J24: SIM | K24: SIM | L24: SIM | M24: NÃO | N24: SIM | O24: SIM | P24: SIM | Q24: SIM | R24: SIM | S24: SIM | T24: SIM | U24: SIM | V24: SIM | W24: SIM | X24: SIM | Y24: SIM | Z24: SIM | AA24: NÃO | AB24: SIM | AC24: SIM | AD24: NÃO | AE24: SIM | AF24: SIM | AG24: SIM | AH24: SIM | AI24: SIM | AJ24: SIM | AK24: SIM | AL24: SIM | AM24: SIM | AN24: NÃO | AO24: SIM | AP24: SIM | AQ24: SIM | AR24: NÃO | AS24: SIM | AT24: SIM | AU24: SIM | AV24: SIM | AW24: SIM | AX24: SIM | AY24: SIM | AZ24: SIM | BA24: NÃO | BB24: SIM | BC24: SIM | BD24: SIM | BE24: SIM | BF24: SIM | BG24: SIM | BH24: SIM | BI24: SIM | BJ24: SIM | BK24: SIM | BL24: SIM | BM24: SIM | BN24: SIM | BO24: NÃO | BP24: NÃO | BQ24: SIM | BR24: SIM | BS24: NÃO | BT24: NÃO | BU24: NÃO | BV24: SIM | BW24: NÃO | BX24: SIM | BY24: SIM | BZ24: SIM | CA24: SIM | CB24: SIM | CC24: SIM | CD24: SIM | CE24: SIM | CF24: NÃO | CG24: SIM | CH24: SIM | CI24: SIM
A25: É lider nacional ou mundial no setor em que atua? | C25: SIM | D25: SIM | E25: SIM | F25: NÃO | G25: SIM | H25: SIM | I25: NÃO | J25: NÃO | K25: NÃO | L25: NÃO | M25: NÃO | N25: SIM | O25: SIM | P25: NÃO | Q25: NÃO | R25: SIM | S25: NÃO | T25: SIM | U25: NÃO | V25: SIM | W25: NÃO | X25: NÃO | Y25: SIM | Z25: SIM | AA25: SIM | AB25: NÃO | AC25: SIM | AD25: SIM | AE25: SIM | AF25: SIM | AG25: SIM | AH25: SIM | AI25: SIM | AJ25: SIM | AK25: SIM | AL25: SIM | AM25: SIM | AN25: SIM | AO25: SIM | AP25: SIM | AQ25: SIM | AR25: SIM | AS25: SIM | AT25: NÃO | AU25: NÃO | AV25: SIM | AW25: SIM | AX25: SIM | AY25: SIM | AZ25: NÃO | BA25: SIM | BB25: SIM | BC25: SIM | BD25: SIM | BE25: SIM | BF25: SIM | BG25: NÃO | BH25: SIM | BI25: SIM | BJ25: SIM | BK25: SIM | BL25: NÃO | BM25: SIM | BN25: SIM | BO25: NÃO | BP25: SIM | BQ25: NÃO | BR25: SIM | BS25: NÃO | BT25: NÃO | BU25: SIM | BV25: SIM | BW25: SIM | BX25: SIM | BY25: NÃO | BZ25: NÃO | CA25: NÃO | CB25: NÃO | CC25: SIM | CD25: NÃO | CE25: SIM | CF25: SIM | CG25: SIM | CH25: NÃO | CI25: SIM
A26: O setor em que a empresa atua tem mais de 100 anos? | C26: SIM | D26: SIM | E26: SIM | F26: SIM | G26: SIM | H26: SIM | I26: SIM | J26: SIM | K26: SIM | L26: SIM | M26: SIM | N26: SIM | O26: SIM | P26: SIM | Q26: SIM | R26: SIM | S26: SIM | T26: SIM | U26: SIM | V26: SIM | W26: SIM | X26: SIM | Y26: SIM | Z26: NÃO | AA26: NÃO | AB26: NÃO | AC26: NÃO | AD26: SIM | AE26: NÃO | AF26: NÃO | AG26: NÃO | AH26: SIM | AI26: SIM | AJ26: SIM | AK26: SIM | AL26: SIM | AM26: SIM | AN26: SIM | AO26: NÃO | AP26: SIM | AQ26: SIM | AR26: NÃO | AS26: SIM | AT26: SIM | AU26: SIM | AV26: SIM | AW26: SIM | AX26: SIM | AY26: SIM | AZ26: SIM | BA26: SIM | BB26: SIM | BC26: SIM | BD26: SIM | BE26: SIM | BF26: SIM | BG26: SIM | BH26: SIM | BI26: SIM | BJ26: SIM | BK26: SIM | BL26: SIM | BM26: SIM | BN26: SIM | BO26: SIM | BP26: SIM | BQ26: SIM | BR26: SIM | BS26: SIM | BT26: SIM | BU26: SIM | BV26: SIM | BW26: SIM | BX26: SIM | BY26: SIM | BZ26: SIM | CA26: SIM | CB26: SIM | CC26: SIM | CD26: SIM | CE26: SIM | CF26: SIM | CG26: SIM | CH26: SIM | CI26: SIM
A27: A empresa é uma blue chip? (>R$ 10 bilhões de valor de mercado) | C27: SIM | D27: SIM | E27: SIM | F27: NÃO | G27: SIM | H27: SIM | I27: NÃO | J27: SIM | K27: NÃO | L27: SIM | M27: SIM | N27: SIM | O27: SIM | P27: NÃO | Q27: NÃO | R27: SIM | S27: NÃO | T27: SIM | U27: SIM | V27: SIM | W27: SIM | X27: NÃO | Y27: SIM | Z27: SIM | AA27: NÃO | AB27: SIM | AC27: NÃO | AD27: SIM | AE27: NÃO | AF27: NÃO | AG27: SIM | AH27: SIM | AI27: NÃO | AJ27: NÃO | AK27: NÃO | AL27: NÃO | AM27: NÃO | AN27: SIM | AO27: NÃO | AP27: NÃO | AQ27: NÃO | AR27: NÃO | AS27: SIM | AT27: NÃO | AU27: NÃO | AV27: NÃO | AW27: NÃO | AX27: SIM | AY27: NÃO | AZ27: NÃO | BA27: NÃO | BB27: SIM | BC27: SIM | BD27: NÃO | BE27: NÃO | BF27: SIM | BG27: SIM | BH27: NÃO | BI27: NÃO | BJ27: SIM | BK27: NÃO | BL27: NÃO | BM27: SIM | BN27: NÃO | BO27: NÃO | BP27: NÃO | BQ27: NÃO | BR27: NÃO | BS27: NÃO | BT27: NÃO | BU27: NÃO | BV27: SIM | BW27: NÃO | BX27: SIM | BY27: SIM | BZ27: SIM | CA27: NÃO | CB27: NÃO | CC27: SIM | CD27: NÃO | CE27: SIM | CF27: NÃO | CG27: SIM | CH27: NÃO | CI27: SIM
A28: ROE históricamente maior que 5% | C28: SIM | D28: SIM | E28: SIM | F28: SIM | G28: SIM | H28: SIM | I28: SIM | J28: SIM | K28: SIM | L28: SIM | M28: SIM | N28: SIM | O28: SIM | P28: SIM | Q28: SIM | R28: SIM | S28: SIM | T28: SIM | U28: SIM | V28: SIM | W28: SIM | X28: SIM | Y28: SIM | Z28: SIM | AA28: SIM | AB28: SIM | AC28: SIM | AD28: SIM | AE28: SIM | AF28: SIM | AG28: SIM | AH28: SIM | AI28: SIM | AJ28: SIM | AK28: SIM | AL28: SIM | AM28: SIM | AN28: SIM | AO28: SIM | AP28: SIM | AQ28: SIM | AR28: SIM | AS28: SIM | AT28: NÃO | AU28: SIM | AV28: SIM | AW28: SIM | AX28: SIM | AY28: SIM | AZ28: SIM | BA28: SIM | BB28: SIM | BC28: SIM | BD28: SIM | BE28: SIM | BF28: SIM | BG28: SIM | BH28: SIM | BI28: SIM | BJ28: NÃO | BK28: SIM | BL28: SIM | BM28: SIM | BN28: SIM | BO28: SIM | BP28: SIM | BQ28: SIM | BR28: SIM | BS28: SIM | BT28: SIM | BU28: SIM | BV28: SIM | BW28: SIM | BX28: SIM | BY28: SIM | BZ28: SIM | CA28: SIM | CB28: SIM | CC28: SIM | CD28: SIM | CE28: SIM | CF28: SIM | CG28: SIM | CH28: SIM | CI28: SIM
A29: Tem crescimento consistente no patrimonio nos últimos 5 anos? | C29: SIM | D29: SIM | E29: SIM | F29: SIM | G29: SIM | H29: SIM | I29: SIM | J29: SIM | K29: SIM | L29: SIM | M29: SIM | N29: SIM | O29: SIM | P29: SIM | Q29: SIM | R29: SIM | S29: SIM | T29: SIM | U29: SIM | V29: SIM | W29: SIM | X29: SIM | Y29: SIM | Z29: SIM | AA29: SIM | AB29: SIM | AC29: SIM | AD29: NÃO | AE29: SIM | AF29: SIM | AG29: SIM | AH29: SIM | AI29: SIM | AJ29: SIM | AK29: SIM | AL29: SIM | AM29: SIM | AN29: SIM | AO29: SIM | AP29: SIM | AQ29: SIM | AR29: SIM | AS29: SIM | AT29: SIM | AU29: SIM | AV29: SIM | AW29: SIM | AX29: SIM | AY29: SIM | AZ29: SIM | BA29: SIM | BB29: SIM | BC29: SIM | BD29: SIM | BE29: SIM | BF29: SIM | BG29: SIM | BH29: SIM | BI29: SIM | BJ29: SIM | BK29: SIM | BL29: SIM | BM29: SIM | BN29: SIM | BO29: SIM | BP29: SIM | BQ29: SIM | BR29: SIM | BS29: SIM | BT29: SIM | BU29: SIM | BV29: SIM | BW29: NÃO | BX29: SIM | BY29: SIM | BZ29: SIM | CA29: SIM | CB29: SIM | CC29: SIM | CD29: SIM | CE29: SIM | CF29: SIM | CG29: SIM | CH29: SIM | CI29: SIM
A30: Tem histórico de distribuição de dividendos? | C30: SIM | D30: SIM | E30: SIM | F30: SIM | G30: SIM | H30: SIM | I30: SIM | J30: SIM | K30: SIM | L30: SIM | M30: NÃO | N30: SIM | O30: SIM | P30: SIM | Q30: SIM | R30: SIM | S30: SIM | T30: SIM | U30: SIM | V30: SIM | W30: SIM | X30: SIM | Y30: SIM | Z30: SIM | AA30: SIM | AB30: SIM | AC30: SIM | AD30: SIM | AE30: NÃO | AF30: SIM | AG30: SIM | AH30: SIM | AI30: SIM | AJ30: SIM | AK30: SIM | AL30: SIM | AM30: SIM | AN30: SIM | AO30: SIM | AP30: SIM | AQ30: SIM | AR30: SIM | AS30: SIM | AT30: SIM | AU30: SIM | AV30: SIM | AW30: SIM | AX30: SIM | AY30: SIM | AZ30: SIM | BA30: SIM | BB30: SIM | BC30: SIM | BD30: SIM | BE30: SIM | BF30: SIM | BG30: SIM | BH30: SIM | BI30: SIM | BJ30: SIM | BK30: SIM | BL30: SIM | BM30: SIM | BN30: NÃO | BO30: SIM | BP30: SIM | BQ30: SIM | BR30: SIM | BS30: SIM | BT30: SIM | BU30: SIM | BV30: SIM | BW30: SIM | BX30: SIM | BY30: SIM | BZ30: SIM | CA30: SIM | CB30: SIM | CC30: SIM | CD30: SIM | CE30: SIM | CF30: SIM | CG30: SIM | CH30: SIM | CI30: SIM
A31: A empresa investe amplamente em pesquisa e inovação? | C31: SIM | D31: SIM | E31: SIM | F31: NÃO | G31: NÃO | H31: SIM | I31: SIM | J31: NÃO | K31: NÃO | L31: SIM | M31: SIM | N31: NÃO | O31: SIM | P31: SIM | Q31: SIM | R31: NÃO | S31: NÃO | T31: NÃO | U31: NÃO | V31: NÃO | W31: SIM | X31: NÃO | Y31: NÃO | Z31: SIM | AA31: SIM | AB31: SIM | AC31: SIM | AD31: NÃO | AE31: NÃO | AF31: SIM | AG31: NÃO | AH31: SIM | AI31: SIM | AJ31: NÃO | AK31: NÃO | AL31: NÃO | AM31: NÃO | AN31: NÃO | AO31: SIM | AP31: SIM | AQ31: SIM | AR31: SIM | AS31: NÃO | AT31: NÃO | AU31: NÃO | AV31: SIM | AW31: NÃO | AX31: SIM | AY31: SIM | AZ31: SIM | BA31: NÃO | BB31: NÃO | BC31: NÃO | BD31: NÃO | BE31: NÃO | BF31: NÃO | BG31: NÃO | BH31: SIM | BI31: SIM | BJ31: NÃO | BK31: SIM | BL31: NÃO | BM31: NÃO | BN31: NÃO | BO31: NÃO | BP31: NÃO | BQ31: NÃO | BR31: NÃO | BS31: NÃO | BT31: NÃO | BU31: NÃO | BV31: NÃO | BW31: NÃO | BX31: SIM | BY31: SIM | BZ31: SIM | CA31: NÃO | CB31: NÃO | CC31: SIM | CD31: NÃO | CE31: SIM | CF31: NÃO | CG31: SIM | CH31: NÃO | CI31: NÃO
A32: Apresenta lucros consistentes? | C32: SIM | D32: SIM | E32: SIM | F32: SIM | G32: SIM | H32: SIM | I32: SIM | J32: SIM | K32: SIM | L32: SIM | M32: SIM | N32: SIM | O32: SIM | P32: SIM | Q32: SIM | R32: SIM | S32: SIM | T32: NÃO | U32: SIM | V32: SIM | W32: SIM | X32: SIM | Y32: SIM | Z32: SIM | AA32: SIM | AB32: SIM | AC32: SIM | AD32: SIM | AE32: SIM | AF32: SIM | AG32: SIM | AH32: SIM | AI32: SIM | AJ32: SIM | AK32: SIM | AL32: SIM | AM32: SIM | AN32: SIM | AO32: SIM | AP32: SIM | AQ32: SIM | AR32: SIM | AS32: SIM | AT32: NÃO | AU32: NÃO | AV32: SIM | AW32: SIM | AX32: SIM | AY32: SIM | AZ32: NÃO | BA32: NÃO | BB32: NÃO | BC32: NÃO | BD32: SIM | BE32: NÃO | BF32: SIM | BG32: SIM | BH32: SIM | BI32: SIM | BJ32: SIM | BK32: SIM | BL32: SIM | BM32: NÃO | BN32: NÃO | BO32: SIM | BP32: SIM | BQ32: SIM | BR32: SIM | BS32: SIM | BT32: SIM | BU32: SIM | BV32: SIM | BW32: NÃO | BX32: SIM | BY32: NÃO | BZ32: NÃO | CA32: NÃO | CB32: SIM | CC32: SIM | CD32: NÃO | CE32: SIM | CF32: SIM | CG32: SIM | CH32: SIM | CI32: SIM
A33: Tem liquidez maior que R$ 2 milhões/dia? | C33: SIM | D33: SIM | E33: SIM | F33: SIM | G33: SIM | H33: SIM | I33: SIM | J33: SIM | K33: SIM | L33: SIM | M33: SIM | N33: SIM | O33: SIM | P33: SIM | Q33: SIM | R33: SIM | S33: SIM | T33: SIM | U33: SIM | V33: SIM | W33: SIM | X33: NÃO | Y33: SIM | Z33: SIM | AA33: SIM | AB33: SIM | AC33: SIM | AD33: SIM | AE33: SIM | AF33: SIM | AG33: SIM | AH33: SIM | AI33: SIM | AJ33: SIM | AK33: SIM | AL33: SIM | AM33: SIM | AN33: SIM | AO33: SIM | AP33: SIM | AQ33: SIM | AR33: SIM | AS33: SIM | AT33: SIM | AU33: SIM | AV33: SIM | AW33: SIM | AX33: SIM | AY33: SIM | AZ33: SIM | BA33: SIM | BB33: SIM | BC33: SIM | BD33: SIM | BE33: SIM | BF33: SIM | BG33: SIM | BH33: SIM | BI33: SIM | BJ33: SIM | BK33: SIM | BL33: SIM | BM33: SIM | BN33: SIM | BO33: SIM | BP33: SIM | BQ33: SIM | BR33: SIM | BS33: SIM | BT33: SIM | BU33: SIM | BV33: SIM | BW33: SIM | BX33: SIM | BY33: SIM | BZ33: SIM | CA33: SIM | CB33: SIM | CC33: SIM | CD33: SIM | CE33: SIM | CF33: SIM | CG33: SIM | CH33: SIM | CI33: SIM
A34: A empresa tem uma boa gestão? | C34: SIM | D34: SIM | E34: NÃO | F34: SIM | G34: SIM | H34: SIM | I34: SIM | J34: SIM | K34: SIM | L34: SIM | M34: SIM | N34: SIM | O34: SIM | P34: SIM | Q34: NÃO | R34: SIM | S34: SIM | T34: SIM | U34: SIM | V34: SIM | W34: SIM | X34: NÃO | Y34: SIM | Z34: SIM | AA34: SIM | AB34: SIM | AC34: SIM | AD34: SIM | AE34: SIM | AF34: SIM | AG34: SIM | AH34: SIM | AI34: SIM | AJ34: SIM | AK34: SIM | AL34: SIM | AM34: SIM | AN34: SIM | AO34: NÃO | AP34: SIM | AQ34: SIM | AR34: SIM | AS34: SIM | AT34: SIM | AU34: SIM | AV34: SIM | AW34: SIM | AX34: SIM | AY34: SIM | AZ34: NÃO | BA34: SIM | BB34: SIM | BC34: SIM | BD34: SIM | BE34: SIM | BF34: SIM | BG34: SIM | BH34: NÃO | BI34: SIM | BJ34: SIM | BK34: SIM | BL34: NÃO | BM34: SIM | BN34: SIM | BO34: SIM | BP34: SIM | BQ34: SIM | BR34: SIM | BS34: SIM | BT34: SIM | BU34: SIM | BV34: SIM | BW34: SIM | BX34: SIM | BY34: SIM | BZ34: SIM | CA34: SIM | CB34: NÃO | CC34: SIM | CD34: NÃO | CE34: SIM | CF34: NÃO | CG34: SIM | CH34: SIM | CI34: SIM
C35: =COUNTIF(C24:C34,"SIM") -> 11 | D35: =COUNTIF(D24:D34,"SIM") -> 11 | E35: =COUNTIF(E24:E34,"SIM") -> 10 | F35: =COUNTIF(F24:F34,"SIM") -> 8 | G35: =COUNTIF(G24:G34,"SIM") -> 10 | H35: =COUNTIF(H24:H34,"SIM") -> 11 | I35: =COUNTIF(I24:I34,"SIM") -> 9 | J35: =COUNTIF(J24:J34,"SIM") -> 9 | ... CK35: =COUNTIF(CK24:CK34,"SIM") -> 0
A36: Total | B36: =SUMIF(C37:CK37,">=0",C37:CK37) -> 575 | C36: =-COUNTIF(C24:C34,"NÃO") -> 0 | D36: =-COUNTIF(D24:D34,"NÃO") -> 0 | E36: =-COUNTIF(E24:E34,"NÃO") -> -1 | F36: =-COUNTIF(F24:F34,"NÃO") -> -3 | G36: =-COUNTIF(G24:G34,"NÃO") -> -1 | H36: =-COUNTIF(H24:H34,"NÃO") -> 0 | I36: =-COUNTIF(I24:I34,"NÃO") -> -2 | J36: =-COUNTIF(J24:J34,"NÃO") -> -2 | ... CK36: =-COUNTIF(CK24:CK34,"NÃO") -> 0
A37: Soma | C37: =C35+C36 -> 11 | D37: =D35+D36 -> 11 | E37: =E35+E36 -> 9 | F37: =F35+F36 -> 5 | G37: =G35+G36 -> 9 | H37: =H35+H36 -> 11 | I37: =I35+I36 -> 7 | J37: =J35+J36 -> 7 | ... CK37: =CK35+CK36 -> 0
